Workbook
Name Slicer_Customer_Name: #N/A
Name Slicer_Machine_Code: #N/A
Name Slicer_Machine_Name: #N/A
Name Slicer_Machine_Name1: #N/A
Name Slicer_Staff_Code: #N/A

Sheet 01-Apr
A1: Production Output
A2: Filter: Date Completed: 01/04/25
A4: Work Order No. | B4: Work Order Line No. | C4: WO Journal Line No. | D4: Add Date | E4: Add User | F4: Add Time | G4: Material Batch No. | H4: Die Cut | I4: Process No. | J4: Posted | K4: Machine Code | L4: Staff Code | M4: No. of Press | N4: Date Started | O4: Time Started | P4: Date Completed | Q4: Time Completed | R4: No. of Ups | S4: Printed Quantity | T4: Journal Type | U4: Item Code | V4: Quantity | W4: QC Approved Quantity | X4: Rejected Quantity | Y4: Roll | Z4: Length | AA4: Width | AB4: Length UOM | AC4: Width UOM | AD4: RM Quantity | AE4: Material Code | AF4: Variant Code | AG4: Request Delivery Date | AH4: Non QC Record | AI4: Link to Line No. | AJ4: Related | AK4: Expire Date | AL4: Label Remark | AM4: Customer Part Number | AN4: Customer Code | AO4: ddmm | AP4: Label Packing Quantity 1 | AQ4: Label Quantity 1 | AR4: Label Packing Quantity 2 | AS4: Label Quantity 2 | AT4: Label Packing Quantity 3 | AU4: Label Quantity 3 | AV4: UOM for Label Printing | AW4: QC Inspector | AX4: Summarised Period | AY4: Summarised | AZ4: Posted Work Order No. | BA4: Colour | BB4: Currency | BC4: Ref Customer | BD4: Group | BE4: PO | BF4: Source Doc. No.
A5: W0680449 | B5: 10000 | C5: 10000 | D5: 45786 | E5: 502LAUGH | F5: 9:26:40 am | G5: 2321164 | H5: DC03278 | I5: 1 | J5: No | K5: 88 | L5: PP24 | M5: 3500 | P5: 45748 | R5: 1 | S5: 3500 | T5: PE | U5: CE-1070129715-010001 | V5: 0 | W5: 0 | X5: 0 | Y5: 0 | Z5: 0 | AA5: 0 | AD5: 0 | AH5: No | AI5: 0 | AJ5: No | AM5: CE-1070129715-01 | AN5: C03043 | AP5: 0 | AQ5: 0 | AR5: 0 | AS5: 0 | AT5: 0 | AU5: 0 | AY5: No | BC5: C03043 | BF5: S0359242
A6: W0682349 | B6: 10000 | C6: 10000 | D6: 45751 | E6: 502LAUGH | F6: 5:16:20 pm | G6: 10620258022 | H6: FDC30934 | I6: 1 | J6: No | K6: 79 | L6: PM16 | M6: 200 | P6: 45748 | R6: 36 | S6: 7200 | T6: PE | U6: CZ633-800050001 | V6: 0 | W6: 0 | X6: 0 | Y6: 0 | Z6: 0 | AA6: 0 | AD6: 0 | AH6: No | AI6: 0 | AJ6: No | AM6: CZ633-80005 | AN6: H08031-JIM | AP6: 0 | AQ6: 0 | AR6: 0 | AS6: 0 | AT6: 0 | AU6: 0 | AY6: No | BC6: H08031-JIM | BF6: S0361845
A7: W0682425 | B7: 10000 | C7: 10000 | D7: 45751 | E7: 502LAUGH | F7: 5:15:26 pm | G7: 10620258022 | H7: FDC30934 | I7: 1 | J7: No | K7: 79 | L7: PM16 | M7: 167 | P7: 45748 | R7: 36 | S7: 6012 | T7: PE | U7: CZ635-800050001 | V7: 0 | W7: 0 | X7: 0 | Y7: 0 | Z7: 0 | AA7: 0 | AD7: 0 | AH7: No | AI7: 0 | AJ7: No | AM7: CZ635-80005 | AN7: H08031-JIM | AP7: 0 | AQ7: 0 | AR7: 0 | AS7: 0 | AT7: 0 | AU7: 0 | AY7: No | BC7: H08031-JIM | BF7: S0361902
A8: W0670634 | B8: 10000 | C8: 40000 | D8: 45748 | E8: 502LAUGH | F8: 5:42:25 pm | G8: D005H7770 | I8: 1 | J8: Yes | K8: 73 | L8: PM59 | M8: 3667 | P8: 45748 | R8: 30 | S8: 110010 | T8: PE | U8: R390-411 REV1.00001 | V8: 0 | W8: 104761 | X8: 5249 | Y8: 0 | Z8: 0 | AA8: 0 | AD8: 0 | AM8: R390-411 REV1.0 | AN8: R18131-MEIBAN MIC-M | AP8: 0 | AQ8: 0 | AR8: 0 | AS8: 0 | AT8: 0 | AU8: 0 | AY8: No | AZ8: W664003 | BA8: 0 | BC8: R18131-MEIBAN MIC-M | BF8: S0348898
A9: W0670634 | B9: 10000 | C9: 50000 | D9: 45748 | E9: 502LAUGH | F9: 5:42:25 pm | G9: D005H7770 | I9: 2 | J9: Yes | K9: 73 | L9: PM59 | M9: 3334 | P9: 45748 | R9: 30 | S9: 100020 | T9: PE | U9: R390-411 REV1.00001 | V9: 0 | W9: 100010 | X9: 10 | Y9: 0 | Z9: 0 | AA9: 0 | AD9: 0 | AM9: R390-411 REV1.0 | AN9: R18131-MEIBAN MIC-M | AP9: 0 | AQ9: 0 | AR9: 0 | AS9: 0 | AT9: 0 | AU9: 0 | AY9: No | AZ9: W664003 | BA9: 0 | BC9: R18131-MEIBAN MIC-M | BF9: S0348898
A10: W0675399 | B10: 10000 | C10: 30000 | D10: 45751 | E10: 502LAUGH | F10: 0.44092593 | G10: 10639931053/10639931059/10639931056/10639931055 | I10: 2 | J10: Yes | K10: 77 | L10: PM74 | M10: 29723 | P10: 45748 | R10: 36 | S10: 1070028 | T10: PE | U10: 5180-0100-BH2120001 | V10: 0 | W10: 1000000 | X10: 70028 | Y10: 0 | Z10: 0 | AA10: 0 | AD10: 0 | AM10: 5180-0100-BH212 | AN10: H08031-JIM | AP10: 0 | AQ10: 0 | AR10: 0 | AS10: 0 | AT10: 0 | AU10: 0 | AY10: No | AZ10: W664068 | BA10: 0 | BC10: H08031-JIM | BF10: S0353202
A11: W0679222 | B11: 10000 | C11: 10000 | D11: 45749 | E11: 502LAUGH | F11: 3:35:20 pm | G11: J00TP9191/J00WA7110 | I11: 1 | J11: Yes | K11: 111 | L11: PM46 | M11: 24375 | P11: 45748 | R11: 8 | S11: 195000 | T11: PE | U11: Z512 REV 6.00001 | V11: 0 | W11: 195000 | X11: 0 | Y11: 0 | Z11: 0 | AA11: 0 | AD11: 0 | AM11: Z512 REV 8.0 | AN11: R18131 | AP11: 0 | AQ11: 0 | AR11: 0 | AS11: 0 | AT11: 0 | AU11: 0 | AY11: No | AZ11: W664076 | BA11: 0 | BC11: R18131 | BF11: S0357874
A12: W0680426 | B12: 10000 | C12: 10000 | D12: 45754 | E12: 502LAUGH | F12: 9:01:59 am | G12: 1010831/80117500/XHX24911A1407/XHX2412190201/WO2024/5284 | I12: 1 | J12: Yes | K12: 103 | L12: PM47 | M12: 41875 | P12: 45748 | R12: 8 | S12: 335000 | T12: PE | U12: MT273730001 | V12: 0 | W12: 335000 | X12: 0 | Y12: 0 | Z12: 0 | AA12: 0 | AD12: 0 | AM12: MT27373 | AN12: Z26002 | AP12: 0 | AQ12: 0 | AR12: 0 | AS12: 0 | AT12: 0 | AU12: 0 | AY12: No | AZ12: W664503 | BA12: 0 | BC12: Z26002 | BF12: S0359228
A13: W0680426 | B13: 10000 | C13: 20000 | D13: 45754 | E13: 502LAUGH | F13: 9:01:59 am | G13: 1010831/80117500/XHX24911A1407/XHX2412190201/WO2024/5284 | I13: 1 | J13: Yes | K13: 103N | L13: PM41 | M13: 48125 | P13: 45748 | R13: 8 | S13: 385000 | T13: PE | U13: MT273730001 | V13: 0 | W13: 385000 | X13: 0 | Y13: 0 | Z13: 0 | AA13: 0 | AD13: 0 | AM13: MT27373 | AN13: Z26002 | AP13: 0 | AQ13: 0 | AR13: 0 | AS13: 0 | AT13: 0 | AU13: 0 | AY13: No | AZ13: W664503 | BA13: 0 | BC13: Z26002 | BF13: S0359228
A14: W0680873 | B14: 10000 | C14: 10000 | D14: 45750 | E14: 502LAUGH | F14: 0.4421875 | G14: 502200327 | I14: 1 | J14: Yes | K14: 59 | L14: PS74 | M14: 32000 | P14: 45748 | R14: 18 | S14: 576000 | T14: PE | U14: 7062430001 | V14: 0 | W14: 552000 | X14: 24000 | Y14: 0 | Z14: 0 | AA14: 0 | AD14: 0 | AM14: 706243 INDEX07 | AN14: V22000-DE | AP14: 0 | AQ14: 0 | AR14: 0 | AS14: 0 | AT14: 0 | AU14: 0 | AY14: No | AZ14: W665408 | BA14: 0 | BC14: V22000-DE | BF14: S0360724
A15: W0680948 | B15: 10000 | C15: 10000 | D15: 45749 | E15: 502LAUGH | F15: 8:32:31 am | G15: 3082510U9/4032711U5 | I15: 1 | J15: Yes | K15: 61 | L15: PM68 | M15: 500 | P15: 45748 | R15: 1 | S15: 500 | T15: PE | U15: 701684070001 | V15: 0 | W15: 500 | X15: 0 | Y15: 0 | Z15: 0 | AA15: 0 | AD15: 0 | AM15: 70168407 | AN15: P16186 | AP15: 0 | AQ15: 0 | AR15: 0 | AS15: 0 | AT15: 0 | AU15: 0 | AY15: No | AZ15: W663620 | BA15: 0 | BC15: P16186 | BF15: S0360882
A16: W0681067 | B16: 10000 | C16: 10000 | D16: 45749 | E16: 502LAUGH | F16: 8:35:58 am | G16: 4177S1/3830U7060 | I16: 1 | J16: Yes | K16: 78 | L16: PM84 | M16: 1000 | P16: 45748 | R16: 3 | S16: 3000 | T16: PE | U16: 4.4017009e+17 | V16: 0 | W16: 3000 | X16: 0 | Y16: 0 | Z16: 0 | AA16: 0 | AD16: 0 | AM16: 44017008600402 | AN16: T20096 | AP16: 0 | AQ16: 0 | AR16: 0 | AS16: 0 | AT16: 0 | AU16: 0 | AY16: No | AZ16: W663637 | BA16: 0 | BC16: T20096 | BF16: S0360941
A17: W0681280 | B17: 10000 | C17: 40000 | D17: 45749 | E17: 502LAUGH | F17: 8:35:14 am | G17: L5114U8024/405172625 | I17: 2 | J17: Yes | K17: 60 | L17: PM30 | M17: 750 | P17: 45748 | R17: 2 | S17: 1500 | T17: PE | U17: TSMC00350020001 | V17: 0 | W17: 429 | X17: 1071 | Y17: 0 | Z17: 0 | AA17: 0 | AD17: 0 | AM17: TSMC0035002 | AN17: T20104 | AP17: 0 | AQ17: 0 | AR17: 0 | AS17: 0 | AT17: 0 | AU17: 0 | AY17: No | AZ17: W663663 | BA17: 0 | BC17: T20104 | BF17: S0361067
A18: W0681379 | B18: 10000 | C18: 10000 | D18: 45748 | E18: 502LAUGH | F18: 3:51:58 pm | G18: BZA050-02 | I18: 1 | J18: Yes | K18: 46 | L18: PS66 | M18: 3000 | P18: 45748 | R18: 1 | S18: 3000 | T18: PE | U18: IMK-50001 | V18: 0 | W18: 3000 | X18: 0 | Y18: 0 | Z18: 0 | AA18: 0 | AD18: 0 | AM18: IMK-5 | AN18: G07075 | AP18: 0 | AQ18: 0 | AR18: 0 | AS18: 0 | AT18: 0 | AU18: 0 | AY18: No | AZ18: W663684 | BA18: 0 | BC18: G07075 | BF18: S0361130
A19: W0681513 | B19: 10000 | C19: 20000 | D19: 45749 | E19: 502LAUGH | F19: 8:35:14 am | G19: M0BTQ4850 | I19: 1 | J19: Yes | K19: 94 | L19: PM09 | M19: 10000 | P19: 45748 | R19: 4 | S19: 40000 | T19: PE | U19: L001-773057-00000007 | V19: 0 | W19: 40000 | X19: 0 | Y19: 0 | Z19: 0 | AA19: 0 | AD19: 0 | AM19: L001-773057-000007CM | AN19: W23041-TH | AP19: 0 | AQ19: 0 | AR19: 0 | AS19: 0 | AT19: 0 | AU19: 0 | AY19: No | AZ19: W664539 | BA19: 0 | BC19: W23041-TH | BF19: H0064786
A20: W0681514 | B20: 10000 | C20: 10000 | D20: 45749 | E20: 502LAUGH | F20: 9:46:52 am | G20: M0BTQ4850 | I20: 1 | J20: Yes | K20: 94 | L20: PM09 | M20: 10000 | P20: 45748 | R20: 4 | S20: 40000 | T20: PE | U20: L001-773057-00000007 | V20: 0 | W20: 40000 | X20: 0 | Y20: 0 | Z20: 0 | AA20: 0 | AD20: 0 | AM20: L001-773057-000007CM | AN20: W23041-TH | AP20: 0 | AQ20: 0 | AR20: 0 | AS20: 0 | AT20: 0 | AU20: 0 | AY20: No | AZ20: W664987 | BA20: 0 | BC20: W23041-TH | BF20: H0064787
A21: W0681678 | B21: 10000 | C21: 20000 | D21: 45749 | E21: 502LAUGH | F21: 0.47717593 | G21: U4A04S306 | I21: 2 | J21: Yes | K21: 60 | L21: PM30 | M21: 7000 | P21: 45748 | R21: 1 | S21: 7000 | T21: PE | U21: 60005003-D-GREEN0001 | V21: 0 | W21: 5000 | X21: 2000 | Y21: 0 | Z21: 0 | AA21: 0 | AD21: 0 | AM21: 60005003-D-GREEN | AN21: B02083 | AP21: 0 | AQ21: 0 | AR21: 0 | AS21: 0 | AT21: 0 | AU21: 0 | AY21: No | AZ21: W663754 | BA21: 0 | BC21: B02083 | BF21: S0361285
A22: W0681702 | B22: 10000 | C22: 10000 | D22: 45749 | E22: 502LAUGH | F22: 8:35:14 am | G22: M0BTQ4850 | I22: 1 | J22: Yes | K22: 94 | L22: PM09 | M22: 250 | P22: 45748 | R22: 4 | S22: 1000 | T22: PE | U22: L001-773057-00000007 | V22: 0 | W22: 1000 | X22: 0 | Y22: 0 | Z22: 0 | AA22: 0 | AD22: 0 | AM22: L001-773057-000007CM | AN22: X24001-WD-SUZHOU | AP22: 0 | AQ22: 0 | AR22: 0 | AS22: 0 | AT22: 0 | AU22: 0 | AY22: No | AZ22: W664118 | BA22: 0 | BC22: X24001-WD-SUZHOU | BF22: S0361288
A23: W0681760 | B23: 10000 | C23: 10000 | D23: 45749 | E23: 502LAUGH | F23: 8:58:47 am | G23: E0223920 | I23: 1 | J23: Yes | K23: 63 | L23: PM80 | M23: 2500 | P23: 45748 | R23: 72 | S23: 180000 | T23: PE | U23: 1114-790-00007 R0001 | V23: 0 | W23: 180000 | X23: 0 | Y23: 0 | Z23: 0 | AA23: 0 | AD23: 0 | AM23: 1114-790-00007 REVD | AN23: M13337-SMD | AP23: 0 | AQ23: 0 | AR23: 0 | AS23: 0 | AT23: 0 | AU23: 0 | AY23: No | AZ23: W664119 | BA23: 0 | BC23: M13337-SMD | BF23: S0361340
A24: W0681763 | B24: 10000 | C24: 10000 | D24: 45749 | E24: 502LAUGH | F24: 8:58:47 am | G24: 1006323 | I24: 1 | J24: Yes | K24: 63 | L24: PM80 | M24: 3334 | P24: 45748 | R24: 90 | S24: 300060 | T24: PE | U24: 1115-790-00003 R0001 | V24: 0 | W24: 300000 | X24: 60 | Y24: 0 | Z24: 0 | AA24: 0 | AD24: 0 | AM24: 1115-790-00003 REVB | AN24: M13337-SMD | AP24: 0 | AQ24: 0 | AR24: 0 | AS24: 0 | AT24: 0 | AU24: 0 | AY24: No | AZ24: W663771 | BA24: 0 | BC24: M13337-SMD | BF24: S0361340
A25: W0681773 | B25: 10000 | C25: 10000 | D25: 45748 | E25: 502LAUGH | F25: 5:43:19 pm | G25: D005H7770 | I25: 1 | J25: Yes | K25: 73 | L25: PM59 | M25: 667 | P25: 45748 | R25: 30 | S25: 20010 | T25: PE | U25: R390-411 REV1.00001 | V25: 0 | W25: 14334 | X25: 5676 | Y25: 0 | Z25: 0 | AA25: 0 | AD25: 0 | AM25: R390-411 REV1.0 | AN25: R18131-MEIBAN MIC-M | AP25: 0 | AQ25: 0 | AR25: 0 | AS25: 0 | AT25: 0 | AU25: 0 | AY25: No | AZ25: W664121 | BA25: 0 | BC25: R18131-MEIBAN MIC-M | BF25: GRR62158
A26: W0681773 | B26: 10000 | C26: 20000 | D26: 45748 | E26: 502LAUGH | F26: 5:43:19 pm | G26: D005H7770 | I26: 2 | J26: Yes | K26: 73 | L26: PM59 | M26: 478 | P26: 45748 | R26: 30 | S26: 14340 | T26: PE | U26: R390-411 REV1.00001 | V26: 0 | W26: 14334 | X26: 6 | Y26: 0 | Z26: 0 | AA26: 0 | AD26: 0 | AM26: R390-411 REV1.0 | AN26: R18131-MEIBAN MIC-M | AP26: 0 | AQ26: 0 | AR26: 0 | AS26: 0 | AT26: 0 | AU26: 0 | AY26: No | AZ26: W664121 | BA26: 0 | BC26: R18131-MEIBAN MIC-M | BF26: GRR62158
A27: W0681890 | B27: 10000 | C27: 10000 | D27: 45748 | E27: 502LAUGH | F27: 5:40:42 pm | G27: 3082510U9/4032711U5 | I27: 1 | J27: Yes | K27: 61 | L27: PM68 | M27: 3500 | P27: 45748 | R27: 1 | S27: 3500 | T27: PE | U27: 701684140001 | V27: 0 | W27: 3500 | X27: 0 | Y27: 0 | Z27: 0 | AA27: 0 | AD27: 0 | AM27: 70168414 | AN27: P16186 | AP27: 0 | AQ27: 0 | AR27: 0 | AS27: 0 | AT27: 0 | AU27: 0 | AY27: No | AZ27: W663811 | BA27: 0 | BC27: P16186 | BF27: S0361400
A28: W0681984 | B28: 10000 | C28: 10000 | D28: 45749 | E28: 502LAUGH | F28: 8:55:00 am | G28: E0223920 | I28: 1 | J28: Yes | K28: 63 | L28: PM80 | M28: 4667 | P28: 45748 | R28: 90 | S28: 420030 | T28: PE | U28: 1115-790-00001 R0001 | V28: 0 | W28: 420000 | X28: 30 | Y28: 0 | Z28: 0 | AA28: 0 | AD28: 0 | AM28: 1115-790-00001 REVB | AN28: M13337-SMD | AP28: 0 | AQ28: 0 | AR28: 0 | AS28: 0 | AT28: 0 | AU28: 0 | AY28: No | AZ28: W663819 | BA28: 0 | BC28: M13337-SMD | BF28: S0361340
A29: W0682107 | B29: 10000 | C29: 10000 | D29: 45754 | E29: 502LAUGH | F29: 8:56:52 am | G29: M0BUQ9711/M0BUF4241 | I29: 1 | J29: Yes | K29: 70 | L29: PS84 | M29: 60000 | P29: 45748 | R29: 2 | S29: 120000 | T29: PE | U29: 725427400 REVA0002 | V29: 0 | W29: 120000 | X29: 0 | Y29: 0 | Z29: 0 | AA29: 0 | AD29: 0 | AM29: 725427400 REVA | AN29: S19081-TH | AP29: 0 | AQ29: 0 | AR29: 0 | AS29: 0 | AT29: 0 | AU29: 0 | AY29: No | AZ29: W664144 | BA29: 0 | BC29: S19081-TH | BF29: H0064875
A30: W0682197 | B30: 10000 | C30: 20000 | D30: 45749 | E30: 502LAUGH | F30: 8:40:57 am | G30: U4A04S213/3082512U9 | I30: 2 | J30: Yes | K30: 100 | L30: PM87 | M30: 600 | P30: 45748 | R30: 1 | S30: 600 | T30: PE | U30: 104489220001 | V30: 0 | W30: 500 | X30: 100 | Y30: 0 | Z30: 0 | AA30: 0 | AD30: 0 | AM30: 10448922 | AN30: I09109 | AP30: 0 | AQ30: 0 | AR30: 0 | AS30: 0 | AT30: 0 | AU30: 0 | AY30: No | AZ30: W663883 | BA30: 0 | BC30: I09109 | BF30: S0361694
A31: W0682199 | B31: 10000 | C31: 20000 | D31: 45749 | E31: 502LAUGH | F31: 8:40:57 am | G31: U4A04S213/3082512U9 | I31: 2 | J31: Yes | K31: 100 | L31: PM87 | M31: 20 | P31: 45748 | R31: 1 | S31: 20 | T31: PE | U31: 104489220001 | V31: 0 | W31: 20 | X31: 0 | Y31: 0 | Z31: 0 | AA31: 0 | AD31: 0 | AM31: 10448922 | AN31: I09109 | AP31: 0 | AQ31: 0 | AR31: 0 | AS31: 0 | AT31: 0 | AU31: 0 | AY31: No | AZ31: W663885 | BA31: 0 | BC31: I09109 | BF31: ZSA101777
A32: W0682202 | B32: 10000 | C32: 10000 | D32: 45748 | E32: 502LAUGH | F32: 2:53:33 pm | G32: 4092S1 | I32: 1 | J32: Yes | K32: 61 | L32: PM68 | M32: 100 | P32: 45748 | R32: 1 | S32: 100 | T32: PE | U32: 03225846-010001 | V32: 0 | W32: 100 | X32: 0 | Y32: 0 | Z32: 0 | AA32: 0 | AD32: 0 | AM32: 03225846-01 | AN32: A01413 | AP32: 0 | AQ32: 0 | AR32: 0 | AS32: 0 | AT32: 0 | AU32: 0 | AY32: No | AZ32: W664151 | BA32: 0 | BC32: A01413 | BF32: S0361696
A33: W0682213 | B33: 10000 | C33: 20000 | D33: 45749 | E33: 502LAUGH | F33: 8:44:50 am | G33: 3082512U9/U4A04S213 | I33: 2 | J33: Yes | K33: 100 | L33: PM87 | M33: 600 | P33: 45748 | R33: 1 | S33: 600 | T33: PE | U33: 107355880001 | V33: 0 | W33: 500 | X33: 100 | Y33: 0 | Z33: 0 | AA33: 0 | AD33: 0 | AM33: 10735588 | AN33: I09109 | AP33: 0 | AQ33: 0 | AR33: 0 | AS33: 0 | AT33: 0 | AU33: 0 | AY33: No | AZ33: W663891 | BA33: 0 | BC33: I09109 | BF33: S0361705
A34: W0682214 | B34: 10000 | C34: 20000 | D34: 45749 | E34: 502LAUGH | F34: 8:49:04 am | G34: 3082512U9/U4A04S213 | I34: 2 | J34: Yes | K34: 100 | L34: PM87 | M34: 600 | P34: 45748 | R34: 1 | S34: 600 | T34: PE | U34: 107355890001 | V34: 0 | W34: 500 | X34: 100 | Y34: 0 | Z34: 0 | AA34: 0 | AD34: 0 | AM34: 10735589 | AN34: I09109 | AP34: 0 | AQ34: 0 | AR34: 0 | AS34: 0 | AT34: 0 | AU34: 0 | AY34: No | AZ34: W663892 | BA34: 0 | BC34: I09109 | BF34: S0361705
A35: W0682215 | B35: 10000 | C35: 20000 | D35: 45749 | E35: 502LAUGH | F35: 8:42:50 am | G35: D105Y48501525 | I35: 2 | J35: Yes | K35: 92 | L35: PM87 | M35: 600 | P35: 45748 | R35: 1 | S35: 600 | T35: PE | U35: 107472350001 | V35: 0 | W35: 500 | X35: 100 | Y35: 0 | Z35: 0 | AA35: 0 | AD35: 0 | AM35: 10747235 | AN35: I09109 | AP35: 0 | AQ35: 0 | AR35: 0 | AS35: 0 | AT35: 0 | AU35: 0 | AY35: No | AZ35: W663893 | BA35: 0 | BC35: I09109 | BF35: S0361705
A36: W0682217 | B36: 10000 | C36: 20000 | D36: 45749 | E36: 502LAUGH | F36: 8:44:50 am | G36: 3082512U9/U4A04S213 | I36: 2 | J36: Yes | K36: 100 | L36: PM87 | M36: 20 | P36: 45748 | R36: 1 | S36: 20 | T36: PE | U36: 107355880001 | V36: 0 | W36: 20 | X36: 0 | Y36: 0 | Z36: 0 | AA36: 0 | AD36: 0 | AM36: 10735588 | AN36: I09109 | AP36: 0 | AQ36: 0 | AR36: 0 | AS36: 0 | AT36: 0 | AU36: 0 | AY36: No | AZ36: W663895 | BA36: 0 | BC36: I09109 | BF36: ZSA101778
A37: W0682218 | B37: 10000 | C37: 20000 | D37: 45749 | E37: 502LAUGH | F37: 8:49:04 am | G37: 3082512U9/U4A04S213 | I37: 2 | J37: Yes | K37: 100 | L37: PM87 | M37: 20 | P37: 45748 | R37: 1 | S37: 20 | T37: PE | U37: 107355890001 | V37: 0 | W37: 20 | X37: 0 | Y37: 0 | Z37: 0 | AA37: 0 | AD37: 0 | AM37: 10735589 | AN37: I09109 | AP37: 0 | AQ37: 0 | AR37: 0 | AS37: 0 | AT37: 0 | AU37: 0 | AY37: No | AZ37: W663896 | BA37: 0 | BC37: I09109 | BF37: ZSA101778
A38: W0682219 | B38: 10000 | C38: 20000 | D38: 45749 | E38: 502LAUGH | F38: 8:42:50 am | G38: D105Y48501525 | I38: 2 | J38: Yes | K38: 92 | L38: PM87 | M38: 20 | P38: 45748 | R38: 1 | S38: 20 | T38: PE | U38: 107472350001 | V38: 0 | W38: 20 | X38: 0 | Y38: 0 | Z38: 0 | AA38: 0 | AD38: 0 | AM38: 10747235 | AN38: I09109 | AP38: 0 | AQ38: 0 | AR38: 0 | AS38: 0 | AT38: 0 | AU38: 0 | AY38: No | AZ38: W663897 | BA38: 0 | BC38: I09109 | BF38: ZSA101778
A39: W0682274 | B39: 10000 | C39: 20000 | D39: 45748 | E39: 502LAUGH | F39: 5:44:23 pm | G39: M0BVE5230 | I39: 2 | J39: Yes | K39: 73 | L39: PM59 | M39: 250 | P39: 45748 | R39: 1 | S39: 250 | T39: PE | U39: 10056878001 REVA0001 | V39: 0 | W39: 250 | X39: 0 | Y39: 0 | Z39: 0 | AA39: 0 | AD39: 0 | AM39: 10056878001 REVA | AN39: E05166-JAPAC | AP39: 0 | AQ39: 0 | AR39: 0 | AS39: 0 | AT39: 0 | AU39: 0 | AY39: No | AZ39: W664156 | BA39: 0 | BC39: E05166-JAPAC | BF39: S0361738
A40: W0682283 | B40: 10000 | C40: 20000 | D40: 45749 | E40: 502LAUGH | F40: 0.4762963 | G40: J00ML98601525 | I40: 2 | J40: Yes | K40: 92 | L40: PM87 | M40: 600 | P40: 45748 | R40: 1 | S40: 600 | T40: PE | U40: 107343730001 | V40: 0 | W40: 500 | X40: 100 | Y40: 0 | Z40: 0 | AA40: 0 | AD40: 0 | AM40: 10734373 | AN40: I09109 | AP40: 0 | AQ40: 0 | AR40: 0 | AS40: 0 | AT40: 0 | AU40: 0 | AY40: No | AZ40: W663922 | BA40: 0 | BC40: I09109 | BF40: S0361740
A41: W0682284 | B41: 10000 | C41: 20000 | D41: 45749 | E41: 502LAUGH | F41: 0.47821759 | G41: J00ML98601525 | I41: 2 | J41: Yes | K41: 92 | L41: PM87 | M41: 600 | P41: 45748 | R41: 1 | S41: 600 | T41: PE | U41: 107343750001 | V41: 0 | W41: 500 | X41: 100 | Y41: 0 | Z41: 0 | AA41: 0 | AD41: 0 | AM41: 10734375 | AN41: I09109 | AP41: 0 | AQ41: 0 | AR41: 0 | AS41: 0 | AT41: 0 | AU41: 0 | AY41: No | AZ41: W663923 | BA41: 0 | BC41: I09109 | BF41: S0361740
A42: W0682285 | B42: 10000 | C42: 20000 | D42: 45749 | E42: 502LAUGH | F42: 0.4762963 | G42: J00ML98601525 | I42: 2 | J42: Yes | K42: 92 | L42: PM87 | M42: 20 | P42: 45748 | R42: 1 | S42: 20 | T42: PE | U42: 107343730001 | V42: 0 | W42: 20 | X42: 0 | Y42: 0 | Z42: 0 | AA42: 0 | AD42: 0 | AM42: 10734373 | AN42: I09109 | AP42: 0 | AQ42: 0 | AR42: 0 | AS42: 0 | AT42: 0 | AU42: 0 | AY42: No | AZ42: W663924 | BA42: 0 | BC42: I09109 | BF42: ZSA101780
A43: W0682286 | B43: 10000 | C43: 20000 | D43: 45749 | E43: 502LAUGH | F43: 0.47869213 | G43: J00ML98601525 | I43: 2 | J43: Yes | K43: 92 | L43: PM87 | M43: 20 | P43: 45748 | R43: 1 | S43: 20 | T43: PE | U43: 107343750001 | V43: 0 | W43: 20 | X43: 0 | Y43: 0 | Z43: 0 | AA43: 0 | AD43: 0 | AM43: 10734375 | AN43: I09109 | AP43: 0 | AQ43: 0 | AR43: 0 | AS43: 0 | AT43: 0 | AU43: 0 | AY43: No | AZ43: W663925 | BA43: 0 | BC43: I09109 | BF43: ZSA101780
A44: W0682303 | B44: 10000 | C44: 10000 | D44: 45749 | E44: 502LAUGH | F44: 8:35:58 am | G44: 4177S1/3830U7060 | I44: 1 | J44: Yes | K44: 78 | L44: PM84 | M44: 1000 | P44: 45748 | R44: 3 | S44: 3000 | T44: PE | U44: 4.4017009e+17 | V44: 0 | W44: 3000 | X44: 0 | Y44: 0 | Z44: 0 | AA44: 0 | AD44: 0 | AM44: 44017008600402 | AN44: T20096 | AP44: 0 | AQ44: 0 | AR44: 0 | AS44: 0 | AT44: 0 | AU44: 0 | AY44: No | AZ44: W663934 | BA44: 0 | BC44: T20096 | BF44: S0361750
A45: W0682307 | B45: 10000 | C45: 10000 | D45: 45749 | E45: 502LAUGH | F45: 8:33:32 am | G45: J00UH0552 | I45: 1 | J45: Yes | K45: 65 | L45: PMJ7 | M45: 8000 | P45: 45748 | R45: 1 | S45: 8000 | T45: PE | U45: LABEL BLANKS SEN0001 | V45: 0 | W45: 8000 | X45: 0 | Y45: 0 | Z45: 0 | AA45: 0 | AD45: 0 | AM45: LABEL BLANKS SENSOR | AN45: F06061 | AP45: 0 | AQ45: 0 | AR45: 0 | AS45: 0 | AT45: 0 | AU45: 0 | AY45: No | AZ45: W664158 | BA45: 0 | BC45: F06061 | BF45: S0361751
A46: W0682308 | B46: 10000 | C46: 10000 | D46: 45749 | E46: 502LAUGH | F46: 0.4737963 | G46: J00UH0552 | I46: 1 | J46: Yes | K46: 65 | L46: PMJ7 | M46: 8000 | P46: 45748 | R46: 1 | S46: 8000 | T46: PE | U46: LABEL TEMPLATE 10001 | V46: 0 | W46: 8000 | X46: 0 | Y46: 0 | Z46: 0 | AA46: 0 | AD46: 0 | AM46: LABEL TEMPLATE 1 | AN46: F06061 | AP46: 0 | AQ46: 0 | AR46: 0 | AS46: 0 | AT46: 0 | AU46: 0 | AY46: No | AZ46: W664159 | BA46: 0 | BC46: F06061 | BF46: S0361751
A47: W0682337 | B47: 10000 | C47: 10000 | D47: 45749 | E47: 502LAUGH | F47: 8:32:31 am | G47: L5305U8039 | I47: 1 | J47: Yes | K47: 82 | L47: PM11 | M47: 12000 | P47: 45748 | R47: 5 | S47: 60000 | T47: PE | U47: 150-02285-2K0001 | V47: 0 | W47: 60000 | X47: 0 | Y47: 0 | Z47: 0 | AA47: 0 | AD47: 0 | AM47: 150-02319 | AN47: I09146 | AP47: 0 | AQ47: 0 | AR47: 0 | AS47: 0 | AT47: 0 | AU47: 0 | AY47: No | AZ47: W663936 | BA47: 0 | BC47: I09146 | BF47: S0361843
A48: W0682350 | B48: 10000 | C48: 10000 | D48: 45751 | E48: 502LAUGH | F48: 5:17:08 pm | G48: 10620258022 | I48: 1 | J48: Yes | K48: 79 | L48: PM16 | M48: 40 | P48: 45748 | R48: 550 | S48: 22000 | T48: PE | U48: G0Z24-800110001 | V48: 0 | W48: 5000 | X48: 17000 | Y48: 0 | Z48: 0 | AA48: 0 | AD48: 0 | AM48: G0Z24-80011 | AN48: H08031-JIM | AP48: 0 | AQ48: 0 | AR48: 0 | AS48: 0 | AT48: 0 | AU48: 0 | AY48: No | AZ48: W665431 | BA48: 0 | BC48: H08031-JIM | BF48: S0361847
A49: W0682397 | B49: 10000 | C49: 10000 | D49: 45751 | E49: 502LAUGH | F49: 2:52:49 pm | G49: 10656256095 | I49: 1 | J49: Yes | K49: 79 | L49: PM16 | M49: 540 | P49: 45748 | R49: 176 | S49: 95040 | T49: PE | U49: B3B28-80007-FT0001 | V49: 0 | W49: 80000 | X49: 15040 | Y49: 0 | Z49: 0 | AA49: 0 | AD49: 0 | AM49: B3B28-80007-FT | AN49: H08031-JIM-M | AP49: 0 | AQ49: 0 | AR49: 0 | AS49: 0 | AT49: 0 | AU49: 0 | AY49: No | AZ49: W664631 | BA49: 0 | BC49: H08031-JIM-M | BF49: S0361875
A50: W0682405 | B50: 10000 | C50: 10000 | D50: 45755 | E50: 502LAUGH | F50: 1:05:56 pm | G50: 10656256095 | I50: 1 | J50: Yes | K50: 79 | L50: PM16 | M50: 540 | P50: 45748 | R50: 176 | S50: 95040 | T50: PE | U50: E5Z01-80008-FT0001 | V50: 0 | W50: 80000 | X50: 15040 | Y50: 0 | Z50: 0 | AA50: 0 | AD50: 0 | AM50: E5Z01-80008-FT | AN50: H08031-JIM-M | AP50: 0 | AQ50: 0 | AR50: 0 | AS50: 0 | AT50: 0 | AU50: 0 | AY50: No | AZ50: W664635 | BA50: 0 | BC50: H08031-JIM-M | BF50: S0361883
A51: W0682407 | B51: 10000 | C51: 10000 | D51: 45754 | E51: 505KANGHS | F51: 1:49:32 pm | G51: 10656256086/10656256095 | I51: 1 | J51: Yes | K51: 79 | L51: PM16 | M51: 1142 | P51: 45748 | R51: 297 | S51: 339174 | T51: PE | U51: 6ZD61-800010001 | V51: 0 | W51: 330000 | X51: 9174 | Y51: 0 | Z51: 0 | AA51: 0 | AD51: 0 | AM51: 6ZD61-80001 | AN51: H08031-JIM-M | AP51: 0 | AQ51: 0 | AR51: 0 | AS51: 0 | AT51: 0 | AU51: 0 | AY51: No | AZ51: W665181 | BA51: 0 | BC51: H08031-JIM-M | BF51: S0361886
A52: W0682423 | B52: 10000 | C52: 10000 | D52: 45751 | E52: 502LAUGH | F52: 5:14:27 pm | G52: 10620258022 | I52: 1 | J52: Yes | K52: 79 | L52: PM16 | M52: 417 | P52: 45748 | R52: 36 | S52: 15012 | T52: PE | U52: CR330-800150001 | V52: 0 | W52: 10000 | X52: 5012 | Y52: 0 | Z52: 0 | AA52: 0 | AD52: 0 | AM52: CR330-80015 | AN52: H08031-JIM | AP52: 0 | AQ52: 0 | AR52: 0 | AS52: 0 | AT52: 0 | AU52: 0 | AY52: No | AZ52: W665919 | BA52: 0 | BC52: H08031-JIM | BF52: S0361900
A53: W0682444 | B53: 10000 | C53: 10000 | D53: 45749 | E53: 502LAUGH | F53: 5:10:27 pm | G53: J00WT7100 | I53: 1 | J53: Yes | K53: 72 | L53: PMJ4 | M53: 3750 | P53: 45748 | R53: 4 | S53: 15000 | T53: PE | U53: 5000443890001 | V53: 0 | W53: 12000 | X53: 3000 | Y53: 0 | Z53: 0 | AA53: 0 | AD53: 0 | AM53: 500044389 | AN53: B02083 | AP53: 0 | AQ53: 0 | AR53: 0 | AS53: 0 | AT53: 0 | AU53: 0 | AY53: No | AZ53: W663938 | BA53: 0 | BC53: B02083 | BF53: S0361912
A54: W0682445 | B54: 10000 | C54: 10000 | D54: 45749 | E54: 502LAUGH | F54: 5:10:27 pm | G54: J00WT7100 | I54: 1 | J54: Yes | K54: 72 | L54: PMJ4 | M54: 1750 | P54: 45748 | R54: 4 | S54: 7000 | T54: PE | U54: 5000514790001 | V54: 0 | W54: 5000 | X54: 2000 | Y54: 0 | Z54: 0 | AA54: 0 | AD54: 0 | AM54: 500051479 | AN54: B02083 | AP54: 0 | AQ54: 0 | AR54: 0 | AS54: 0 | AT54: 0 | AU54: 0 | AY54: No | AZ54: W664165 | BA54: 0 | BC54: B02083 | BF54: S0361912
A55: W0682446 | B55: 10000 | C55: 10000 | D55: 45749 | E55: 502LAUGH | F55: 5:10:27 pm | G55: J00WT7100 | I55: 1 | J55: Yes | K55: 72 | L55: PMJ4 | M55: 2000 | P55: 45748 | R55: 4 | S55: 8000 | T55: PE | U55: 5000514800001 | V55: 0 | W55: 6000 | X55: 2000 | Y55: 0 | Z55: 0 | AA55: 0 | AD55: 0 | AM55: 500051480 | AN55: B02083 | AP55: 0 | AQ55: 0 | AR55: 0 | AS55: 0 | AT55: 0 | AU55: 0 | AY55: No | AZ55: W664166 | BA55: 0 | BC55: B02083 | BF55: S0361912
A56: W0682447 | B56: 10000 | C56: 20000 | D56: 45748 | E56: 502LAUGH | F56: 4:47:19 pm | G56: J00WT7100 | I56: 2 | J56: Yes | K56: 71 | L56: PS95 | M56: 625 | P56: 45748 | R56: 8 | S56: 5000 | T56: PE | U56: 5000562920001 | V56: 0 | W56: 5000 | X56: 0 | Y56: 0 | Z56: 0 | AA56: 0 | AD56: 0 | AM56: 500056292 | AN56: B02083 | AP56: 0 | AQ56: 0 | AR56: 0 | AS56: 0 | AT56: 0 | AU56: 0 | AY56: No | AZ56: W663939 | BA56: 0 | BC56: B02083 | BF56: S0361912
A57: W0682448 | B57: 10000 | C57: 20000 | D57: 45748 | E57: 502LAUGH | F57: 4:46:04 pm | G57: J00WT7100 | I57: 2 | J57: Yes | K57: 71 | L57: PS95 | M57: 750 | P57: 45748 | R57: 8 | S57: 6000 | T57: PE | U57: 5000579950001 | V57: 0 | W57: 6000 | X57: 0 | Y57: 0 | Z57: 0 | AA57: 0 | AD57: 0 | AM57: 500057995 | AN57: B02083 | AP57: 0 | AQ57: 0 | AR57: 0 | AS57: 0 | AT57: 0 | AU57: 0 | AY57: No | AZ57: W663940 | BA57: 0 | BC57: B02083 | BF57: S0361912
A58: W0682450 | B58: 10000 | C58: 20000 | D58: 45749 | E58: 502LAUGH | F58: 8:38:44 am | G58: J00WT7100 | I58: 2 | J58: Yes | K58: 71 | L58: PS95 | M58: 167 | P58: 45748 | R58: 6 | S58: 1002 | T58: PE | U58: 5000514720001 | V58: 0 | W58: 1000 | X58: 2 | Y58: 0 | Z58: 0 | AA58: 0 | AD58: 0 | AM58: 500051472 | AN58: B02083 | AP58: 0 | AQ58: 0 | AR58: 0 | AS58: 0 | AT58: 0 | AU58: 0 | AY58: No | AZ58: W663941 | BA58: 0 | BC58: B02083 | BF58: S0361914
A59: W0682451 | B59: 10000 | C59: 20000 | D59: 45749 | E59: 502LAUGH | F59: 8:38:44 am | G59: J00WT7100 | I59: 2 | J59: Yes | K59: 71 | L59: PS95 | M59: 834 | P59: 45748 | R59: 6 | S59: 5004 | T59: PE | U59: 5000514730001 | V59: 0 | W59: 5000 | X59: 4 | Y59: 0 | Z59: 0 | AA59: 0 | AD59: 0 | AM59: 500051473 | AN59: B02083 | AP59: 0 | AQ59: 0 | AR59: 0 | AS59: 0 | AT59: 0 | AU59: 0 | AY59: No | AZ59: W663942 | BA59: 0 | BC59: B02083 | BF59: S0361914
A60: W0682452 | B60: 10000 | C60: 20000 | D60: 45749 | E60: 502LAUGH | F60: 8:38:44 am | G60: J00WT7100 | I60: 2 | J60: Yes | K60: 71 | L60: PS95 | M60: 834 | P60: 45748 | R60: 6 | S60: 5004 | T60: PE | U60: 5000579970001 | V60: 0 | W60: 5000 | X60: 4 | Y60: 0 | Z60: 0 | AA60: 0 | AD60: 0 | AM60: 500057997 | AN60: B02083 | AP60: 0 | AQ60: 0 | AR60: 0 | AS60: 0 | AT60: 0 | AU60: 0 | AY60: No | AZ60: W663943 | BA60: 0 | BC60: B02083 | BF60: S0361914
A61: W0682453 | B61: 10000 | C61: 20000 | D61: 45749 | E61: 502LAUGH | F61: 8:38:44 am | G61: J00WT7100 | I61: 2 | J61: Yes | K61: 71 | L61: PS95 | M61: 834 | P61: 45748 | R61: 6 | S61: 5004 | T61: PE | U61: 5000595780001 | V61: 0 | W61: 5000 | X61: 4 | Y61: 0 | Z61: 0 | AA61: 0 | AD61: 0 | AM61: 500059578 | AN61: B02083 | AP61: 0 | AQ61: 0 | AR61: 0 | AS61: 0 | AT61: 0 | AU61: 0 | AY61: No | AZ61: W663944 | BA61: 0 | BC61: B02083 | BF61: S0361914
A62: W0682462 | B62: 10000 | C62: 20000 | D62: 45748 | E62: 502LAUGH | F62: 4:48:20 pm | G62: J00WT7100 | I62: 2 | J62: Yes | K62: 71 | L62: PS95 | M62: 1875 | P62: 45748 | R62: 8 | S62: 15000 | T62: PE | U62: 5000562920001 | V62: 0 | W62: 15000 | X62: 0 | Y62: 0 | Z62: 0 | AA62: 0 | AD62: 0 | AM62: 500056292 | AN62: B02083 | AP62: 0 | AQ62: 0 | AR62: 0 | AS62: 0 | AT62: 0 | AU62: 0 | AY62: No | AZ62: W663949 | BA62: 0 | BC62: B02083 | BF62: S0361915
A63: W0682463 | B63: 10000 | C63: 20000 | D63: 45748 | E63: 502LAUGH | F63: 4:49:06 pm | G63: J00WT7100 | I63: 2 | J63: Yes | K63: 71 | L63: PS95 | M63: 1875 | P63: 45748 | R63: 8 | S63: 15000 | T63: PE | U63: 5000769160001 | V63: 0 | W63: 15000 | X63: 0 | Y63: 0 | Z63: 0 | AA63: 0 | AD63: 0 | AM63: 500076916 | AN63: B02083 | AP63: 0 | AQ63: 0 | AR63: 0 | AS63: 0 | AT63: 0 | AU63: 0 | AY63: No | AZ63: W663950 | BA63: 0 | BC63: B02083 | BF63: S0361915
A64: W0682474 | B64: 10000 | C64: 20000 | D64: 45749 | E64: 502LAUGH | F64: 8:38:44 am | G64: J00WT7100 | I64: 2 | J64: Yes | K64: 71 | L64: PS95 | M64: 167 | P64: 45748 | R64: 6 | S64: 1002 | T64: PE | U64: 5000444000001 | V64: 0 | W64: 1000 | X64: 2 | Y64: 0 | Z64: 0 | AA64: 0 | AD64: 0 | AM64: 500044400 | AN64: B02083 | AP64: 0 | AQ64: 0 | AR64: 0 | AS64: 0 | AT64: 0 | AU64: 0 | AY64: No | AZ64: W663954 | BA64: 0 | BC64: B02083 | BF64: S0361918
A65: W0682475 | B65: 10000 | C65: 20000 | D65: 45749 | E65: 502LAUGH | F65: 8:39:27 am | G65: J00WT7100 | I65: 2 | J65: Yes | K65: 71 | L65: PS95 | M65: 834 | P65: 45748 | R65: 6 | S65: 5004 | T65: PE | U65: 5000444260001 | V65: 0 | W65: 5000 | X65: 4 | Y65: 0 | Z65: 0 | AA65: 0 | AD65: 0 | AM65: 500044426 | AN65: B02083 | AP65: 0 | AQ65: 0 | AR65: 0 | AS65: 0 | AT65: 0 | AU65: 0 | AY65: No | AZ65: W663955 | BA65: 0 | BC65: B02083 | BF65: S0361918
A66: W0682485 | B66: 10000 | C66: 10000 | D66: 45749 | E66: 502LAUGH | F66: 8:33:32 am | G66: 152265H103 | I66: 1 | J66: Yes | K66: 82 | L66: PM11 | M66: 3334 | P66: 45748 | R66: 3 | S66: 10002 | T66: PE | U66: BLANK LBL-76X1020001 | V66: 0 | W66: 10000 | X66: 2 | Y66: 0 | Z66: 0 | AA66: 0 | AD66: 0 | AM66: BLANK LBL-76X102MM | AN66: T20300 | AP66: 0 | AQ66: 0 | AR66: 0 | AS66: 0 | AT66: 0 | AU66: 0 | AY66: No | AZ66: W664170 | BA66: 0 | BC66: T20300 | BF66: S0361928
A67: W0682500 | B67: 10000 | C67: 20000 | D67: 45748 | E67: 502LAUGH | F67: 1:18:04 pm | G67: J00WT7100 | I67: 2 | J67: Yes | K67: 71 | L67: PS95 | M67: 1000 | P67: 45748 | R67: 6 | S67: 6000 | T67: PE | U67: 5000580730001 | V67: 0 | W67: 6000 | X67: 0 | Y67: 0 | Z67: 0 | AA67: 0 | AD67: 0 | AM67: 500058073 | AN67: B02083 | AP67: 0 | AQ67: 0 | AR67: 0 | AS67: 0 | AT67: 0 | AU67: 0 | AY67: No | AZ67: W663959 | BA67: 0 | BC67: B02083 | BF67: S0361931
A68: W0682501 | B68: 10000 | C68: 20000 | D68: 45748 | E68: 502LAUGH | F68: 1:18:47 pm | G68: J00WT7100 | I68: 2 | J68: Yes | K68: 71 | L68: PS95 | M68: 2000 | P68: 45748 | R68: 6 | S68: 12000 | T68: PE | U68: 5000582200001 | V68: 0 | W68: 12000 | X68: 0 | Y68: 0 | Z68: 0 | AA68: 0 | AD68: 0 | AM68: 500058220 | AN68: B02083 | AP68: 0 | AQ68: 0 | AR68: 0 | AS68: 0 | AT68: 0 | AU68: 0 | AY68: No | AZ68: W663960 | BA68: 0 | BC68: B02083 | BF68: S0361931
A69: W0682502 | B69: 10000 | C69: 20000 | D69: 45748 | E69: 502LAUGH | F69: 1:19:34 pm | G69: J00WT7100 | I69: 2 | J69: Yes | K69: 71 | L69: PS95 | M69: 834 | P69: 45748 | R69: 6 | S69: 5004 | T69: PE | U69: 5000582250001 | V69: 0 | W69: 5000 | X69: 4 | Y69: 0 | Z69: 0 | AA69: 0 | AD69: 0 | AM69: 500058225 | AN69: B02083 | AP69: 0 | AQ69: 0 | AR69: 0 | AS69: 0 | AT69: 0 | AU69: 0 | AY69: No | AZ69: W663961 | BA69: 0 | BC69: B02083 | BF69: S0361931
A70: W0682503 | B70: 10000 | C70: 10000 | D70: 45750 | E70: 502LAUGH | F70: 8:35:03 am | G70: J00WT7100 | I70: 1 | J70: Yes | K70: 72 | L70: PMJ4 | M70: 1125 | P70: 45748 | R70: 4 | S70: 4500 | T70: PE | U70: 5000478010001 | V70: 0 | W70: 2500 | X70: 2000 | Y70: 0 | Z70: 0 | AA70: 0 | AD70: 0 | AM70: 500047801 | AN70: B02083 | AP70: 0 | AQ70: 0 | AR70: 0 | AS70: 0 | AT70: 0 | AU70: 0 | AY70: No | AZ70: W664172 | BA70: 0 | BC70: B02083 | BF70: S0361932
A71: W0682503 | B71: 20000 | C71: 10000 | D71: 45750 | E71: 502LAUGH | F71: 8:35:03 am | G71: J00WT7100 | I71: 1 | J71: Yes | K71: 72 | L71: PMJ4 | M71: 625 | P71: 45748 | R71: 4 | S71: 2500 | T71: PE | U71: 5000478010001 | V71: 0 | W71: 2500 | X71: 0 | Y71: 0 | Z71: 0 | AA71: 0 | AD71: 0 | AM71: 500047801 | AN71: B02083 | AP71: 0 | AQ71: 0 | AR71: 0 | AS71: 0 | AT71: 0 | AU71: 0 | AY71: No | AZ71: W664172 | BA71: 0 | BC71: B02083 | BF71: S0361932
A72: W0682504 | B72: 10000 | C72: 10000 | D72: 45750 | E72: 502LAUGH | F72: 8:35:03 am | G72: J00WT7100 | I72: 1 | J72: Yes | K72: 72 | L72: PMJ4 | M72: 1125 | P72: 45748 | R72: 4 | S72: 4500 | T72: PE | U72: 5000596190001 | V72: 0 | W72: 2500 | X72: 2000 | Y72: 0 | Z72: 0 | AA72: 0 | AD72: 0 | AM72: 500059619 | AN72: B02083 | AP72: 0 | AQ72: 0 | AR72: 0 | AS72: 0 | AT72: 0 | AU72: 0 | AY72: No | AZ72: W664173 | BA72: 0 | BC72: B02083 | BF72: S0361932
A73: W0682504 | B73: 20000 | C73: 10000 | D73: 45750 | E73: 502LAUGH | F73: 8:35:03 am | G73: J00WT7100 | I73: 1 | J73: Yes | K73: 72 | L73: PMJ4 | M73: 625 | P73: 45748 | R73: 4 | S73: 2500 | T73: PE | U73: 5000596190001 | V73: 0 | W73: 2500 | X73: 0 | Y73: 0 | Z73: 0 | AA73: 0 | AD73: 0 | AM73: 500059619 | AN73: B02083 | AP73: 0 | AQ73: 0 | AR73: 0 | AS73: 0 | AT73: 0 | AU73: 0 | AY73: No | AZ73: W664173 | BA73: 0 | BC73: B02083 | BF73: S0361932
A74: W0682505 | B74: 10000 | C74: 10000 | D74: 45749 | E74: 502LAUGH | F74: 0.47518519 | G74: J00WT7100 | I74: 1 | J74: Yes | K74: 72 | L74: PMJ4 | M74: 1750 | P74: 45748 | R74: 4 | S74: 7000 | T74: PE | U74: 5000634590001 | V74: 0 | W74: 5000 | X74: 2000 | Y74: 0 | Z74: 0 | AA74: 0 | AD74: 0 | AM74: 500063459 | AN74: B02083 | AP74: 0 | AQ74: 0 | AR74: 0 | AS74: 0 | AT74: 0 | AU74: 0 | AY74: No | AZ74: W663962 | BA74: 0 | BC74: B02083 | BF74: S0361932
A75: W0682506 | B75: 10000 | C75: 10000 | D75: 45749 | E75: 502LAUGH | F75: 0.47518519 | G75: J00WT7100 | I75: 1 | J75: Yes | K75: 72 | L75: PMJ4 | M75: 1750 | P75: 45748 | R75: 4 | S75: 7000 | T75: PE | U75: 5000635400001 | V75: 0 | W75: 5000 | X75: 2000 | Y75: 0 | Z75: 0 | AA75: 0 | AD75: 0 | AM75: 500063540 | AN75: B02083 | AP75: 0 | AQ75: 0 | AR75: 0 | AS75: 0 | AT75: 0 | AU75: 0 | AY75: No | AZ75: W664174 | BA75: 0 | BC75: B02083 | BF75: S0361932
A76: W0682538 | B76: 10000 | C76: 20000 | D76: 45779 | E76: 502LAUGH | F76: 5:43:37 pm | G76: 10656256088/10656256086 | I76: 1 | J76: Yes | K76: 79 | L76: PM16 | M76: 2570 | P76: 45748 | R76: 297 | S76: 763290 | T76: PE | U76: 3YM60-80017-FT0001 | V76: 0 | W76: 700000 | X76: 63290 | Y76: 0 | Z76: 0 | AA76: 0 | AD76: 0 | AM76: 3YM60-80017-FT | AN76: H08031-JIM-M | AP76: 0 | AQ76: 0 | AR76: 0 | AS76: 0 | AT76: 0 | AU76: 0 | AY76: No | AZ76: W665921 | BA76: 0 | BC76: H08031-JIM-M | BF76: S0361950
A77: W0682539 | B77: 10000 | C77: 10000 | D77: 45771 | E77: 502LAUGH | F77: 8:34:44 am | G77: 10620258022 | I77: 1 | J77: Yes | K77: 79 | L77: PM16 | M77: 879 | P77: 45748 | R77: 264 | S77: 232056 | T77: PE | U77: 7FP01-80003-FT0001 | V77: 0 | W77: 200000 | X77: 32056 | Y77: 0 | Z77: 0 | AA77: 0 | AD77: 0 | AM77: 7FP01-80003-FT | AN77: H08031-JIM-M | AP77: 0 | AQ77: 0 | AR77: 0 | AS77: 0 | AT77: 0 | AU77: 0 | AY77: No | AZ77: W665437 | BA77: 0 | BC77: H08031-JIM-M | BF77: S0361955
A78: W0682597 | B78: 10000 | C78: 40000 | D78: 45750 | E78: 502LAUGH | F78: 9:30:13 am | G78: 5316405-03-02-02 | I78: 1 | J78: Yes | K78: 63 | L78: PM80 | M78: 109 | P78: 45748 | R78: 60 | S78: 6540 | T78: PE | U78: 1124-790-00006RE0001 | V78: 0 | W78: 6500 | X78: 40 | Y78: 0 | Z78: 0 | AA78: 0 | AD78: 0 | AM78: 1124-790-00006REVTH1 | AN78: M13337-SMD | AP78: 0 | AQ78: 0 | AR78: 0 | AS78: 0 | AT78: 0 | AU78: 0 | AY78: No | AZ78: W663964 | BA78: 0 | BC78: M13337-SMD | BF78: S0361976
A79: W0682639 | B79: 10000 | C79: 10000 | D79: 45749 | E79: 502LAUGH | F79: 8:55:00 am | G79: 5316405-03-02-02 | I79: 1 | J79: Yes | K79: 63 | L79: PM80 | M79: 1000 | P79: 45748 | R79: 40 | S79: 40000 | T79: PE | U79: 11C4-790-00009 R0001 | V79: 0 | W79: 40000 | X79: 0 | Y79: 0 | Z79: 0 | AA79: 0 | AD79: 0 | AM79: 1125-790-00001 REVA | AN79: M13337-SMD | AP79: 0 | AQ79: 0 | AR79: 0 | AS79: 0 | AT79: 0 | AU79: 0 | AY79: No | AZ79: W665681 | BA79: 0 | BC79: M13337-SMD | BF79: S0361340
A80: W0682641 | B80: 10000 | C80: 10000 | D80: 45755 | E80: 502LAUGH | F80: 2:18:23 pm | G80: SG-5399135-01 | I80: 1 | J80: Yes | K80: 88 | L80: PP24 | M80: 800 | P80: 45748 | R80: 1 | S80: 800 | T80: PE | U80: GR-1580001 | V80: 0 | W80: 500 | X80: 300 | Y80: 0 | Z80: 0 | AA80: 0 | AD80: 0 | AM80: GR-158 | AN80: G07076 | AP80: 0 | AQ80: 0 | AR80: 0 | AS80: 0 | AT80: 0 | AU80: 0 | AY80: No | AZ80: W664710 | BA80: 0 | BC80: G07076 | BF80: S0362015
A81: W0682643 | B81: 10000 | C81: 10000 | D81: 45749 | E81: 502LAUGH | F81: 8:55:00 am | G81: 5316405-03-02-02 | I81: 1 | J81: Yes | K81: 63 | L81: PM80 | M81: 5 | P81: 45748 | R81: 40 | S81: 200 | T81: PE | U81: 11C4-790-00009 R0001 | V81: 0 | W81: 182 | X81: 18 | Y81: 0 | Z81: 0 | AA81: 0 | AD81: 0 | AM81: 1125-790-00001 REVA | AN81: M13337-SMD | AP81: 0 | AQ81: 0 | AR81: 0 | AS81: 0 | AT81: 0 | AU81: 0 | AY81: No | AZ81: W663965 | BA81: 0 | BC81: M13337-SMD | BF81: ZSA101789
A82: W0682661 | B82: 10000 | C82: 10000 | D82: 45754 | E82: 502LAUGH | F82: 9:18:57 am | G82: 59470/59469 | I82: 1 | J82: Yes | K82: 73N | L82: PM18 | M82: 55917 | P82: 45748 | R82: 12 | S82: 671004 | T82: PE | U82: MT-1000173-00REV0003 | V82: 0 | W82: 697647 | X82: -26643 | Y82: 0 | Z82: 0 | AA82: 0 | AD82: 0 | AM82: MT-1000173-00REV008 | AN82: Z26002 | AP82: 0 | AQ82: 0 | AR82: 0 | AS82: 0 | AT82: 0 | AU82: 0 | AY82: No | AZ82: W664723 | BA82: 0 | BC82: Z26002 | BF82: S0362021
A83: W0682662 | B83: 10000 | C83: 10000 | D83: 45750 | E83: 502LAUGH | F83: 8:42:45 am | G83: 59470 | I83: 1 | J83: Yes | K83: 73 | L83: PS96 | M83: 5000 | P83: 45748 | R83: 12 | S83: 60000 | T83: PE | U83: MT-1000241-907RE0001 | V83: 0 | W83: 59998 | X83: 2 | Y83: 0 | Z83: 0 | AA83: 0 | AD83: 0 | AM83: MT-1000241-907REV005 | AN83: Z26002 | AP83: 0 | AQ83: 0 | AR83: 0 | AS83: 0 | AT83: 0 | AU83: 0 | AY83: No | AZ83: W663966 | BA83: 0 | BC83: Z26002 | BF83: S0362021
A84: W0682662 | B84: 10000 | C84: 20000 | D84: 45750 | E84: 502LAUGH | F84: 8:42:45 am | G84: 59470 | I84: 1 | J84: Yes | K84: 73N | L84: PM18 | M84: 10313 | P84: 45748 | R84: 12 | S84: 123756 | T84: PE | U84: MT-1000241-907RE0001 | V84: 0 | W84: 123752 | X84: 4 | Y84: 0 | Z84: 0 | AA84: 0 | AD84: 0 | AM84: MT-1000241-907REV005 | AN84: Z26002 | AP84: 0 | AQ84: 0 | AR84: 0 | AS84: 0 | AT84: 0 | AU84: 0 | AY84: No | AZ84: W663966 | BA84: 0 | BC84: Z26002 | BF84: S0362021
A85: W0682667 | B85: 10000 | C85: 20000 | D85: 45749 | E85: 502LAUGH | F85: 2:20:32 pm | G85: J00WT7100 | I85: 1 | J85: Yes | K85: 72 | L85: PMJ4 | M85: 1750 | P85: 45748 | R85: 4 | S85: 7000 | T85: PE | U85: 86090840001 | V85: 0 | W85: 5000 | X85: 2000 | Y85: 0 | Z85: 0 | AA85: 0 | AD85: 0 | AM85: 8609084 | AN85: B02083 | AP85: 0 | AQ85: 0 | AR85: 0 | AS85: 0 | AT85: 0 | AU85: 0 | AY85: No | AZ85: W664725 | BA85: 0 | BC85: B02083 | BF85: S0362024
A86: W0682668 | B86: 10000 | C86: 10000 | D86: 45749 | E86: 502LAUGH | F86: 2:20:32 pm | G86: J00WT7100 | I86: 1 | J86: Yes | K86: 72 | L86: PMJ4 | M86: 1750 | P86: 45748 | R86: 4 | S86: 7000 | T86: PE | U86: 86090860001 | V86: 0 | W86: 5000 | X86: 2000 | Y86: 0 | Z86: 0 | AA86: 0 | AD86: 0 | AM86: 8609086 | AN86: B02083 | AP86: 0 | AQ86: 0 | AR86: 0 | AS86: 0 | AT86: 0 | AU86: 0 | AY86: No | AZ86: W664726 | BA86: 0 | BC86: B02083 | BF86: S0362024
A87: W0682685 | B87: 10000 | C87: 20000 | D87: 45750 | E87: 502LAUGH | F87: 9:30:13 am | G87: 1006323 | I87: 1 | J87: Yes | K87: 90N | L87: QC04 | M87: 5264 | P87: 45748 | R87: 38 | S87: 200032 | T87: PE | U87: 737025900-EL93160001 | V87: 0 | W87: 200000 | X87: 32 | Y87: 0 | Z87: 0 | AA87: 0 | AD87: 0 | AM87: 737025900-EL93164 | AN87: S19314 | AP87: 0 | AQ87: 0 | AR87: 0 | AS87: 0 | AT87: 0 | AU87: 0 | AY87: No | AZ87: W663967 | BA87: 0 | BC87: S19314 | BF87: H0064912
A88: W0682686 | B88: 10000 | C88: 10000 | D88: 45750 | E88: 502LAUGH | F88: 9:30:13 am | G88: E190912129 | I88: 1 | J88: Yes | K88: 63 | L88: PM80 | M88: 4000 | P88: 45748 | R88: 60 | S88: 240000 | T88: PE | U88: 739709802 REVA0001 | V88: 0 | W88: 240000 | X88: 0 | Y88: 0 | Z88: 0 | AA88: 0 | AD88: 0 | AM88: 739709802 REVA | AN88: S19314 | AP88: 0 | AQ88: 0 | AR88: 0 | AS88: 0 | AT88: 0 | AU88: 0 | AY88: No | AZ88: W664741 | BA88: 0 | BC88: S19314 | BF88: H0064913
A89: W0682689 | B89: 10000 | C89: 10000 | D89: 45751 | E89: 502LAUGH | F89: 1:00:22 pm | G89: E0801904/M0BSO4460 | I89: 1 | J89: Yes | K89: 87 | L89: PM14 | M89: 100 | P89: 45748 | R89: 2 | S89: 200 | T89: PE | U89: 762070100 REVA0001 | V89: 0 | W89: 200 | X89: 0 | Y89: 0 | Z89: 0 | AA89: 0 | AD89: 0 | AM89: 762070100 REVA | AN89: S19081 | AP89: 0 | AQ89: 0 | AR89: 0 | AS89: 0 | AT89: 0 | AU89: 0 | AY89: No | AZ89: W664743 | BA89: 0 | BC89: S19081 | BF89: ZSA101790

Sheet 02-Apr
A1: Production Output
A2: Filter: Date Completed: 02/04/25
A4: Work Order No. | B4: Work Order Line No. | C4: WO Journal Line No. | D4: Add Date | E4: Add User | F4: Add Time | G4: Material Batch No. | H4: Die Cut | I4: Process No. | J4: Posted | K4: Machine Code | L4: Staff Code | M4: No. of Press | N4: Date Started | O4: Time Started | P4: Date Completed | Q4: Time Completed | R4: No. of Ups | S4: Printed Quantity | T4: Journal Type | U4: Item Code | V4: Quantity | W4: QC Approved Quantity | X4: Rejected Quantity | Y4: Roll | Z4: Length | AA4: Width | AB4: Length UOM | AC4: Width UOM | AD4: RM Quantity | AE4: Material Code | AF4: Variant Code | AG4: Request Delivery Date | AH4: Non QC Record | AI4: Link to Line No. | AJ4: Related | AK4: Expire Date | AL4: Label Remark | AM4: Customer Part Number | AN4: Customer Code | AO4: ddmm | AP4: Label Packing Quantity 1 | AQ4: Label Quantity 1 | AR4: Label Packing Quantity 2 | AS4: Label Quantity 2 | AT4: Label Packing Quantity 3 | AU4: Label Quantity 3 | AV4: UOM for Label Printing | AW4: QC Inspector | AX4: Summarised Period | AY4: Summarised | AZ4: Posted Work Order No. | BA4: Colour | BB4: Currency | BC4: Ref Customer | BD4: Group | BE4: PO | BF4: Source Doc. No.
A5: W0675399 | B5: 10000 | C5: 40000 | D5: 45751 | E5: 502LAUGH | F5: 0.44092593 | G5: 10639931053/10639931059/10639931056/10639931055 | I5: 3 | J5: Yes | K5: 91 | L5: QM54 | M5: 112000 | P5: 45749 | R5: 9 | S5: 1008000 | T5: PE | U5: 5180-0100-BH2120001 | V5: 0 | W5: 1000000 | X5: 8000 | Y5: 0 | Z5: 0 | AA5: 0 | AD5: 0 | AM5: 5180-0100-BH212 | AN5: H08031-JIM | AP5: 0 | AQ5: 0 | AR5: 0 | AS5: 0 | AT5: 0 | AU5: 0 | AY5: No | AZ5: W664068 | BA5: 0 | BC5: H08031-JIM | BF5: S0353202
A6: W0676859 | B6: 10000 | C6: 20000 | D6: 45758 | E6: 502LAUGH | F6: 0.46591435 | G6: BZC064-08 | I6: 1 | J6: Yes | K6: 79 | L6: PM16 | M6: 8700 | P6: 45749 | R6: 5 | S6: 43500 | T6: PE | U6: RR 6X6-WHITE0001 | V6: 0 | W6: 40910 | X6: 2590 | Y6: 0 | Z6: 0 | AA6: 0 | AD6: 0 | AM6: RR 6X6-WHITE | AN6: E05203 | AP6: 0 | AQ6: 0 | AR6: 0 | AS6: 0 | AT6: 0 | AU6: 0 | AY6: No | AZ6: W664979 | BA6: 0 | BC6: E05203 | BF6: S0355056
A7: W0677858 | B7: 10000 | C7: 10000 | D7: 45776 | E7: 502LAUGH | F7: 8:28:44 am | G7: BVG027-04/BWK014-01 | I7: 1 | J7: Yes | K7: 88 | L7: PP24 | M7: 3500 | P7: 45749 | R7: 1 | S7: 3500 | T7: PE | U7: CE6401-9000-00080001 | V7: 0 | W7: 1500 | X7: 2000 | Y7: 0 | Z7: 0 | AA7: 0 | AD7: 0 | AM7: CE6401-9000-0008 | AN7: C03043 | AP7: 0 | AQ7: 0 | AR7: 0 | AS7: 0 | AT7: 0 | AU7: 0 | AY7: No | AZ7: W665665 | BA7: 0 | BC7: C03043 | BF7: S0356636
A8: W0678504 | B8: 10000 | C8: 20000 | D8: 45755 | E8: 502LAUGH | F8: 8:51:28 am | G8: J00WA6960/J00TB1180/J00VB8021/J00TB1740 | I8: 1 | J8: Yes | K8: 110 | L8: PM40 | M8: 126000 | P8: 45749 | R8: 4 | S8: 504000 | T8: PE | U8: Z980 REV11.00001 | V8: 0 | W8: 504000 | X8: 0 | Y8: 0 | Z8: 0 | AA8: 0 | AD8: 0 | AM8: Z980 REV11.0 | AN8: R18131 | AP8: 0 | AQ8: 0 | AR8: 0 | AS8: 0 | AT8: 0 | AU8: 0 | AY8: No | AZ8: W664487 | BA8: 0 | BC8: R18131 | BF8: S0357206
A9: W0678953 | B9: 10000 | C9: 10000 | D9: 45750 | E9: 502LAUGH | F9: 8:35:03 am | G9: J206L2871 | I9: 1 | J9: Yes | K9: 65 | L9: PMJ7 | M9: 9000 | P9: 45749 | R9: 6 | S9: 54000 | T9: PE | U9: Z513 REV3.00001 | V9: 0 | W9: 54000 | X9: 0 | Y9: 0 | Z9: 0 | AA9: 0 | AD9: 0 | AM9: Z513 REV3.0 | AN9: R18131 | AP9: 0 | AQ9: 0 | AR9: 0 | AS9: 0 | AT9: 0 | AU9: 0 | AY9: No | AZ9: W664073 | BA9: 0 | BC9: R18131 | BF9: S0357731
A10: W0679222 | B10: 10000 | C10: 20000 | D10: 45749 | E10: 502LAUGH | F10: 3:42:07 pm | G10: J00TP9191/J00WA7110 | I10: 1 | J10: Yes | K10: 111 | L10: PM11 | M10: 5625 | P10: 45749 | R10: 8 | S10: 45000 | T10: PE | U10: Z512 REV 6.00001 | V10: 0 | W10: 45000 | X10: 0 | Y10: 0 | Z10: 0 | AA10: 0 | AD10: 0 | AM10: Z512 REV 8.0 | AN10: R18131 | AP10: 0 | AQ10: 0 | AR10: 0 | AS10: 0 | AT10: 0 | AU10: 0 | AY10: No | AZ10: W664076 | BA10: 0 | BC10: R18131 | BF10: S0357874
A11: W0680522 | B11: 10000 | C11: 10000 | D11: 45749 | E11: 502LAUGH | F11: 5:41:53 pm | G11: 2101110U5/3082510U9 | I11: 1 | J11: Yes | K11: 61 | L11: PM68 | M11: 1000 | P11: 45749 | R11: 4 | S11: 4000 | T11: PE | U11: 726017 REV4000001 | V11: 0 | W11: 4000 | X11: 0 | Y11: 0 | Z11: 0 | AA11: 0 | AD11: 0 | AM11: 726017 REV400 | AN11: V22000 | AP11: 0 | AQ11: 0 | AR11: 0 | AS11: 0 | AT11: 0 | AU11: 0 | AY11: No | AZ11: W664079 | BA11: 0 | BC11: V22000 | BF11: S0359313
A12: W0680734 | B12: 10000 | C12: 10000 | D12: 45750 | E12: 502LAUGH | F12: 0.42329861 | G12: TOA1G75701525 | I12: 1 | J12: Yes | K12: 82 | L12: PM11 | M12: 15000 | P12: 45749 | R12: 2 | S12: 30000 | T12: PE | U12: BL-4X60006 | V12: 0 | W12: 30000 | X12: 0 | Y12: 0 | Z12: 0 | AA12: 0 | AD12: 0 | AM12: BL-4X6 | AN12: Z26000 | AP12: 0 | AQ12: 0 | AR12: 0 | AS12: 0 | AT12: 0 | AU12: 0 | AY12: No | AZ12: W664080 | BA12: 0 | BC12: Z26000 | BF12: ZSA101751
A13: W0680747 | B13: 10000 | C13: 10000 | D13: 45749 | E13: 502LAUGH | F13: 3:37:00 pm | G13: SG-5644655 01 | I13: 1 | J13: Yes | K13: 46 | L13: PS66 | M13: 258 | P13: 45749 | R13: 4 | S13: 1032 | T13: PE | U13: 112887410001 | V13: 0 | W13: 1030 | X13: 2 | Y13: 0 | Z13: 0 | AA13: 0 | AD13: 0 | AM13: 11288741 | AN13: I09180 | AP13: 0 | AQ13: 0 | AR13: 0 | AS13: 0 | AT13: 0 | AU13: 0 | AY13: No | AZ13: W664081 | BA13: 0 | BC13: I09180 | BF13: S0359863
A14: W0680753 | B14: 10000 | C14: 10000 | D14: 45749 | E14: 502LAUGH | F14: 0.47282407 | G14: SG-5644655 01 | I14: 1 | J14: Yes | K14: 46 | L14: PS66 | M14: 258 | P14: 45749 | R14: 4 | S14: 1032 | T14: PE | U14: 112887590001 | V14: 0 | W14: 1030 | X14: 2 | Y14: 0 | Z14: 0 | AA14: 0 | AD14: 0 | AM14: 11288759 | AN14: I09180 | AP14: 0 | AQ14: 0 | AR14: 0 | AS14: 0 | AT14: 0 | AU14: 0 | AY14: No | AZ14: W663609 | BA14: 0 | BC14: I09180 | BF14: S0359866
A15: W0680754 | B15: 10000 | C15: 10000 | D15: 45749 | E15: 502LAUGH | F15: 0.47282407 | G15: SG-5644655 01 | I15: 1 | J15: Yes | K15: 46 | L15: PS66 | M15: 258 | P15: 45749 | R15: 4 | S15: 1032 | T15: PE | U15: 112887590001 | V15: 0 | W15: 1030 | X15: 2 | Y15: 0 | Z15: 0 | AA15: 0 | AD15: 0 | AM15: 11288759 | AN15: I09180 | AP15: 0 | AQ15: 0 | AR15: 0 | AS15: 0 | AT15: 0 | AU15: 0 | AY15: No | AZ15: W663610 | BA15: 0 | BC15: I09180 | BF15: S0359867
A16: W0680762 | B16: 10000 | C16: 10000 | D16: 45749 | E16: 502LAUGH | F16: 5:29:41 pm | G16: SG-5644655 01 | I16: 1 | J16: Yes | K16: 46 | L16: PS66 | M16: 258 | P16: 45749 | R16: 4 | S16: 1032 | T16: PE | U16: 112887830001 | V16: 0 | W16: 1030 | X16: 2 | Y16: 0 | Z16: 0 | AA16: 0 | AD16: 0 | AM16: 11288783 | AN16: I09180 | AP16: 0 | AQ16: 0 | AR16: 0 | AS16: 0 | AT16: 0 | AU16: 0 | AY16: No | AZ16: W664082 | BA16: 0 | BC16: I09180 | BF16: S0359875
A17: W0681211 | B17: 10000 | C17: 10000 | D17: 45751 | E17: 502LAUGH | F17: 8:35:18 am | G17: M0BUF4292/M0BUQ9711 | I17: 1 | J17: Yes | K17: 29 | L17: PS70 | M17: 24000 | P17: 45749 | R17: 2 | S17: 48000 | T17: PE | U17: 100823881-75367 0001 | V17: 0 | W17: 48000 | X17: 0 | Y17: 0 | Z17: 0 | AA17: 0 | AD17: 0 | AM17: 100823881-75367 A | AN17: S19081-TH | AP17: 0 | AQ17: 0 | AR17: 0 | AS17: 0 | AT17: 0 | AU17: 0 | AY17: No | AZ17: W664091 | BA17: 0 | BC17: S19081-TH | BF17: H0064754
A18: W0681471 | B18: 10000 | C18: 10000 | D18: 45754 | E18: 502LAUGH | F18: 8:43:38 am | G18: 4101908U5A | I18: 1 | J18: Yes | K18: 12 | L18: PP05 | M18: 42000 | P18: 45749 | R18: 1 | S18: 42000 | T18: PE | U18: 250-6223-000001 | V18: 0 | W18: 42000 | X18: 0 | Y18: 0 | Z18: 0 | AA18: 0 | AD18: 0 | AM18: 250-6223-00 | AN18: J10025 | AP18: 0 | AQ18: 0 | AR18: 0 | AS18: 0 | AT18: 0 | AU18: 0 | AY18: No | AZ18: W664533 | BA18: 0 | BC18: J10025 | BF18: S0361174
A19: W0681510 | B19: 10000 | C19: 30000 | D19: 45749 | E19: 502LAUGH | F19: 1:56:09 pm | G19: M0BSO3780 | I19: 1 | J19: Yes | K19: 94 | L19: PM94 | M19: 5000 | P19: 45749 | R19: 4 | S19: 20000 | T19: PE | U19: L001-773057-00000005 | V19: 0 | W19: 20000 | X19: 0 | Y19: 0 | Z19: 0 | AA19: 0 | AD19: 0 | AM19: L001-773057-000005CM | AN19: W23041-TH | AP19: 0 | AQ19: 0 | AR19: 0 | AS19: 0 | AT19: 0 | AU19: 0 | AY19: No | AZ19: W664538 | BA19: 0 | BC19: W23041-TH | BF19: H0064783
A20: W0681511 | B20: 10000 | C20: 20000 | D20: 45749 | E20: 502LAUGH | F20: 5:41:53 pm | G20: M0BTQ4850 | I20: 1 | J20: Yes | K20: 94 | L20: PM09 | M20: 5000 | P20: 45749 | R20: 4 | S20: 20000 | T20: PE | U20: L001-773057-00000005 | V20: 0 | W20: 20000 | X20: 0 | Y20: 0 | Z20: 0 | AA20: 0 | AD20: 0 | AM20: L001-773057-000005CM | AN20: W23041-TH | AP20: 0 | AQ20: 0 | AR20: 0 | AS20: 0 | AT20: 0 | AU20: 0 | AY20: No | AZ20: W664103 | BA20: 0 | BC20: W23041-TH | BF20: H0064784
A21: W0681576 | B21: 10000 | C21: 20000 | D21: 45751 | E21: 502LAUGH | F21: 1:46:58 pm | G21: 10620258046 | I21: 2 | J21: Yes | K21: 77 | L21: PM74 | M21: 1285 | P21: 45749 | R21: 88 | S21: 113080 | T21: PE | U21: T6N02-80020-FT0001 | V21: 0 | W21: 100000 | X21: 13080 | Y21: 0 | Z21: 0 | AA21: 0 | AD21: 0 | AM21: T6N02-80020-FT | AN21: H08031-JIM-M | AP21: 0 | AQ21: 0 | AR21: 0 | AS21: 0 | AT21: 0 | AU21: 0 | AY21: No | AZ21: W664109 | BA21: 0 | BC21: H08031-JIM-M | BF21: S0361213
A22: W0681676 | B22: 10000 | C22: 30000 | D22: 45750 | E22: 502LAUGH | F22: 8:36:27 am | G22: U4A04S306 | I22: 2 | J22: Yes | K22: 60 | L22: PM61 | M22: 3900 | P22: 45749 | R22: 1 | S22: 3900 | T22: PE | U22: 60005003-D-BLUE0001 | V22: 0 | W22: 2000 | X22: 1900 | Y22: 0 | Z22: 0 | AA22: 0 | AD22: 0 | AM22: 60005003-D-BLUE | AN22: B02083 | AP22: 0 | AQ22: 0 | AR22: 0 | AS22: 0 | AT22: 0 | AU22: 0 | AY22: No | AZ22: W663753 | BA22: 0 | BC22: B02083 | BF22: S0361285
A23: W0681677 | B23: 10000 | C23: 20000 | D23: 45750 | E23: 502LAUGH | F23: 5:04:42 pm | G23: U4A04S306 | I23: 2 | J23: Yes | K23: 60 | L23: PM30 | M23: 18000 | P23: 45749 | R23: 1 | S23: 18000 | T23: PE | U23: 60005003-D-DARK 0001 | V23: 0 | W23: 15000 | X23: 3000 | Y23: 0 | Z23: 0 | AA23: 0 | AD23: 0 | AM23: 60005003-D-DARK GREY | AN23: B02083 | AP23: 0 | AQ23: 0 | AR23: 0 | AS23: 0 | AT23: 0 | AU23: 0 | AY23: No | AZ23: W664114 | BA23: 0 | BC23: B02083 | BF23: S0361285
A24: W0681680 | B24: 10000 | C24: 20000 | D24: 45749 | E24: 502LAUGH | F24: 3:35:20 pm | G24: U4A04S306 | I24: 2 | J24: Yes | K24: 60 | L24: PM30 | M24: 2000 | P24: 45749 | R24: 1 | S24: 2000 | T24: PE | U24: 60005003-D-ROSE0001 | V24: 0 | W24: 1000 | X24: 1000 | Y24: 0 | Z24: 0 | AA24: 0 | AD24: 0 | AM24: 60005003-D-ROSE | AN24: B02083 | AP24: 0 | AQ24: 0 | AR24: 0 | AS24: 0 | AT24: 0 | AU24: 0 | AY24: No | AZ24: W663755 | BA24: 0 | BC24: B02083 | BF24: S0361285
A25: W0681681 | B25: 10000 | C25: 20000 | D25: 45749 | E25: 502LAUGH | F25: 4:17:10 pm | G25: U4A04S306 | I25: 2 | J25: Yes | K25: 60 | L25: PM61 | M25: 4000 | P25: 45749 | R25: 1 | S25: 4000 | T25: PE | U25: 60005003-D-WHITE0001 | V25: 0 | W25: 2000 | X25: 2000 | Y25: 0 | Z25: 0 | AA25: 0 | AD25: 0 | AM25: 60005003-D-WHITE | AN25: B02083 | AP25: 0 | AQ25: 0 | AR25: 0 | AS25: 0 | AT25: 0 | AU25: 0 | AY25: No | AZ25: W663756 | BA25: 0 | BC25: B02083 | BF25: S0361285
A26: W0681800 | B26: 10000 | C26: 10000 | D26: 45750 | E26: 502LAUGH | F26: 8:41:24 am | G26: E04LE7190 | I26: 1 | J26: Yes | K26: 22 | L26: PS13 | M26: 1000 | P26: 45749 | R26: 1 | S26: 1000 | T26: PE | U26: 12000 SQ FEET0001 | V26: 0 | W26: 1000 | X26: 0 | Y26: 0 | Z26: 0 | AA26: 0 | AD26: 0 | AM26: 12000 SQ FEET | AN26: T20326 | AP26: 0 | AQ26: 0 | AR26: 0 | AS26: 0 | AT26: 0 | AU26: 0 | AY26: No | AZ26: W664122 | BA26: 0 | BC26: T20326 | BF26: S0361365
A27: W0681801 | B27: 10000 | C27: 10000 | D27: 45749 | E27: 502LAUGH | F27: 5:11:48 pm | G27: E04LE7190 | I27: 1 | J27: Yes | K27: 22 | L27: PS13 | M27: 1000 | P27: 45749 | R27: 1 | S27: 1000 | T27: PE | U27: 16000 SQ FEET0001 | V27: 0 | W27: 1000 | X27: 0 | Y27: 0 | Z27: 0 | AA27: 0 | AD27: 0 | AM27: 16000 SQ FEET | AN27: T20326 | AP27: 0 | AQ27: 0 | AR27: 0 | AS27: 0 | AT27: 0 | AU27: 0 | AY27: No | AZ27: W664123 | BA27: 0 | BC27: T20326 | BF27: S0361365
A28: W0681802 | B28: 10000 | C28: 10000 | D28: 45750 | E28: 502LAUGH | F28: 8:41:24 am | G28: E04LE7190 | I28: 1 | J28: Yes | K28: 22 | L28: PS13 | M28: 2000 | P28: 45749 | R28: 1 | S28: 2000 | T28: PE | U28: 500 SQ FEET0001 | V28: 0 | W28: 2000 | X28: 0 | Y28: 0 | Z28: 0 | AA28: 0 | AD28: 0 | AM28: 500 SQ FEET | AN28: T20326 | AP28: 0 | AQ28: 0 | AR28: 0 | AS28: 0 | AT28: 0 | AU28: 0 | AY28: No | AZ28: W664124 | BA28: 0 | BC28: T20326 | BF28: S0361365
A29: W0681815 | B29: 10000 | C29: 10000 | D29: 45749 | E29: 502LAUGH | F29: 2:37:21 pm | G29: 4110602U5A | I29: 1 | J29: Yes | K29: 22 | L29: PS13 | M29: 7000 | P29: 45749 | R29: 1 | S29: 7000 | T29: PE | U29: 250-6224-000001 | V29: 0 | W29: 7000 | X29: 0 | Y29: 0 | Z29: 0 | AA29: 0 | AD29: 0 | AM29: 250-6224-00 | AN29: J10025 | AP29: 0 | AQ29: 0 | AR29: 0 | AS29: 0 | AT29: 0 | AU29: 0 | AY29: No | AZ29: W664126 | BA29: 0 | BC29: J10025 | BF29: S0361373
A30: W0681881 | B30: 10000 | C30: 10000 | D30: 45750 | E30: 502LAUGH | F30: 0.42506944 | G30: L5305U8039 | I30: 1 | J30: Yes | K30: 78 | L30: PM84 | M30: 6000 | P30: 45749 | R30: 1 | S30: 6000 | T30: PE | U30: SCREAMER LB-80X10001 | V30: 0 | W30: 6000 | X30: 0 | Y30: 0 | Z30: 0 | AA30: 0 | AD30: 0 | AM30: SCREAMER LB-80X134MM | AN30: I09146 | AP30: 0 | AQ30: 0 | AR30: 0 | AS30: 0 | AT30: 0 | AU30: 0 | AY30: No | AZ30: W664132 | BA30: 0 | BC30: I09146 | BF30: S0361394
A31: W0681895 | B31: 10000 | C31: 20000 | D31: 45754 | E31: 502LAUGH | F31: 8:47:11 am | G31: 10620258046 | I31: 2 | J31: Yes | K31: 77 | L31: PM74 | M31: 1285 | P31: 45749 | R31: 88 | S31: 113080 | T31: PE | U31: 3UB27-800030001 | V31: 0 | W31: 100000 | X31: 13080 | Y31: 0 | Z31: 0 | AA31: 0 | AD31: 0 | AM31: 3UB27-80003 | AN31: H08031-JIM-M | AP31: 0 | AQ31: 0 | AR31: 0 | AS31: 0 | AT31: 0 | AU31: 0 | AY31: No | AZ31: W664576 | BA31: 0 | BC31: H08031-JIM-M | BF31: S0361404
A32: W0681896 | B32: 10000 | C32: 20000 | D32: 45754 | E32: 502LAUGH | F32: 8:36:19 am | G32: 10620258046 | I32: 2 | J32: Yes | K32: 77 | L32: PM74 | M32: 1285 | P32: 45749 | R32: 88 | S32: 113080 | T32: PE | U32: 3YM83-800010001 | V32: 0 | W32: 100000 | X32: 13080 | Y32: 0 | Z32: 0 | AA32: 0 | AD32: 0 | AM32: 3YM83-80001 | AN32: H08031-JIM-M | AP32: 0 | AQ32: 0 | AR32: 0 | AS32: 0 | AT32: 0 | AU32: 0 | AY32: No | AZ32: W664577 | BA32: 0 | BC32: H08031-JIM-M | BF32: S0361405
A33: W0681902 | B33: 10000 | C33: 20000 | D33: 45754 | E33: 502LAUGH | F33: 5:26:27 pm | G33: 10656256096 | I33: 2 | J33: Yes | K33: 77 | L33: PM74 | M33: 1285 | P33: 45749 | R33: 88 | S33: 113080 | T33: PE | U33: 3YM75-80011-FT0001 | V33: 0 | W33: 100000 | X33: 13080 | Y33: 0 | Z33: 0 | AA33: 0 | AD33: 0 | AM33: 3YM75-80011-FT | AN33: H08031-JIM-M | AP33: 0 | AQ33: 0 | AR33: 0 | AS33: 0 | AT33: 0 | AU33: 0 | AY33: No | AZ33: W664579 | BA33: 0 | BC33: H08031-JIM-M | BF33: S0361409
A34: W0681903 | B34: 10000 | C34: 20000 | D34: 45754 | E34: 502LAUGH | F34: 3:42:29 pm | G34: 10620258039 | I34: 2 | J34: Yes | K34: 77 | L34: PM74 | M34: 2884 | P34: 45749 | R34: 77 | S34: 222068 | T34: PE | U34: 7FP20-80002-FT0001 | V34: 0 | W34: 200000 | X34: 22068 | Y34: 0 | Z34: 0 | AA34: 0 | AD34: 0 | AM34: 7FP20-80002-FT | AN34: H08031-JIM-M | AP34: 0 | AQ34: 0 | AR34: 0 | AS34: 0 | AT34: 0 | AU34: 0 | AY34: No | AZ34: W664580 | BA34: 0 | BC34: H08031-JIM-M | BF34: S0361410
A35: W0681930 | B35: 10000 | C35: 10000 | D35: 45749 | E35: 502LAUGH | F35: 0.47378472 | G35: MDRLR4W211124 | I35: 1 | J35: Yes | K35: 65 | L35: PMJ7 | M35: 112 | P35: 45749 | R35: 90 | S35: 10080 | T35: PE | U35: 720502 REV4010001 | V35: 0 | W35: 10000 | X35: 80 | Y35: 0 | Z35: 0 | AA35: 0 | AD35: 0 | AM35: 720502 REV402 | AN35: V22000 | AP35: 0 | AQ35: 0 | AR35: 0 | AS35: 0 | AT35: 0 | AU35: 0 | AY35: No | AZ35: W663818 | BA35: 0 | BC35: V22000 | BF35: S0361418
A36: W0681951 | B36: 10000 | C36: 10000 | D36: 45749 | E36: 502LAUGH | F36: 2:37:21 pm | G36: 4170S1 | I36: 1 | J36: Yes | K36: 78 | L36: PM84 | M36: 3500 | P36: 45749 | R36: 1 | S36: 3500 | T36: PE | U36: 805512 REV4000001 | V36: 0 | W36: 3500 | X36: 0 | Y36: 0 | Z36: 0 | AA36: 0 | AD36: 0 | AM36: 805512 REV400 | AN36: V22000 | AP36: 0 | AQ36: 0 | AR36: 0 | AS36: 0 | AT36: 0 | AU36: 0 | AY36: No | AZ36: W664137 | BA36: 0 | BC36: V22000 | BF36: S0361431
A37: W0682027 | B37: 10000 | C37: 10000 | D37: 45750 | E37: 502LAUGH | F37: 5:39:51 pm | G37: TW1116349-04 | I37: 1 | J37: Yes | K37: 72 | L37: PMJ4 | M37: 1459 | P37: 45749 | R37: 24 | S37: 35016 | T37: PE | U37: P1S0455 60001 | V37: 0 | W37: 30000 | X37: 5016 | Y37: 0 | Z37: 0 | AA37: 0 | AD37: 0 | AM37: P1S0455 6 | AN37: H08220 | AP37: 0 | AQ37: 0 | AR37: 0 | AS37: 0 | AT37: 0 | AU37: 0 | AY37: No | AZ37: W664139 | BA37: 0 | BC37: H08220 | BF37: S0361538
A38: W0682041 | B38: 10000 | C38: 20000 | D38: 45754 | E38: 502LAUGH | F38: 8:50:45 am | G38: 10620258046 | I38: 2 | J38: Yes | K38: 77 | L38: PM74 | M38: 1285 | P38: 45749 | R38: 88 | S38: 113080 | T38: PE | U38: T6M58-800040001 | V38: 0 | W38: 100000 | X38: 13080 | Y38: 0 | Z38: 0 | AA38: 0 | AD38: 0 | AM38: T6M58-80004 | AN38: H08031-JIM-M | AP38: 0 | AQ38: 0 | AR38: 0 | AS38: 0 | AT38: 0 | AU38: 0 | AY38: No | AZ38: W664591 | BA38: 0 | BC38: H08031-JIM-M | BF38: S0361539
A39: W0682071 | B39: 10000 | C39: 20000 | D39: 45750 | E39: 502LAUGH | F39: 8:39:28 am | G39: 3082510U9/401180925 | I39: 2 | J39: Yes | K39: 100 | L39: PM87 | M39: 700 | P39: 45749 | R39: 1 | S39: 700 | T39: PE | U39: 107176710001 | V39: 0 | W39: 500 | X39: 200 | Y39: 0 | Z39: 0 | AA39: 0 | AD39: 0 | AM39: 10717671 | AN39: I09109 | AP39: 0 | AQ39: 0 | AR39: 0 | AS39: 0 | AT39: 0 | AU39: 0 | AY39: No | AZ39: W663861 | BA39: 0 | BC39: I09109 | BF39: S0361542
A40: W0682088 | B40: 10000 | C40: 10000 | D40: 45751 | E40: 502LAUGH | F40: 2:29:24 pm | G40: 501060725 | I40: 1 | J40: Yes | K40: 31 | L40: PS19 | M40: 5000 | P40: 45749 | R40: 1 | S40: 5000 | T40: PE | U40: OHARA LABEL0001 | V40: 0 | W40: 5000 | X40: 0 | Y40: 0 | Z40: 0 | AA40: 0 | AD40: 0 | AM40: OHARA LABEL | AN40: H08217 | AP40: 0 | AQ40: 0 | AR40: 0 | AS40: 0 | AT40: 0 | AU40: 0 | AY40: No | AZ40: W664142 | BA40: 0 | BC40: H08217 | BF40: S0361562
A41: W0682114 | B41: 10000 | C41: 20000 | D41: 45754 | E41: 502LAUGH | F41: 2:46:49 pm | G41: 10656256096 | I41: 2 | J41: Yes | K41: 77 | L41: PM74 | M41: 853 | P41: 45749 | R41: 88 | S41: 75064 | T41: PE | U41: 3YM56-80009-FT0001 | V41: 0 | W41: 60000 | X41: 15064 | Y41: 0 | Z41: 0 | AA41: 0 | AD41: 0 | AM41: 3YM56-80009-FT | AN41: H08031-JIM-M | AP41: 0 | AQ41: 0 | AR41: 0 | AS41: 0 | AT41: 0 | AU41: 0 | AY41: No | AZ41: W664602 | BA41: 0 | BC41: H08031-JIM-M | BF41: S0361568
A42: W0682176 | B42: 10000 | C42: 10000 | D42: 45749 | E42: 502LAUGH | F42: 4:43:43 pm | G42: SG-5630465 | I42: 1 | J42: Yes | K42: 31 | L42: PS19 | M42: 2500 | P42: 45749 | R42: 4 | S42: 10000 | T42: PE | U42: 200129790001 | V42: 0 | W42: 10000 | X42: 0 | Y42: 0 | Z42: 0 | AA42: 0 | AD42: 0 | AM42: 20012979 | AN42: I09180 | AP42: 0 | AQ42: 0 | AR42: 0 | AS42: 0 | AT42: 0 | AU42: 0 | AY42: No | AZ42: W664148 | BA42: 0 | BC42: I09180 | BF42: S0361677
A43: W0682176 | B43: 20000 | C43: 10000 | D43: 45749 | E43: 502LAUGH | F43: 4:43:43 pm | G43: SG-5630465 | I43: 1 | J43: Yes | K43: 31 | L43: PS19 | M43: 2500 | P43: 45749 | R43: 4 | S43: 10000 | T43: PE | U43: 200129790001 | V43: 0 | W43: 10000 | X43: 0 | Y43: 0 | Z43: 0 | AA43: 0 | AD43: 0 | AM43: 20012979 | AN43: I09180 | AP43: 0 | AQ43: 0 | AR43: 0 | AS43: 0 | AT43: 0 | AU43: 0 | AY43: No | AZ43: W664148 | BA43: 0 | BC43: I09180 | BF43: S0361677
A44: W0682176 | B44: 30000 | C44: 10000 | D44: 45749 | E44: 502LAUGH | F44: 4:43:43 pm | G44: SG-5630465 | I44: 1 | J44: Yes | K44: 31 | L44: PS19 | M44: 2500 | P44: 45749 | R44: 4 | S44: 10000 | T44: PE | U44: 200129790001 | V44: 0 | W44: 10000 | X44: 0 | Y44: 0 | Z44: 0 | AA44: 0 | AD44: 0 | AM44: 20012979 | AN44: I09180 | AP44: 0 | AQ44: 0 | AR44: 0 | AS44: 0 | AT44: 0 | AU44: 0 | AY44: No | AZ44: W664148 | BA44: 0 | BC44: I09180 | BF44: S0361677
A45: W0682184 | B45: 10000 | C45: 10000 | D45: 45750 | E45: 502LAUGH | F45: 8:31:47 am | G45: BZB084-03 | I45: 1 | J45: Yes | K45: 71 | L45: PS95 | M45: 1750 | P45: 45749 | R45: 8 | S45: 14000 | T45: PE | U45: BLANK LABEL-105X0001 | V45: 0 | W45: 14000 | X45: 0 | Y45: 0 | Z45: 0 | AA45: 0 | AD45: 0 | AM45: 150-01536 | AN45: I09146 | AP45: 0 | AQ45: 0 | AR45: 0 | AS45: 0 | AT45: 0 | AU45: 0 | AY45: No | AZ45: W664150 | BA45: 0 | BC45: I09146 | BF45: S0361685
A46: W0682222 | B46: 10000 | C46: 20000 | D46: 45750 | E46: 502LAUGH | F46: 8:38:48 am | G46: 40718205/3082509U9 | I46: 2 | J46: Yes | K46: 100 | L46: PM87 | M46: 250 | P46: 45749 | R46: 1 | S46: 250 | T46: PE | U46: 209277A0001 | V46: 0 | W46: 200 | X46: 50 | Y46: 0 | Z46: 0 | AA46: 0 | AD46: 0 | AM46: 209277A | AN46: E05185 | AP46: 0 | AQ46: 0 | AR46: 0 | AS46: 0 | AT46: 0 | AU46: 0 | AY46: No | AZ46: W664152 | BA46: 0 | BC46: E05185 | BF46: S0361706
A47: W0682223 | B47: 10000 | C47: 10000 | D47: 45749 | E47: 502LAUGH | F47: 2:22:20 pm | G47: 3082510U9 | I47: 1 | J47: Yes | K47: 61 | L47: PM68 | M47: 100 | P47: 45749 | R47: 1 | S47: 100 | T47: PE | U47: 85516A0001 | V47: 0 | W47: 100 | X47: 0 | Y47: 0 | Z47: 0 | AA47: 0 | AD47: 0 | AM47: 85516A | AN47: E05185 | AP47: 0 | AQ47: 0 | AR47: 0 | AS47: 0 | AT47: 0 | AU47: 0 | AY47: No | AZ47: W663900 | BA47: 0 | BC47: E05185 | BF47: S0361706
A48: W0682224 | B48: 10000 | C48: 10000 | D48: 45751 | E48: 502LAUGH | F48: 3:41:29 pm | G48: TW1116349-04 | I48: 1 | J48: Yes | K48: 72 | L48: PMJ4 | M48: 3709 | P48: 45749 | R48: 24 | S48: 89016 | T48: PE | U48: P1S0455 60001 | V48: 0 | W48: 84000 | X48: 5016 | Y48: 0 | Z48: 0 | AA48: 0 | AD48: 0 | AM48: P1S0455 6 | AN48: H08220 | AP48: 0 | AQ48: 0 | AR48: 0 | AS48: 0 | AT48: 0 | AU48: 0 | AY48: No | AZ48: W664153 | BA48: 0 | BC48: H08220 | BF48: S0361708
A49: W0682253 | B49: 10000 | C49: 10000 | D49: 45754 | E49: 505KANGHS | F49: 8:41:32 am | G49: 211041725 | I49: 1 | J49: Yes | K49: 88 | L49: PP24 | M49: 2200 | P49: 45749 | R49: 1 | S49: 2200 | T49: PE | U49: INSPECTION STICK0002 | V49: 0 | W49: 2000 | X49: 200 | Y49: 0 | Z49: 0 | AA49: 0 | AD49: 0 | AM49: INSPECTION STICKER | AN49: C03033 | AP49: 0 | AQ49: 0 | AR49: 0 | AS49: 0 | AT49: 0 | AU49: 0 | AY49: No | AZ49: W664154 | BA49: 0 | BC49: C03033 | BF49: S0361721
A50: W0682261 | B50: 10000 | C50: 20000 | D50: 45750 | E50: 502LAUGH | F50: 8:40:15 am | G50: J00LU70911000/3082509U9 | I50: 2 | J50: Yes | K50: 100 | L50: PM87 | M50: 2600 | P50: 45749 | R50: 1 | S50: 2600 | T50: PE | U50: 107431990001 | V50: 0 | W50: 2400 | X50: 200 | Y50: 0 | Z50: 0 | AA50: 0 | AD50: 0 | AM50: 10743199 | AN50: I09109 | AP50: 0 | AQ50: 0 | AR50: 0 | AS50: 0 | AT50: 0 | AU50: 0 | AY50: No | AZ50: W664155 | BA50: 0 | BC50: I09109 | BF50: S0361727
A51: W0682312 | B51: 10000 | C51: 20000 | D51: 45750 | E51: 502LAUGH | F51: 8:33:24 am | G51: I2A235H010 | I51: 2 | J51: Yes | K51: 92 | L51: PM87 | M51: 1200 | P51: 45749 | R51: 1 | S51: 1200 | T51: PE | U51: UR79LB4028AB0001 | V51: 0 | W51: 1000 | X51: 200 | Y51: 0 | Z51: 0 | AA51: 0 | AD51: 0 | AM51: UR79LB4028AB | AN51: S19708-M | AP51: 0 | AQ51: 0 | AR51: 0 | AS51: 0 | AT51: 0 | AU51: 0 | AY51: No | AZ51: W664160 | BA51: 0 | BC51: S19708-M | BF51: S0361754
A52: W0682396 | B52: 10000 | C52: 20000 | D52: 45755 | E52: 502LAUGH | F52: 8:38:49 am | G52: 10656256085 | I52: 2 | J52: Yes | K52: 77 | L52: PM74 | M52: 1285 | P52: 45749 | R52: 88 | S52: 113080 | T52: PE | U52: CH562-80137-BH180001 | V52: 0 | W52: 100000 | X52: 13080 | Y52: 0 | Z52: 0 | AA52: 0 | AD52: 0 | AM52: CH562-80137-BH184 | AN52: H08031-JIM-M | AP52: 0 | AQ52: 0 | AR52: 0 | AS52: 0 | AT52: 0 | AU52: 0 | AY52: No | AZ52: W664630 | BA52: 0 | BC52: H08031-JIM-M | BF52: S0361874
A53: W0682412 | B53: 10000 | C53: 20000 | D53: 45770 | E53: 502LAUGH | F53: 8:33:25 am | G53: 10656256092 | I53: 2 | J53: Yes | K53: 77 | L53: PM74 | M53: 1285 | P53: 45749 | R53: 88 | S53: 113080 | T53: PE | U53: 3UB27-800030001 | V53: 0 | W53: 100000 | X53: 13080 | Y53: 0 | Z53: 0 | AA53: 0 | AD53: 0 | AM53: 3UB27-80003 | AN53: H08031-JIM-M | AP53: 0 | AQ53: 0 | AR53: 0 | AS53: 0 | AT53: 0 | AU53: 0 | AY53: No | AZ53: W665278 | BA53: 0 | BC53: H08031-JIM-M | BF53: S0361890
A54: W0682413 | B54: 10000 | C54: 20000 | D54: 45772 | E54: 502LAUGH | F54: 8:31:58 am | G54: 10656256092 | I54: 2 | J54: Yes | K54: 77 | L54: PM74 | M54: 2523 | P54: 45749 | R54: 88 | S54: 222024 | T54: PE | U54: 3YM79-80005-FT0001 | V54: 0 | W54: 200000 | X54: 22024 | Y54: 0 | Z54: 0 | AA54: 0 | AD54: 0 | AM54: 3YM79-80005-FT | AN54: H08031-JIM-M | AP54: 0 | AQ54: 0 | AR54: 0 | AS54: 0 | AT54: 0 | AU54: 0 | AY54: No | AZ54: W665675 | BA54: 0 | BC54: H08031-JIM-M | BF54: S0361891
A55: W0682434 | B55: 10000 | C55: 10000 | D55: 45750 | E55: 502LAUGH | F55: 8:37:58 am | G55: U530352041/501241326 | I55: 1 | J55: Yes | K55: 32 | L55: PM26 | M55: 5860 | P55: 45749 | R55: 1 | S55: 5860 | T55: PE | U55: 250-5322-000001 | V55: 0 | W55: 5360 | X55: 500 | Y55: 0 | Z55: 0 | AA55: 0 | AD55: 0 | AM55: 250-5322-00 | AN55: J10025 | AP55: 0 | AQ55: 0 | AR55: 0 | AS55: 0 | AT55: 0 | AU55: 0 | AY55: No | AZ55: W664645 | BA55: 0 | BC55: J10025 | BF55: S0361906
A56: W0682438 | B56: 10000 | C56: 10000 | D56: 45750 | E56: 502LAUGH | F56: 8:37:58 am | G56: U530352041/501241326 | I56: 1 | J56: Yes | K56: 32 | L56: PM26 | M56: 5860 | P56: 45749 | R56: 1 | S56: 5860 | T56: PE | U56: 250-5322-000001 | V56: 0 | W56: 5360 | X56: 500 | Y56: 0 | Z56: 0 | AA56: 0 | AD56: 0 | AM56: 250-5322-00 | AN56: J10025 | AP56: 0 | AQ56: 0 | AR56: 0 | AS56: 0 | AT56: 0 | AU56: 0 | AY56: No | AZ56: W664649 | BA56: 0 | BC56: J10025 | BF56: S0361907
A57: W0682440 | B57: 10000 | C57: 10000 | D57: 45750 | E57: 502LAUGH | F57: 8:41:24 am | G57: 4067S1 | I57: 1 | J57: Yes | K57: 61 | L57: PM68 | M57: 100 | P57: 45749 | R57: 1 | S57: 100 | T57: PE | U57: 804144 REV4010001 | V57: 0 | W57: 100 | X57: 0 | Y57: 0 | Z57: 0 | AA57: 0 | AD57: 0 | AM57: 804144 REV401 | AN57: V22000 | AP57: 0 | AQ57: 0 | AR57: 0 | AS57: 0 | AT57: 0 | AU57: 0 | AY57: No | AZ57: W664164 | BA57: 0 | BC57: V22000 | BF57: ZSA101781
A58: W0682444 | B58: 10000 | C58: 20000 | D58: 45749 | E58: 502LAUGH | F58: 5:10:27 pm | G58: J00WT7100 | I58: 2 | J58: Yes | K58: 71 | L58: PS95 | M58: 2000 | P58: 45749 | R58: 6 | S58: 12000 | T58: PE | U58: 5000443890001 | V58: 0 | W58: 12000 | X58: 0 | Y58: 0 | Z58: 0 | AA58: 0 | AD58: 0 | AM58: 500044389 | AN58: B02083 | AP58: 0 | AQ58: 0 | AR58: 0 | AS58: 0 | AT58: 0 | AU58: 0 | AY58: No | AZ58: W663938 | BA58: 0 | BC58: B02083 | BF58: S0361912
A59: W0682445 | B59: 10000 | C59: 20000 | D59: 45749 | E59: 502LAUGH | F59: 5:10:27 pm | G59: J00WT7100 | I59: 2 | J59: Yes | K59: 71 | L59: PS95 | M59: 834 | P59: 45749 | R59: 6 | S59: 5004 | T59: PE | U59: 5000514790001 | V59: 0 | W59: 5000 | X59: 4 | Y59: 0 | Z59: 0 | AA59: 0 | AD59: 0 | AM59: 500051479 | AN59: B02083 | AP59: 0 | AQ59: 0 | AR59: 0 | AS59: 0 | AT59: 0 | AU59: 0 | AY59: No | AZ59: W664165 | BA59: 0 | BC59: B02083 | BF59: S0361912
A60: W0682446 | B60: 10000 | C60: 20000 | D60: 45749 | E60: 502LAUGH | F60: 5:10:27 pm | G60: J00WT7100 | I60: 2 | J60: Yes | K60: 71 | L60: PS95 | M60: 1000 | P60: 45749 | R60: 6 | S60: 6000 | T60: PE | U60: 5000514800001 | V60: 0 | W60: 6000 | X60: 0 | Y60: 0 | Z60: 0 | AA60: 0 | AD60: 0 | AM60: 500051480 | AN60: B02083 | AP60: 0 | AQ60: 0 | AR60: 0 | AS60: 0 | AT60: 0 | AU60: 0 | AY60: No | AZ60: W664166 | BA60: 0 | BC60: B02083 | BF60: S0361912
A61: W0682471 | B61: 10000 | C61: 20000 | D61: 45755 | E61: 502LAUGH | F61: 1:03:22 pm | G61: 10656256092 | I61: 2 | J61: Yes | K61: 77 | L61: PM74 | M61: 2282 | P61: 45749 | R61: 88 | S61: 200816 | T61: PE | U61: 3YM62-80017-FT0001 | V61: 0 | W61: 180000 | X61: 20816 | Y61: 0 | Z61: 0 | AA61: 0 | AD61: 0 | AM61: 3YM62-80017-FT | AN61: H08031-JIM-M | AP61: 0 | AQ61: 0 | AR61: 0 | AS61: 0 | AT61: 0 | AU61: 0 | AY61: No | AZ61: W664655 | BA61: 0 | BC61: H08031-JIM-M | BF61: S0361917
A62: W0682472 | B62: 10000 | C62: 20000 | D62: 45749 | E62: 502LAUGH | F62: 0.47518519 | G62: J00WT7100 | I62: 2 | J62: Yes | K62: 71 | L62: PS95 | M62: 834 | P62: 45749 | R62: 6 | S62: 5004 | T62: PE | U62: 5000435330001 | V62: 0 | W62: 5000 | X62: 4 | Y62: 0 | Z62: 0 | AA62: 0 | AD62: 0 | AM62: 500043533 | AN62: B02083 | AP62: 0 | AQ62: 0 | AR62: 0 | AS62: 0 | AT62: 0 | AU62: 0 | AY62: No | AZ62: W664656 | BA62: 0 | BC62: B02083 | BF62: S0361918
A63: W0682483 | B63: 10000 | C63: 20000 | D63: 45755 | E63: 502LAUGH | F63: 1:04:46 pm | G63: 10656256091 | I63: 2 | J63: Yes | K63: 77 | L63: PM74 | M63: 637 | P63: 45749 | R63: 88 | S63: 56056 | T63: PE | U63: 9R1W4-80001-FT0001 | V63: 0 | W63: 40000 | X63: 16056 | Y63: 0 | Z63: 0 | AA63: 0 | AD63: 0 | AM63: 9R1W4-80001-FT | AN63: H08031-JIM-M | AP63: 0 | AQ63: 0 | AR63: 0 | AS63: 0 | AT63: 0 | AU63: 0 | AY63: No | AZ63: W664660 | BA63: 0 | BC63: H08031-JIM-M | BF63: S0361925
A64: W0682486 | B64: 10000 | C64: 10000 | D64: 45749 | E64: 502LAUGH | F64: 0.47282407 | G64: 152265H103 | I64: 1 | J64: Yes | K64: 82 | L64: PM11 | M64: 3334 | P64: 45749 | R64: 3 | S64: 10002 | T64: PE | U64: BLANK-102X76MM-10001 | V64: 0 | W64: 10000 | X64: 2 | Y64: 0 | Z64: 0 | AA64: 0 | AD64: 0 | AM64: BLANK-102X76MM-1PC | AN64: T20300 | AP64: 0 | AQ64: 0 | AR64: 0 | AS64: 0 | AT64: 0 | AU64: 0 | AY64: No | AZ64: W663958 | BA64: 0 | BC64: T20300 | BF64: S0361928
A65: W0682503 | B65: 10000 | C65: 20000 | D65: 45750 | E65: 502LAUGH | F65: 8:35:03 am | G65: J00WT7100 | I65: 2 | J65: Yes | K65: 71 | L65: PS95 | M65: 834 | P65: 45749 | R65: 6 | S65: 5004 | T65: PE | U65: 5000478010001 | V65: 0 | W65: 2500 | X65: 2504 | Y65: 0 | Z65: 0 | AA65: 0 | AD65: 0 | AM65: 500047801 | AN65: B02083 | AP65: 0 | AQ65: 0 | AR65: 0 | AS65: 0 | AT65: 0 | AU65: 0 | AY65: No | AZ65: W664172 | BA65: 0 | BC65: B02083 | BF65: S0361932
A66: W0682504 | B66: 10000 | C66: 20000 | D66: 45750 | E66: 502LAUGH | F66: 8:35:03 am | G66: J00WT7100 | I66: 2 | J66: Yes | K66: 71 | L66: PS95 | M66: 834 | P66: 45749 | R66: 6 | S66: 5004 | T66: PE | U66: 5000596190001 | V66: 0 | W66: 2500 | X66: 2504 | Y66: 0 | Z66: 0 | AA66: 0 | AD66: 0 | AM66: 500059619 | AN66: B02083 | AP66: 0 | AQ66: 0 | AR66: 0 | AS66: 0 | AT66: 0 | AU66: 0 | AY66: No | AZ66: W664173 | BA66: 0 | BC66: B02083 | BF66: S0361932
A67: W0682505 | B67: 10000 | C67: 20000 | D67: 45749 | E67: 502LAUGH | F67: 0.47518519 | G67: J00WT7100 | I67: 2 | J67: Yes | K67: 71 | L67: PS95 | M67: 834 | P67: 45749 | R67: 6 | S67: 5004 | T67: PE | U67: 5000634590001 | V67: 0 | W67: 5000 | X67: 4 | Y67: 0 | Z67: 0 | AA67: 0 | AD67: 0 | AM67: 500063459 | AN67: B02083 | AP67: 0 | AQ67: 0 | AR67: 0 | AS67: 0 | AT67: 0 | AU67: 0 | AY67: No | AZ67: W663962 | BA67: 0 | BC67: B02083 | BF67: S0361932
A68: W0682506 | B68: 10000 | C68: 20000 | D68: 45749 | E68: 502LAUGH | F68: 0.47518519 | G68: J00WT7100 | I68: 2 | J68: Yes | K68: 71 | L68: PS95 | M68: 834 | P68: 45749 | R68: 6 | S68: 5004 | T68: PE | U68: 5000635400001 | V68: 0 | W68: 5000 | X68: 4 | Y68: 0 | Z68: 0 | AA68: 0 | AD68: 0 | AM68: 500063540 | AN68: B02083 | AP68: 0 | AQ68: 0 | AR68: 0 | AS68: 0 | AT68: 0 | AU68: 0 | AY68: No | AZ68: W664174 | BA68: 0 | BC68: B02083 | BF68: S0361932
A69: W0682516 | B69: 10000 | C69: 20000 | D69: 45751 | E69: 502LAUGH | F69: 8:31:55 am | G69: I492555H088 | I69: 2 | J69: Yes | K69: 92 | L69: PM87 | M69: 4000 | P69: 45749 | R69: 3 | S69: 12000 | T69: PE | U69: LEFTFOOT-80-250001 | V69: 0 | W69: 10000 | X69: 2000 | Y69: 0 | Z69: 0 | AA69: 0 | AD69: 0 | AM69: LEFTFOOT-80-25 | AN69: H08117 | AP69: 0 | AQ69: 0 | AR69: 0 | AS69: 0 | AT69: 0 | AU69: 0 | AY69: No | AZ69: W664668 | BA69: 0 | BC69: H08117 | BF69: S0361937
A70: W0682534 | B70: 10000 | C70: 20000 | D70: 45750 | E70: 502LAUGH | F70: 8:32:39 am | G70: 10656256085 | I70: 2 | J70: Yes | K70: 77 | L70: PM74 | M70: 378 | P70: 45749 | R70: 180 | S70: 68040 | T70: PE | U70: 1VV01-80003-FT0001 | V70: 0 | W70: 40000 | X70: 28040 | Y70: 0 | Z70: 0 | AA70: 0 | AD70: 0 | AM70: 1VV01-80003-FT | AN70: H08031-JIM-M | AP70: 0 | AQ70: 0 | AR70: 0 | AS70: 0 | AT70: 0 | AU70: 0 | AY70: No | AZ70: W664674 | BA70: 0 | BC70: H08031-JIM-M | BF70: S0361948
A71: W0682535 | B71: 10000 | C71: 20000 | D71: 45751 | E71: 502LAUGH | F71: 0.48146991 | G71: 10656256085 | I71: 2 | J71: Yes | K71: 77 | L71: PM74 | M71: 936 | P71: 45749 | R71: 77 | S71: 72072 | T71: PE | U71: 7FP39-80002-FT0001 | V71: 0 | W71: 50000 | X71: 22072 | Y71: 0 | Z71: 0 | AA71: 0 | AD71: 0 | AM71: 7FP39-80002-FT | AN71: H08031-JIM-M | AP71: 0 | AQ71: 0 | AR71: 0 | AS71: 0 | AT71: 0 | AU71: 0 | AY71: No | AZ71: W664675 | BA71: 0 | BC71: H08031-JIM-M | BF71: S0361953
A72: W0682544 | B72: 10000 | C72: 20000 | D72: 45770 | E72: 502LAUGH | F72: 0.47258102 | G72: 10656256087 | I72: 2 | J72: Yes | K72: 77 | L72: PM74 | M72: 2884 | P72: 45749 | R72: 77 | S72: 222068 | T72: PE | U72: 7FP02-80003-FT0001 | V72: 0 | W72: 200000 | X72: 22068 | Y72: 0 | Z72: 0 | AA72: 0 | AD72: 0 | AM72: 7FP02-80003-FT | AN72: H08031-JIM-M | AP72: 0 | AQ72: 0 | AR72: 0 | AS72: 0 | AT72: 0 | AU72: 0 | AY72: No | AZ72: W665280 | BA72: 0 | BC72: H08031-JIM-M | BF72: S0361960
A73: W0682556 | B73: 10000 | C73: 10000 | D73: 45751 | E73: 502LAUGH | F73: 8:51:28 am | G73: E053912079 | I73: 1 | J73: Yes | K73: 63 | L73: PM80 | M73: 2000 | P73: 45749 | R73: 40 | S73: 80000 | T73: PE | U73: 709898813-3M66900001 | V73: 0 | W73: 80000 | X73: 0 | Y73: 0 | Z73: 0 | AA73: 0 | AD73: 0 | AM73: 709898813-3M6690SP | AN73: S19081-TH | AP73: 0 | AQ73: 0 | AR73: 0 | AS73: 0 | AT73: 0 | AU73: 0 | AY73: No | AZ73: W664681 | BA73: 0 | BC73: S19081-TH | BF73: H0064889
A74: W0682564 | B74: 10000 | C74: 10000 | D74: 45750 | E74: 502LAUGH | F74: 9:30:13 am | G74: E190912129 | I74: 1 | J74: Yes | K74: 63 | L74: PM80 | M74: 10000 | P74: 45749 | R74: 60 | S74: 600000 | T74: PE | U74: 739709802 REVA0001 | V74: 0 | W74: 600000 | X74: 0 | Y74: 0 | Z74: 0 | AA74: 0 | AD74: 0 | AM74: 739709802 REVA | AN74: S19081-TH | AP74: 0 | AQ74: 0 | AR74: 0 | AS74: 0 | AT74: 0 | AU74: 0 | AY74: No | AZ74: W664684 | BA74: 0 | BC74: S19081-TH | BF74: H0064897
A75: W0682565 | B75: 10000 | C75: 10000 | D75: 45751 | E75: 502LAUGH | F75: 8:51:28 am | G75: E190912129 | I75: 1 | J75: Yes | K75: 63 | L75: PM80 | M75: 10000 | P75: 45749 | R75: 60 | S75: 600000 | T75: PE | U75: 739709802 REVA0001 | V75: 0 | W75: 600000 | X75: 0 | Y75: 0 | Z75: 0 | AA75: 0 | AD75: 0 | AM75: 739709802 REVA | AN75: S19081-TH | AP75: 0 | AQ75: 0 | AR75: 0 | AS75: 0 | AT75: 0 | AU75: 0 | AY75: No | AZ75: W664685 | BA75: 0 | BC75: S19081-TH | BF75: H0064898
A76: W0682578 | B76: 10000 | C76: 10000 | D76: 45749 | E76: 502LAUGH | F76: 4:28:41 pm | G76: J206L2871 | I76: 1 | J76: Yes | K76: 65 | L76: PMJ7 | M76: 9000 | P76: 45749 | R76: 6 | S76: 54000 | T76: PE | U76: Z513 REV3.00001 | V76: 0 | W76: 54000 | X76: 0 | Y76: 0 | Z76: 0 | AA76: 0 | AD76: 0 | AM76: Z513 REV3.0 | AN76: R18131-MALAYSIA | AP76: 0 | AQ76: 0 | AR76: 0 | AS76: 0 | AT76: 0 | AU76: 0 | AY76: No | AZ76: W664688 | BA76: 0 | BC76: R18131-MALAYSIA | BF76: S0361975
A77: W0682596 | B77: 10000 | C77: 10000 | D77: 45749 | E77: 502LAUGH | F77: 3:37:01 pm | G77: SG-5644655 01 | I77: 1 | J77: Yes | K77: 46 | L77: PS66 | M77: 258 | P77: 45749 | R77: 4 | S77: 1032 | T77: PE | U77: 112887410001 | V77: 0 | W77: 1030 | X77: 2 | Y77: 0 | Z77: 0 | AA77: 0 | AD77: 0 | AM77: 11288741 | AN77: I09180 | AP77: 0 | AQ77: 0 | AR77: 0 | AS77: 0 | AT77: 0 | AU77: 0 | AY77: No | AZ77: W664700 | BA77: 0 | BC77: I09180 | BF77: S0362000
A78: W0682598 | B78: 10000 | C78: 10000 | D78: 45749 | E78: 502LAUGH | F78: 3:37:01 pm | G78: SG-5644655 01 | I78: 1 | J78: Yes | K78: 46 | L78: PS66 | M78: 258 | P78: 45749 | R78: 4 | S78: 1032 | T78: PE | U78: 112887410001 | V78: 0 | W78: 1030 | X78: 2 | Y78: 0 | Z78: 0 | AA78: 0 | AD78: 0 | AM78: 11288741 | AN78: I09180 | AP78: 0 | AQ78: 0 | AR78: 0 | AS78: 0 | AT78: 0 | AU78: 0 | AY78: No | AZ78: W664701 | BA78: 0 | BC78: I09180 | BF78: S0362001
A79: W0682600 | B79: 10000 | C79: 10000 | D79: 45749 | E79: 502LAUGH | F79: 5:29:41 pm | G79: SG-5644655 01 | I79: 1 | J79: Yes | K79: 46 | L79: PS66 | M79: 258 | P79: 45749 | R79: 4 | S79: 1032 | T79: PE | U79: 112887830001 | V79: 0 | W79: 1030 | X79: 2 | Y79: 0 | Z79: 0 | AA79: 0 | AD79: 0 | AM79: 11288783 | AN79: I09180 | AP79: 0 | AQ79: 0 | AR79: 0 | AS79: 0 | AT79: 0 | AU79: 0 | AY79: No | AZ79: W664703 | BA79: 0 | BC79: I09180 | BF79: S0362003
A80: W0682661 | B80: 10000 | C80: 20000 | D80: 45754 | E80: 502LAUGH | F80: 9:18:57 am | G80: 59470/59469 | I80: 1 | J80: Yes | K80: 73 | L80: PM59 | M80: 65271 | P80: 45749 | R80: 12 | S80: 783252 | T80: PE | U80: MT-1000173-00REV0003 | V80: 0 | W80: 814353 | X80: -31101 | Y80: 0 | Z80: 0 | AA80: 0 | AD80: 0 | AM80: MT-1000173-00REV008 | AN80: Z26002 | AP80: 0 | AQ80: 0 | AR80: 0 | AS80: 0 | AT80: 0 | AU80: 0 | AY80: No | AZ80: W664723 | BA80: 0 | BC80: Z26002 | BF80: S0362021
A81: W0682662 | B81: 10000 | C81: 30000 | D81: 45750 | E81: 502LAUGH | F81: 8:42:45 am | G81: 59470 | I81: 2 | J81: Yes | K81: 96 | L81: QM87 | M81: 30625 | P81: 45749 | R81: 6 | S81: 183750 | T81: PE | U81: MT-1000241-907RE0001 | V81: 0 | W81: 183750 | X81: 0 | Y81: 0 | Z81: 0 | AA81: 0 | AD81: 0 | AM81: MT-1000241-907REV005 | AN81: Z26002 | AP81: 0 | AQ81: 0 | AR81: 0 | AS81: 0 | AT81: 0 | AU81: 0 | AY81: No | AZ81: W663966 | BA81: 0 | BC81: Z26002 | BF81: S0362021
A82: W0682667 | B82: 10000 | C82: 30000 | D82: 45749 | E82: 502LAUGH | F82: 2:20:32 pm | G82: J00WT7100 | I82: 2 | J82: Yes | K82: 71 | L82: PS95 | M82: 1250 | P82: 45749 | R82: 4 | S82: 5000 | T82: PE | U82: 86090840001 | V82: 0 | W82: 5000 | X82: 0 | Y82: 0 | Z82: 0 | AA82: 0 | AD82: 0 | AM82: 8609084 | AN82: B02083 | AP82: 0 | AQ82: 0 | AR82: 0 | AS82: 0 | AT82: 0 | AU82: 0 | AY82: No | AZ82: W664725 | BA82: 0 | BC82: B02083 | BF82: S0362024
A83: W0682668 | B83: 10000 | C83: 20000 | D83: 45749 | E83: 502LAUGH | F83: 2:20:32 pm | G83: J00WT7100 | I83: 2 | J83: Yes | K83: 71 | L83: PS95 | M83: 1250 | P83: 45749 | R83: 4 | S83: 5000 | T83: PE | U83: 86090860001 | V83: 0 | W83: 5000 | X83: 0 | Y83: 0 | Z83: 0 | AA83: 0 | AD83: 0 | AM83: 8609086 | AN83: B02083 | AP83: 0 | AQ83: 0 | AR83: 0 | AS83: 0 | AT83: 0 | AU83: 0 | AY83: No | AZ83: W664726 | BA83: 0 | BC83: B02083 | BF83: S0362024
A84: W0682670 | B84: 10000 | C84: 10000 | D84: 45751 | E84: 502LAUGH | F84: 0.48287037 | G84: J00WT7100 | I84: 1 | J84: Yes | K84: 72 | L84: PMJ4 | M84: 3834 | P84: 45749 | R84: 6 | S84: 23004 | T84: PE | U84: 86090880001 | V84: 0 | W84: 18000 | X84: 5004 | Y84: 0 | Z84: 0 | AA84: 0 | AD84: 0 | AM84: 8609088 | AN84: B02083 | AP84: 0 | AQ84: 0 | AR84: 0 | AS84: 0 | AT84: 0 | AU84: 0 | AY84: No | AZ84: W664728 | BA84: 0 | BC84: B02083 | BF84: S0362024
A85: W0682671 | B85: 10000 | C85: 10000 | D85: 45750 | E85: 502LAUGH | F85: 8:35:46 am | G85: J00WT7100 | I85: 1 | J85: Yes | K85: 72 | L85: PMJ4 | M85: 2334 | P85: 45749 | R85: 6 | S85: 14004 | T85: PE | U85: 86090890001 | V85: 0 | W85: 10000 | X85: 4004 | Y85: 0 | Z85: 0 | AA85: 0 | AD85: 0 | AM85: 8609089 | AN85: B02083 | AP85: 0 | AQ85: 0 | AR85: 0 | AS85: 0 | AT85: 0 | AU85: 0 | AY85: No | AZ85: W664729 | BA85: 0 | BC85: B02083 | BF85: S0362024
A86: W0682671 | B86: 10000 | C86: 20000 | D86: 45750 | E86: 502LAUGH | F86: 8:35:46 am | G86: J00WT7100 | I86: 2 | J86: Yes | K86: 71 | L86: PS95 | M86: 1667 | P86: 45749 | R86: 6 | S86: 10002 | T86: PE | U86: 86090890001 | V86: 0 | W86: 10000 | X86: 2 | Y86: 0 | Z86: 0 | AA86: 0 | AD86: 0 | AM86: 8609089 | AN86: B02083 | AP86: 0 | AQ86: 0 | AR86: 0 | AS86: 0 | AT86: 0 | AU86: 0 | AY86: No | AZ86: W664729 | BA86: 0 | BC86: B02083 | BF86: S0362024
A87: W0682673 | B87: 10000 | C87: 10000 | D87: 45751 | E87: 502LAUGH | F87: 8:53:18 am | G87: E190912129 | I87: 1 | J87: Yes | K87: 63 | L87: PM80 | M87: 1334 | P87: 45749 | R87: 30 | S87: 40020 | T87: PE | U87: 100542001-3M66900001 | V87: 0 | W87: 40000 | X87: 20 | Y87: 0 | Z87: 0 | AA87: 0 | AD87: 0 | AM87: 100542001-3M6690SP | AN87: S19314 | AP87: 0 | AQ87: 0 | AR87: 0 | AS87: 0 | AT87: 0 | AU87: 0 | AY87: No | AZ87: W664731 | BA87: 0 | BC87: S19314 | BF87: H0064900
A88: W0682792 | B88: 10000 | C88: 10000 | D88: 45749 | E88: 502LAUGH | F88: 5:41:53 pm | G88: U0B07S008/4723U8017 | I88: 1 | J88: Yes | K88: 61 | L88: PM68 | M88: 2000 | P88: 45749 | R88: 5 | S88: 10000 | T88: PE | U88: 2V642190001 | V88: 0 | W88: 10000 | X88: 0 | Y88: 0 | Z88: 0 | AA88: 0 | AD88: 0 | AM88: 2V64219 | AN88: T20198 | AP88: 0 | AQ88: 0 | AR88: 0 | AS88: 0 | AT88: 0 | AU88: 0 | AY88: No | AZ88: W664753 | BA88: 0 | BC88: T20198 | BF88: S0362160
A89: W0682803 | B89: 10000 | C89: 10000 | D89: 45755 | E89: 502LAUGH | F89: 2:16:22 pm | G89: BYF039-01 | I89: 1 | J89: Yes | K89: 88 | L89: PP24 | M89: 1300 | P89: 45749 | R89: 1 | S89: 1300 | T89: PE | U89: BMS-144X38MM0001 | V89: 0 | W89: 1000 | X89: 300 | Y89: 0 | Z89: 0 | AA89: 0 | AD89: 0 | AM89: BMS-144X38MM | AN89: S19671 | AP89: 0 | AQ89: 0 | AR89: 0 | AS89: 0 | AT89: 0 | AU89: 0 | AY89: No | AZ89: W664756 | BA89: 0 | BC89: S19671 | BF89: S0362169
A90: W0682804 | B90: 10000 | C90: 10000 | D90: 45755 | E90: 502LAUGH | F90: 2:17:24 pm | G90: BXC030-01 | I90: 1 | J90: Yes | K90: 88 | L90: PP24 | M90: 1500 | P90: 45749 | R90: 1 | S90: 1500 | T90: PE | U90: BMS-60X20MM0001 | V90: 0 | W90: 1000 | X90: 500 | Y90: 0 | Z90: 0 | AA90: 0 | AD90: 0 | AM90: BMS-60X20MM | AN90: S19671 | AP90: 0 | AQ90: 0 | AR90: 0 | AS90: 0 | AT90: 0 | AU90: 0 | AY90: No | AZ90: W664757 | BA90: 0 | BC90: S19671 | BF90: S0362169
A91: W0682813 | B91: 10000 | C91: 10000 | D91: 45750 | E91: 502LAUGH | F91: 0.42402778 | G91: 2101818U5/M0B7C2220 | I91: 1 | J91: Yes | K91: 79 | L91: PM16 | M91: 286 | P91: 45749 | R91: 245 | S91: 70070 | T91: PE | U91: 86.B9480001 | V91: 0 | W91: 50000 | X91: 20070 | Y91: 0 | Z91: 0 | AA91: 0 | AD91: 0 | AM91: 86.B948 | AN91: C03423 | AP91: 0 | AQ91: 0 | AR91: 0 | AS91: 0 | AT91: 0 | AU91: 0 | AY91: No | AZ91: W664760 | BA91: 0 | BC91: C03423 | BF91: S0362176

Sheet 03-Apr
A1: Production Output
A2: Filter: Date Completed: 03/04/25
A4: Work Order No. | B4: Work Order Line No. | C4: WO Journal Line No. | D4: Add Date | E4: Add User | F4: Add Time | G4: Material Batch No. | H4: Die Cut | I4: Process No. | J4: Posted | K4: Machine Code | L4: Staff Code | M4: No. of Press | N4: Date Started | O4: Time Started | P4: Date Completed | Q4: Time Completed | R4: No. of Ups | S4: Printed Quantity | T4: Journal Type | U4: Item Code | V4: Quantity | W4: QC Approved Quantity | X4: Rejected Quantity | Y4: Roll | Z4: Length | AA4: Width | AB4: Length UOM | AC4: Width UOM | AD4: RM Quantity | AE4: Material Code | AF4: Variant Code | AG4: Request Delivery Date | AH4: Non QC Record | AI4: Link to Line No. | AJ4: Related | AK4: Expire Date | AL4: Label Remark | AM4: Customer Part Number | AN4: Customer Code | AO4: ddmm | AP4: Label Packing Quantity 1 | AQ4: Label Quantity 1 | AR4: Label Packing Quantity 2 | AS4: Label Quantity 2 | AT4: Label Packing Quantity 3 | AU4: Label Quantity 3 | AV4: UOM for Label Printing | AW4: QC Inspector | AX4: Summarised Period | AY4: Summarised | AZ4: Posted Work Order No. | BA4: Colour | BB4: Currency | BC4: Ref Customer | BD4: Group | BE4: PO | BF4: Source Doc. No.
A5: W0678968 | B5: 10000 | C5: 40000 | D5: 45751 | E5: 502LAUGH | F5: 2:54:08 pm | G5: M0BJQ96701065/M0BTQ4840 | H5: FSC30254 | I5: 1 | J5: No | K5: 94 | L5: PM09 | M5: 10000 | P5: 45750 | R5: 4 | S5: 40000 | T5: PE | U5: L001-773057-00000006 | V5: 0 | W5: 0 | X5: 0 | Y5: 0 | Z5: 0 | AA5: 0 | AD5: 0 | AH5: No | AI5: 0 | AJ5: No | AM5: L001-773057-000006CM | AN5: W23041-TH | AP5: 0 | AQ5: 0 | AR5: 0 | AS5: 0 | AT5: 0 | AU5: 0 | AY5: No | BC5: W23041-TH | BF5: H0064486
A6: W0672069 | B6: 10000 | C6: 10000 | D6: 45761 | E6: 502LAUGH | F6: 9:00:06 am | G6: 4072413U5 | I6: 1 | J6: Yes | K6: 82 | L6: PM11 | M6: 100000 | P6: 45750 | R6: 1 | S6: 100000 | T6: PE | U6: 48X110MM TRANS L0001 | V6: 0 | W6: 100000 | X6: 0 | Y6: 0 | Z6: 0 | AA6: 0 | AD6: 0 | AM6: 48X110MM TRANS LBL | AN6: Z26000 | AP6: 0 | AQ6: 0 | AR6: 0 | AS6: 0 | AT6: 0 | AU6: 0 | AY6: No | AZ6: W664977 | BA6: 0 | BC6: Z26000 | BF6: ZSA101609
A7: W0676859 | B7: 10000 | C7: 30000 | D7: 45758 | E7: 502LAUGH | F7: 0.46591435 | G7: BZC064-08 | I7: 1 | J7: Yes | K7: 93N | L7: PC02 | M7: 14334 | P7: 45750 | R7: 6 | S7: 86004 | T7: PE | U7: RR 6X6-WHITE0001 | V7: 0 | W7: 80884 | X7: 5120 | Y7: 0 | Z7: 0 | AA7: 0 | AD7: 0 | AM7: RR 6X6-WHITE | AN7: E05203 | AP7: 0 | AQ7: 0 | AR7: 0 | AS7: 0 | AT7: 0 | AU7: 0 | AY7: No | AZ7: W664979 | BA7: 0 | BC7: E05203 | BF7: S0355056
A8: W0676859 | B8: 10000 | C8: 50000 | D8: 45758 | E8: 502LAUGH | F8: 0.46591435 | G8: BZC064-08 | I8: 2 | J8: Yes | K8: 76 | L8: PM46 | M8: 97000 | P8: 45750 | R8: 2 | S8: 194000 | T8: PE | U8: RR 6X6-WHITE0001 | V8: 0 | W8: 205500 | X8: -11500 | Y8: 0 | Z8: 0 | AA8: 0 | AD8: 0 | AM8: RR 6X6-WHITE | AN8: E05203 | AP8: 0 | AQ8: 0 | AR8: 0 | AS8: 0 | AT8: 0 | AU8: 0 | AY8: No | AZ8: W664979 | BA8: 0 | BC8: E05203 | BF8: S0355056
A9: W0679518 | B9: 10000 | C9: 10000 | D9: 45754 | E9: 505KANGHS | F9: 8:43:15 am | G9: J00VB8021 | I9: 1 | J9: Yes | K9: 102 | L9: PM61 | M9: 27000 | P9: 45750 | R9: 2 | S9: 54000 | T9: PE | U9: R001-410200001 | V9: 0 | W9: 54000 | X9: 0 | Y9: 0 | Z9: 0 | AA9: 0 | AD9: 0 | AM9: R001-41020 | AN9: R18131 | AP9: 0 | AQ9: 0 | AR9: 0 | AS9: 0 | AT9: 0 | AU9: 0 | AY9: No | AZ9: W664493 | BA9: 0 | BC9: R18131 | BF9: S0358294
A10: W0679624 | B10: 10000 | C10: 20000 | D10: 45755 | E10: 502LAUGH | F10: 8:53:34 am | G10: E04OB9810 | I10: 2 | J10: Yes | K10: 62 | L10: PMJ0 | M10: 35000 | P10: 45750 | R10: 1 | S10: 35000 | T10: PE | U10: Y00-0000928-000001 | V10: 0 | W10: 35000 | X10: 0 | Y10: 0 | Z10: 0 | AA10: 0 | AD10: 0 | AM10: 300-0000396-00 | AN10: F06170-JIANGSU | AP10: 0 | AQ10: 0 | AR10: 0 | AS10: 0 | AT10: 0 | AU10: 0 | AY10: No | AZ10: W664495 | BA10: 0 | BC10: F06170-JIANGSU | BF10: S0358339
A11: W0680991 | B11: 10000 | C11: 20000 | D11: 45751 | E11: 502LAUGH | F11: 0.44171296 | G11: M0BRZ2270990 | I11: 1 | J11: Yes | K11: 78 | L11: PM84 | M11: 12500 | P11: 45750 | R11: 4 | S11: 50000 | T11: PE | U11: 5180-38640001 | V11: 0 | W11: 50000 | X11: 0 | Y11: 0 | Z11: 0 | AA11: 0 | AD11: 0 | AM11: 5180-3864 | AN11: H08031-JIM | AP11: 0 | AQ11: 0 | AR11: 0 | AS11: 0 | AT11: 0 | AU11: 0 | AY11: No | AZ11: W664086 | BA11: 0 | BC11: H08031-JIM | BF11: S0360900
A12: W0681128 | B12: 10000 | C12: 10000 | D12: 45751 | E12: 502LAUGH | F12: 8:39:49 am | G12: 4067S1 | I12: 1 | J12: Yes | K12: 22 | L12: PS13 | M12: 1000 | P12: 45750 | R12: 1 | S12: 1000 | T12: PE | U12: 806778 REV4010001 | V12: 0 | W12: 1000 | X12: 0 | Y12: 0 | Z12: 0 | AA12: 0 | AD12: 0 | AM12: 806778 REV401 | AN12: V22000 | AP12: 0 | AQ12: 0 | AR12: 0 | AS12: 0 | AT12: 0 | AU12: 0 | AY12: No | AZ12: W664519 | BA12: 0 | BC12: V22000 | BF12: S0361013
A13: W0681350 | B13: 10000 | C13: 10000 | D13: 45751 | E13: 502LAUGH | F13: 8:36:19 am | G13: SG-5644655 01 | I13: 1 | J13: Yes | K13: 59 | L13: PS74 | M13: 5000 | P13: 45750 | R13: 6 | S13: 30000 | T13: PE | U13: 15058371 REVB0001 | V13: 0 | W13: 30000 | X13: 0 | Y13: 0 | Z13: 0 | AA13: 0 | AD13: 0 | AM13: 15058371 REVB | AN13: I09180 | AP13: 0 | AQ13: 0 | AR13: 0 | AS13: 0 | AT13: 0 | AU13: 0 | AY13: No | AZ13: W664093 | BA13: 0 | BC13: I09180 | BF13: S0361100
A14: W0681351 | B14: 10000 | C14: 10000 | D14: 45751 | E14: 502LAUGH | F14: 8:36:19 am | G14: SG-5644655 01 | I14: 1 | J14: Yes | K14: 59 | L14: PS74 | M14: 5000 | P14: 45750 | R14: 6 | S14: 30000 | T14: PE | U14: 15058371 REVB0001 | V14: 0 | W14: 30000 | X14: 0 | Y14: 0 | Z14: 0 | AA14: 0 | AD14: 0 | AM14: 15058371 REVB | AN14: I09180 | AP14: 0 | AQ14: 0 | AR14: 0 | AS14: 0 | AT14: 0 | AU14: 0 | AY14: No | AZ14: W664094 | BA14: 0 | BC14: I09180 | BF14: S0361101
A15: W0681512 | B15: 10000 | C15: 10000 | D15: 45750 | E15: 502LAUGH | F15: 0.42506944 | G15: N0BTQ4850 | I15: 1 | J15: Yes | K15: 94 | L15: PM09 | M15: 5000 | P15: 45750 | R15: 4 | S15: 20000 | T15: PE | U15: L001-773057-00000005 | V15: 0 | W15: 20000 | X15: 0 | Y15: 0 | Z15: 0 | AA15: 0 | AD15: 0 | AM15: L001-773057-000005CM | AN15: W23041-TH | AP15: 0 | AQ15: 0 | AR15: 0 | AS15: 0 | AT15: 0 | AU15: 0 | AY15: No | AZ15: W664104 | BA15: 0 | BC15: W23041-TH | BF15: H0064785
A16: W0681636 | B16: 10000 | C16: 20000 | D16: 45750 | E16: 502LAUGH | F16: 0.46141204 | G16: SG-5644655 01 | I16: 1 | J16: Yes | K16: 59 | L16: PS74 | M16: 1000 | P16: 45750 | R16: 6 | S16: 6000 | T16: PE | U16: 15058366 REVB0001 | V16: 0 | W16: 6000 | X16: 0 | Y16: 0 | Z16: 0 | AA16: 0 | AD16: 0 | AM16: 15058366 REVB | AN16: I09180 | AP16: 0 | AQ16: 0 | AR16: 0 | AS16: 0 | AT16: 0 | AU16: 0 | AY16: No | AZ16: W664111 | BA16: 0 | BC16: I09180 | BF16: S0361256
A17: W0681637 | B17: 10000 | C17: 10000 | D17: 45750 | E17: 502LAUGH | F17: 0.46141204 | G17: SG-5644655 01 | I17: 1 | J17: Yes | K17: 59 | L17: PS74 | M17: 1000 | P17: 45750 | R17: 6 | S17: 6000 | T17: PE | U17: 15058366 REVB0001 | V17: 0 | W17: 6000 | X17: 0 | Y17: 0 | Z17: 0 | AA17: 0 | AD17: 0 | AM17: 15058366 REVB | AN17: I09180 | AP17: 0 | AQ17: 0 | AR17: 0 | AS17: 0 | AT17: 0 | AU17: 0 | AY17: No | AZ17: W664112 | BA17: 0 | BC17: I09180 | BF17: S0361257
A18: W0681637 | B18: 20000 | C18: 10000 | D18: 45750 | E18: 502LAUGH | F18: 0.46141204 | G18: SG-5644655 01 | I18: 1 | J18: Yes | K18: 59 | L18: PS74 | M18: 1000 | P18: 45750 | R18: 6 | S18: 6000 | T18: PE | U18: 15058366 REVB0001 | V18: 0 | W18: 6000 | X18: 0 | Y18: 0 | Z18: 0 | AA18: 0 | AD18: 0 | AM18: 15058366 REVB | AN18: I09180 | AP18: 0 | AQ18: 0 | AR18: 0 | AS18: 0 | AT18: 0 | AU18: 0 | AY18: No | AZ18: W664112 | BA18: 0 | BC18: I09180 | BF18: S0361257
A19: W0681675 | B19: 10000 | C19: 30000 | D19: 45751 | E19: 502LAUGH | F19: 8:34:07 am | G19: U4A04S306 | I19: 2 | J19: Yes | K19: 60 | L19: PM30 | M19: 4000 | P19: 45750 | R19: 1 | S19: 4000 | T19: PE | U19: 60005003-D LIGHT0001 | V19: 0 | W19: 2000 | X19: 2000 | Y19: 0 | Z19: 0 | AA19: 0 | AD19: 0 | AM19: 60005003-D LIGHT GRN | AN19: B02083 | AP19: 0 | AQ19: 0 | AR19: 0 | AS19: 0 | AT19: 0 | AU19: 0 | AY19: No | AZ19: W664113 | BA19: 0 | BC19: B02083 | BF19: S0361285
A20: W0681679 | B20: 10000 | C20: 20000 | D20: 45751 | E20: 502LAUGH | F20: 8:33:27 am | G20: U4A04S306 | I20: 2 | J20: Yes | K20: 60 | L20: PM30 | M20: 4900 | P20: 45750 | R20: 1 | S20: 4900 | T20: PE | U20: 60005003-D-IVORY0001 | V20: 0 | W20: 3000 | X20: 1900 | Y20: 0 | Z20: 0 | AA20: 0 | AD20: 0 | AM20: 60005003-D-IVORY | AN20: B02083 | AP20: 0 | AQ20: 0 | AR20: 0 | AS20: 0 | AT20: 0 | AU20: 0 | AY20: No | AZ20: W664115 | BA20: 0 | BC20: B02083 | BF20: S0361285
A21: W0681682 | B21: 10000 | C21: 20000 | D21: 45751 | E21: 502LAUGH | F21: 8:35:18 am | G21: U4A04S306 | I21: 2 | J21: Yes | K21: 60 | L21: PM30 | M21: 3900 | P21: 45750 | R21: 1 | S21: 3900 | T21: PE | U21: 60005003-D-YELLO0001 | V21: 0 | W21: 2000 | X21: 1900 | Y21: 0 | Z21: 0 | AA21: 0 | AD21: 0 | AM21: 60005003-D-YELLOW | AN21: B02083 | AP21: 0 | AQ21: 0 | AR21: 0 | AS21: 0 | AT21: 0 | AU21: 0 | AY21: No | AZ21: W664116 | BA21: 0 | BC21: B02083 | BF21: S0361285
A22: W0681740 | B22: 10000 | C22: 10000 | D22: 45754 | E22: 505KANGHS | F22: 8:51:41 am | G22: SG-5650696 | I22: 1 | J22: Yes | K22: 73N | L22: PM18 | M22: 18000 | P22: 45750 | R22: 12 | S22: 216000 | T22: PE | U22: 80256230001 | V22: 0 | W22: 216000 | X22: 0 | Y22: 0 | Z22: 0 | AA22: 0 | AD22: 0 | AM22: 8025623 | AN22: B02083 | AP22: 0 | AQ22: 0 | AR22: 0 | AS22: 0 | AT22: 0 | AU22: 0 | AY22: No | AZ22: W664562 | BA22: 0 | BC22: B02083 | BF22: S0361322
A23: W0681897 | B23: 10000 | C23: 20000 | D23: 45754 | E23: 502LAUGH | F23: 8:35:07 am | G23: 10620258037 | I23: 2 | J23: Yes | K23: 77 | L23: PM74 | M23: 1410 | P23: 45750 | R23: 66 | S23: 93060 | T23: PE | U23: E5Z02-80008-FT0001 | V23: 0 | W23: 80000 | X23: 13060 | Y23: 0 | Z23: 0 | AA23: 0 | AD23: 0 | AM23: E5Z02-80008-FT | AN23: H08031-JIM-M | AP23: 0 | AQ23: 0 | AR23: 0 | AS23: 0 | AT23: 0 | AU23: 0 | AY23: No | AZ23: W664578 | BA23: 0 | BC23: H08031-JIM-M | BF23: S0361406
A24: W0681907 | B24: 10000 | C24: 50000 | D24: 45751 | E24: 502LAUGH | F24: 5:33:58 pm | G24: 10620258042/10620258038 | I24: 2 | J24: Yes | K24: 77 | L24: PM74 | M24: 2728 | P24: 45750 | R24: 66 | S24: 180048 | T24: PE | U24: 3JB26-800010001 | V24: 0 | W24: 99320 | X24: 80728 | Y24: 0 | Z24: 0 | AA24: 0 | AD24: 0 | AM24: 3JB26-80001 | AN24: H08031-JIM-M | AP24: 0 | AQ24: 0 | AR24: 0 | AS24: 0 | AT24: 0 | AU24: 0 | AY24: No | AZ24: W664582 | BA24: 0 | BC24: H08031-JIM-M | BF24: S0361414
A25: W0681925 | B25: 10000 | C25: 20000 | D25: 45750 | E25: 502LAUGH | F25: 2:59:57 pm | G25: M0BTQ4840 | I25: 1 | J25: Yes | K25: 94 | L25: PM09 | M25: 5000 | P25: 45750 | R25: 4 | S25: 20000 | T25: PE | U25: L001-773057-00000005 | V25: 0 | W25: 20000 | X25: 0 | Y25: 0 | Z25: 0 | AA25: 0 | AD25: 0 | AM25: L001-773057-000005CM | AN25: W23041-TH | AP25: 0 | AQ25: 0 | AR25: 0 | AS25: 0 | AT25: 0 | AU25: 0 | AY25: No | AZ25: W664584 | BA25: 0 | BC25: W23041-TH | BF25: H0064817
A26: W0682027 | B26: 10000 | C26: 20000 | D26: 45750 | E26: 502LAUGH | F26: 5:39:51 pm | G26: TW1116349-04 | I26: 2 | J26: Yes | K26: 86 | L26: PS96 | M26: 2500 | P26: 45750 | R26: 12 | S26: 30000 | T26: PE | U26: P1S0455 60001 | V26: 0 | W26: 30000 | X26: 0 | Y26: 0 | Z26: 0 | AA26: 0 | AD26: 0 | AM26: P1S0455 6 | AN26: H08220 | AP26: 0 | AQ26: 0 | AR26: 0 | AS26: 0 | AT26: 0 | AU26: 0 | AY26: No | AZ26: W664139 | BA26: 0 | BC26: H08220 | BF26: S0361538
A27: W0682067 | B27: 10000 | C27: 10000 | D27: 45751 | E27: 502LAUGH | F27: 8:39:49 am | G27: A431833/BYG115-01/XHX2412242227 | I27: 1 | J27: Yes | K27: 60 | L27: PM30 | M27: 50 | P27: 45750 | R27: 5 | S27: 250 | T27: PE | U27: TPK-884595-00100001 | V27: 0 | W27: 250 | X27: 0 | Y27: 0 | Z27: 0 | AA27: 0 | AD27: 0 | AM27: TPK-884595-0010 | AN27: Z26002 | AP27: 0 | AQ27: 0 | AR27: 0 | AS27: 0 | AT27: 0 | AU27: 0 | AY27: No | AZ27: W664140 | BA27: 0 | BC27: Z26002 | BF27: ZSA101775
A28: W0682068 | B28: 10000 | C28: 10000 | D28: 45751 | E28: 502LAUGH | F28: 8:39:49 am | G28: A431833/BYG115-01/XHX2412242227 | I28: 1 | J28: Yes | K28: 60 | L28: PM30 | M28: 50 | P28: 45750 | R28: 5 | S28: 250 | T28: PE | U28: TPK-884596-00100001 | V28: 0 | W28: 250 | X28: 0 | Y28: 0 | Z28: 0 | AA28: 0 | AD28: 0 | AM28: TPK-884596-0010 | AN28: Z26002 | AP28: 0 | AQ28: 0 | AR28: 0 | AS28: 0 | AT28: 0 | AU28: 0 | AY28: No | AZ28: W664141 | BA28: 0 | BC28: Z26002 | BF28: ZSA101775
A29: W0682092 | B29: 10000 | C29: 10000 | D29: 45754 | E29: 505KANGHS | F29: 1:51:38 pm | G29: M0BUG7190/M0BUQ9671 | I29: 1 | J29: Yes | K29: 29 | L29: PS70 | M29: 24000 | P29: 45750 | R29: 2 | S29: 48000 | T29: PE | U29: 100823881-75367 0001 | V29: 0 | W29: 48000 | X29: 0 | Y29: 0 | Z29: 0 | AA29: 0 | AD29: 0 | AM29: 100823881-75367 A | AN29: S19081-TH | AP29: 0 | AQ29: 0 | AR29: 0 | AS29: 0 | AT29: 0 | AU29: 0 | AY29: No | AZ29: W664593 | BA29: 0 | BC29: S19081-TH | BF29: H0064860
A30: W0682108 | B30: 10000 | C30: 10000 | D30: 45756 | E30: 502LAUGH | F30: 0.44246528 | G30: M0BUQ9711/M0BUQ9671/M0BUG7190/M0BUF4292 | I30: 1 | J30: Yes | K30: 70 | L30: PS84 | M30: 60000 | P30: 45750 | R30: 2 | S30: 120000 | T30: PE | U30: 725427400 REVA0002 | V30: 0 | W30: 120000 | X30: 0 | Y30: 0 | Z30: 0 | AA30: 0 | AD30: 0 | AM30: 725427400 REVA | AN30: S19081-TH | AP30: 0 | AQ30: 0 | AR30: 0 | AS30: 0 | AT30: 0 | AU30: 0 | AY30: No | AZ30: W664600 | BA30: 0 | BC30: S19081-TH | BF30: H0064876
A31: W0682170 | B31: 10000 | C31: 20000 | D31: 45750 | E31: 502LAUGH | F31: 1:46:38 pm | G31: SG-5644655 01 | I31: 1 | J31: Yes | K31: 59 | L31: PS74 | M31: 1000 | P31: 45750 | R31: 6 | S31: 6000 | T31: PE | U31: 15058360-3K-R8LT0001 | V31: 0 | W31: 6000 | X31: 0 | Y31: 0 | Z31: 0 | AA31: 0 | AD31: 0 | AM31: 15058360-3K-R8LT-28 | AN31: I09180 | AP31: 0 | AQ31: 0 | AR31: 0 | AS31: 0 | AT31: 0 | AU31: 0 | AY31: No | AZ31: W664146 | BA31: 0 | BC31: I09180 | BF31: S0361671
A32: W0682170 | B32: 20000 | C32: 10000 | D32: 45750 | E32: 502LAUGH | F32: 1:46:38 pm | G32: SG-5644655 01 | I32: 1 | J32: Yes | K32: 59 | L32: PS74 | M32: 1000 | P32: 45750 | R32: 6 | S32: 6000 | T32: PE | U32: 15058360-3K-R8LT0001 | V32: 0 | W32: 6000 | X32: 0 | Y32: 0 | Z32: 0 | AA32: 0 | AD32: 0 | AM32: 15058360-3K-R8LT-28 | AN32: I09180 | AP32: 0 | AQ32: 0 | AR32: 0 | AS32: 0 | AT32: 0 | AU32: 0 | AY32: No | AZ32: W664146 | BA32: 0 | BC32: I09180 | BF32: S0361671
A33: W0682174 | B33: 10000 | C33: 10000 | D33: 45751 | E33: 502LAUGH | F33: 8:36:19 am | G33: SG-5644655 01 | I33: 1 | J33: Yes | K33: 59 | L33: PS74 | M33: 5000 | P33: 45750 | R33: 6 | S33: 30000 | T33: PE | U33: 15058371 REVB0001 | V33: 0 | W33: 30000 | X33: 0 | Y33: 0 | Z33: 0 | AA33: 0 | AD33: 0 | AM33: 15058371 REVB | AN33: I09180 | AP33: 0 | AQ33: 0 | AR33: 0 | AS33: 0 | AT33: 0 | AU33: 0 | AY33: No | AZ33: W664147 | BA33: 0 | BC33: I09180 | BF33: S0361675
A34: W0682224 | B34: 10000 | C34: 20000 | D34: 45751 | E34: 502LAUGH | F34: 3:41:29 pm | G34: TW1116349-04 | I34: 2 | J34: Yes | K34: 86 | L34: PS96 | M34: 7000 | P34: 45750 | R34: 12 | S34: 84000 | T34: PE | U34: P1S0455 60001 | V34: 0 | W34: 84000 | X34: 0 | Y34: 0 | Z34: 0 | AA34: 0 | AD34: 0 | AM34: P1S0455 6 | AN34: H08220 | AP34: 0 | AQ34: 0 | AR34: 0 | AS34: 0 | AT34: 0 | AU34: 0 | AY34: No | AZ34: W664153 | BA34: 0 | BC34: H08220 | BF34: S0361708
A35: W0682241 | B35: 10000 | C35: 10000 | D35: 45751 | E35: 502LAUGH | F35: 4:17:10 pm | G35: J00WT7100 | I35: 1 | J35: Yes | K35: 72 | L35: PM17 | M35: 2500 | P35: 45750 | R35: 6 | S35: 15000 | T35: PE | U35: 80834720001 | V35: 0 | W35: 10000 | X35: 5000 | Y35: 0 | Z35: 0 | AA35: 0 | AD35: 0 | AM35: 8083472 | AN35: B02083 | AP35: 0 | AQ35: 0 | AR35: 0 | AS35: 0 | AT35: 0 | AU35: 0 | AY35: No | AZ35: W664619 | BA35: 0 | BC35: B02083 | BF35: S0361716
A36: W0682242 | B36: 10000 | C36: 10000 | D36: 45756 | E36: 502LAUGH | F36: 8:34:05 am | G36: J00WT7100 | I36: 1 | J36: Yes | K36: 72 | L36: PM17 | M36: 1750 | P36: 45750 | R36: 4 | S36: 7000 | T36: PE | U36: 80834730001 | V36: 0 | W36: 5000 | X36: 2000 | Y36: 0 | Z36: 0 | AA36: 0 | AD36: 0 | AM36: 8083473 | AN36: B02083 | AP36: 0 | AQ36: 0 | AR36: 0 | AS36: 0 | AT36: 0 | AU36: 0 | AY36: No | AZ36: W664620 | BA36: 0 | BC36: B02083 | BF36: S0361716
A37: W0682299 | B37: 10000 | C37: 10000 | D37: 45751 | E37: 502LAUGH | F37: 8:32:42 am | G37: L5305U8039 | I37: 1 | J37: Yes | K37: 65 | L37: PMJ7 | M37: 6667 | P37: 45750 | R37: 3 | S37: 20001 | T37: PE | U37: LABEL CLNRM-2X50001 | V37: 0 | W37: 20000 | X37: 1 | Y37: 0 | Z37: 0 | AA37: 0 | AD37: 0 | AM37: LABEL CLNRM-2X5 | AN37: I09146 | AP37: 0 | AQ37: 0 | AR37: 0 | AS37: 0 | AT37: 0 | AU37: 0 | AY37: No | AZ37: W664157 | BA37: 0 | BC37: I09146 | BF37: S0361746
A38: W0682336 | B38: 10000 | C38: 10000 | D38: 45750 | E38: 502LAUGH | F38: 0.42506944 | G38: L5305U8039 | I38: 1 | J38: Yes | K38: 78 | L38: PM84 | M38: 3000 | P38: 45750 | R38: 1 | S38: 3000 | T38: PE | U38: SCREAMER LB-80X10001 | V38: 0 | W38: 3000 | X38: 0 | Y38: 0 | Z38: 0 | AA38: 0 | AD38: 0 | AM38: SCREAMER LB-80X134MM | AN38: I09146 | AP38: 0 | AQ38: 0 | AR38: 0 | AS38: 0 | AT38: 0 | AU38: 0 | AY38: No | AZ38: W664161 | BA38: 0 | BC38: I09146 | BF38: S0361843
A39: W0682348 | B39: 10000 | C39: 10000 | D39: 45751 | E39: 502LAUGH | F39: 8:40:17 am | G39: 4177S1 | I39: 1 | J39: Yes | K39: 61 | L39: PM68 | M39: 1000 | P39: 45750 | R39: 5 | S39: 5000 | T39: PE | U39: 704845 INDEX000001 | V39: 0 | W39: 5000 | X39: 0 | Y39: 0 | Z39: 0 | AA39: 0 | AD39: 0 | AM39: 704845 INDEX00 | AN39: V22000-RO | AP39: 0 | AQ39: 0 | AR39: 0 | AS39: 0 | AT39: 0 | AU39: 0 | AY39: No | AZ39: W664162 | BA39: 0 | BC39: V22000-RO | BF39: S0361761
A40: W0682350 | B40: 10000 | C40: 20000 | D40: 45751 | E40: 502LAUGH | F40: 5:17:08 pm | G40: 10620258022 | I40: 2 | J40: Yes | K40: 77 | L40: PM74 | M40: 130 | P40: 45750 | R40: 154 | S40: 20020 | T40: PE | U40: G0Z24-800110001 | V40: 0 | W40: 5000 | X40: 15020 | Y40: 0 | Z40: 0 | AA40: 0 | AD40: 0 | AM40: G0Z24-80011 | AN40: H08031-JIM | AP40: 0 | AQ40: 0 | AR40: 0 | AS40: 0 | AT40: 0 | AU40: 0 | AY40: No | AZ40: W665431 | BA40: 0 | BC40: H08031-JIM | BF40: S0361847
A41: W0682378 | B41: 10000 | C41: 10000 | D41: 45750 | E41: 502LAUGH | F41: 3:56:06 pm | G41: 4067S1 | I41: 1 | J41: Yes | K41: 22 | L41: PS13 | M41: 5000 | P41: 45750 | R41: 2 | S41: 10000 | T41: PE | U41: 805589 REV4000001 | V41: 0 | W41: 10000 | X41: 0 | Y41: 0 | Z41: 0 | AA41: 0 | AD41: 0 | AM41: 805589 REV400 | AN41: V22000 | AP41: 0 | AQ41: 0 | AR41: 0 | AS41: 0 | AT41: 0 | AU41: 0 | AY41: No | AZ41: W664163 | BA41: 0 | BC41: V22000 | BF41: S0361869
A42: W0682397 | B42: 10000 | C42: 20000 | D42: 45751 | E42: 502LAUGH | F42: 2:52:49 pm | G42: 10656256095 | I42: 2 | J42: Yes | K42: 77 | L42: PM74 | M42: 1364 | P42: 45750 | R42: 66 | S42: 90024 | T42: PE | U42: B3B28-80007-FT0001 | V42: 0 | W42: 80000 | X42: 10024 | Y42: 0 | Z42: 0 | AA42: 0 | AD42: 0 | AM42: B3B28-80007-FT | AN42: H08031-JIM-M | AP42: 0 | AQ42: 0 | AR42: 0 | AS42: 0 | AT42: 0 | AU42: 0 | AY42: No | AZ42: W664631 | BA42: 0 | BC42: H08031-JIM-M | BF42: S0361875
A43: W0682398 | B43: 10000 | C43: 10000 | D43: 45758 | E43: 502LAUGH | F43: 8:41:31 am | G43: 10620258021/10620258023/10620258018 | I43: 1 | J43: Yes | K43: 79 | L43: PM16 | M43: 4108 | P43: 45750 | R43: 28 | S43: 115024 | T43: PE | U43: CZ107-80016-FT0001 | V43: 0 | W43: 100000 | X43: 15024 | Y43: 0 | Z43: 0 | AA43: 0 | AD43: 0 | AM43: CZ107-80016-FT | AN43: H08031-JIM-M | AP43: 0 | AQ43: 0 | AR43: 0 | AS43: 0 | AT43: 0 | AU43: 0 | AY43: No | AZ43: W664632 | BA43: 0 | BC43: H08031-JIM-M | BF43: S0361876
A44: W0682401 | B44: 10000 | C44: 10000 | D44: 45758 | E44: 502LAUGH | F44: 4:46:04 pm | G44: 10620258021/10620258023/10620258018 | I44: 1 | J44: Yes | K44: 79 | L44: PM16 | M44: 4108 | P44: 45750 | R44: 28 | S44: 115024 | T44: PE | U44: N9K04-80019-FT0001 | V44: 0 | W44: 100000 | X44: 15024 | Y44: 0 | Z44: 0 | AA44: 0 | AD44: 0 | AM44: N9K04-80019-FT | AN44: H08031-JIM-M | AP44: 0 | AQ44: 0 | AR44: 0 | AS44: 0 | AT44: 0 | AU44: 0 | AY44: No | AZ44: W665119 | BA44: 0 | BC44: H08031-JIM-M | BF44: S0361879
A45: W0682402 | B45: 10000 | C45: 10000 | D45: 45758 | E45: 502LAUGH | F45: 4:46:05 pm | G45: 10620258021/10620258023/10620258018 | I45: 1 | J45: Yes | K45: 79 | L45: PM16 | M45: 4108 | P45: 45750 | R45: 28 | S45: 115024 | T45: PE | U45: 3YM73-80008-FT0001 | V45: 0 | W45: 100000 | X45: 15024 | Y45: 0 | Z45: 0 | AA45: 0 | AD45: 0 | AM45: 3YM73-80008-FT | AN45: H08031-JIM-M | AP45: 0 | AQ45: 0 | AR45: 0 | AS45: 0 | AT45: 0 | AU45: 0 | AY45: No | AZ45: W664999 | BA45: 0 | BC45: H08031-JIM-M | BF45: S0361880
A46: W0682403 | B46: 10000 | C46: 10000 | D46: 45758 | E46: 502LAUGH | F46: 8:41:31 am | G46: 10620258021/10620258023/10620258018 | I46: 1 | J46: Yes | K46: 79 | L46: PM16 | M46: 4108 | P46: 45750 | R46: 28 | S46: 115024 | T46: PE | U46: 3YM77-80008-FT0001 | V46: 0 | W46: 100000 | X46: 15024 | Y46: 0 | Z46: 0 | AA46: 0 | AD46: 0 | AM46: 3YM77-80008-FT | AN46: H08031-JIM-M | AP46: 0 | AQ46: 0 | AR46: 0 | AS46: 0 | AT46: 0 | AU46: 0 | AY46: No | AZ46: W665000 | BA46: 0 | BC46: H08031-JIM-M | BF46: S0361881
A47: W0682404 | B47: 10000 | C47: 20000 | D47: 45757 | E47: 502LAUGH | F47: 2:40:20 pm | G47: 10656256091 | I47: 2 | J47: Yes | K47: 77 | L47: PM74 | M47: 3455 | P47: 45750 | R47: 66 | S47: 228030 | T47: PE | U47: 6ZD21-800010001 | V47: 0 | W47: 205000 | X47: 23030 | Y47: 0 | Z47: 0 | AA47: 0 | AD47: 0 | AM47: 6ZD21-80001 | AN47: H08031-JIM-M | AP47: 0 | AQ47: 0 | AR47: 0 | AS47: 0 | AT47: 0 | AU47: 0 | AY47: No | AZ47: W664634 | BA47: 0 | BC47: H08031-JIM-M | BF47: S0361882
A48: W0682405 | B48: 10000 | C48: 20000 | D48: 45755 | E48: 502LAUGH | F48: 1:05:56 pm | G48: 10656256095 | I48: 2 | J48: Yes | K48: 77 | L48: PM74 | M48: 1364 | P48: 45750 | R48: 66 | S48: 90024 | T48: PE | U48: E5Z01-80008-FT0001 | V48: 0 | W48: 80000 | X48: 10024 | Y48: 0 | Z48: 0 | AA48: 0 | AD48: 0 | AM48: E5Z01-80008-FT | AN48: H08031-JIM-M | AP48: 0 | AQ48: 0 | AR48: 0 | AS48: 0 | AT48: 0 | AU48: 0 | AY48: No | AZ48: W664635 | BA48: 0 | BC48: H08031-JIM-M | BF48: S0361883
A49: W0682406 | B49: 10000 | C49: 10000 | D49: 45758 | E49: 502LAUGH | F49: 8:39:38 am | G49: 10620258021/10620258023/10620258018 | I49: 1 | J49: Yes | K49: 79 | L49: PM16 | M49: 4108 | P49: 45750 | R49: 28 | S49: 115024 | T49: PE | U49: F6U62-80030-FT0001 | V49: 0 | W49: 100000 | X49: 15024 | Y49: 0 | Z49: 0 | AA49: 0 | AD49: 0 | AM49: F6U62-80030-FT | AN49: H08031-JIM-M | AP49: 0 | AQ49: 0 | AR49: 0 | AS49: 0 | AT49: 0 | AU49: 0 | AY49: No | AZ49: W664636 | BA49: 0 | BC49: H08031-JIM-M | BF49: S0361885
A50: W0682417 | B50: 10000 | C50: 10000 | D50: 45758 | E50: 502LAUGH | F50: 4:46:05 pm | G50: 10620258021/10620258023/10620258018 | I50: 1 | J50: Yes | K50: 79 | L50: PM16 | M50: 4108 | P50: 45750 | R50: 56 | S50: 230048 | T50: PE | U50: F6U66-80033-FT0001 | V50: 0 | W50: 200000 | X50: 30048 | Y50: 0 | Z50: 0 | AA50: 0 | AD50: 0 | AM50: F6U66-80033-FT | AN50: H08031-JIM-M | AP50: 0 | AQ50: 0 | AR50: 0 | AS50: 0 | AT50: 0 | AU50: 0 | AY50: No | AZ50: W665120 | BA50: 0 | BC50: H08031-JIM-M | BF50: S0361894
A51: W0682419 | B51: 10000 | C51: 10000 | D51: 45758 | E51: 502LAUGH | F51: 8:43:29 am | G51: 10620258021/10620258023/10620258018 | I51: 1 | J51: Yes | K51: 79 | L51: PM16 | M51: 4108 | P51: 45750 | R51: 28 | S51: 115024 | T51: PE | U51: 3YM57-80010-FT0001 | V51: 0 | W51: 100000 | X51: 15024 | Y51: 0 | Z51: 0 | AA51: 0 | AD51: 0 | AM51: 3YM57-80010-FT | AN51: H08031-JIM-M | AP51: 0 | AQ51: 0 | AR51: 0 | AS51: 0 | AT51: 0 | AU51: 0 | AY51: No | AZ51: W665001 | BA51: 0 | BC51: H08031-JIM-M | BF51: S0361896
A52: W0682428 | B52: 10000 | C52: 10000 | D52: 45751 | E52: 502LAUGH | F52: 8:38:02 am | G52: U532052062/503011726 | I52: 1 | J52: Yes | K52: 32 | L52: PM26 | M52: 5860 | P52: 45750 | R52: 1 | S52: 5860 | T52: PE | U52: 250-5312-000001 | V52: 0 | W52: 5360 | X52: 500 | Y52: 0 | Z52: 0 | AA52: 0 | AD52: 0 | AM52: 250-5312-00 | AN52: J10025 | AP52: 0 | AQ52: 0 | AR52: 0 | AS52: 0 | AT52: 0 | AU52: 0 | AY52: No | AZ52: W664639 | BA52: 0 | BC52: J10025 | BF52: S0361905
A53: W0682432 | B53: 10000 | C53: 10000 | D53: 45751 | E53: 502LAUGH | F53: 8:38:02 am | G53: U530352041/501241326 | I53: 1 | J53: Yes | K53: 32 | L53: PM26 | M53: 5860 | P53: 45750 | R53: 1 | S53: 5860 | T53: PE | U53: 250-5312-000001 | V53: 0 | W53: 5360 | X53: 500 | Y53: 0 | Z53: 0 | AA53: 0 | AD53: 0 | AM53: 250-5312-00 | AN53: J10025 | AP53: 0 | AQ53: 0 | AR53: 0 | AS53: 0 | AT53: 0 | AU53: 0 | AY53: No | AZ53: W664643 | BA53: 0 | BC53: J10025 | BF53: S0361906
A54: W0682436 | B54: 10000 | C54: 10000 | D54: 45751 | E54: 502LAUGH | F54: 8:38:02 am | G54: U532052062/503011726 | I54: 1 | J54: Yes | K54: 32 | L54: PM26 | M54: 5860 | P54: 45750 | R54: 1 | S54: 5860 | T54: PE | U54: 250-5312-000001 | V54: 0 | W54: 5360 | X54: 500 | Y54: 0 | Z54: 0 | AA54: 0 | AD54: 0 | AM54: 250-5312-00 | AN54: J10025 | AP54: 0 | AQ54: 0 | AR54: 0 | AS54: 0 | AT54: 0 | AU54: 0 | AY54: No | AZ54: W664647 | BA54: 0 | BC54: J10025 | BF54: S0361907
A55: W0682449 | B55: 10000 | C55: 10000 | D55: 45755 | E55: 502LAUGH | F55: 8:32:04 am | G55: 860909190840 | I55: 1 | J55: Yes | K55: 79 | L55: PM16 | M55: 100 | P55: 45750 | R55: 20 | S55: 2000 | T55: PE | U55: 200680320001 | V55: 0 | W55: 1200 | X55: 800 | Y55: 0 | Z55: 0 | AA55: 0 | AD55: 0 | AM55: 20068032 | AN55: Z26005 | AP55: 0 | AQ55: 0 | AR55: 0 | AS55: 0 | AT55: 0 | AU55: 0 | AY55: No | AZ55: W664651 | BA55: 0 | BC55: Z26005 | BF55: S0361913
A56: W0682454 | B56: 10000 | C56: 10000 | D56: 45754 | E56: 502LAUGH | F56: 0.53334491 | G56: J00WT7100 | I56: 1 | J56: Yes | K56: 72 | L56: PM17 | M56: 2750 | P56: 45750 | R56: 4 | S56: 11000 | T56: PE | U56: 83614970001 | V56: 0 | W56: 9000 | X56: 2000 | Y56: 0 | Z56: 0 | AA56: 0 | AD56: 0 | AM56: 8361497 | AN56: B02083 | AP56: 0 | AQ56: 0 | AR56: 0 | AS56: 0 | AT56: 0 | AU56: 0 | AY56: No | AZ56: W664652 | BA56: 0 | BC56: B02083 | BF56: S0361915
A57: W0682455 | B57: 10000 | C57: 10000 | D57: 45754 | E57: 502LAUGH | F57: 0.4897338 | G57: J00WT7100 | I57: 1 | J57: Yes | K57: 72 | L57: PM17 | M57: 5750 | P57: 45750 | R57: 4 | S57: 23000 | T57: PE | U57: 83615010001 | V57: 0 | W57: 20000 | X57: 3000 | Y57: 0 | Z57: 0 | AA57: 0 | AD57: 0 | AM57: 8361501 | AN57: B02083 | AP57: 0 | AQ57: 0 | AR57: 0 | AS57: 0 | AT57: 0 | AU57: 0 | AY57: No | AZ57: W664653 | BA57: 0 | BC57: B02083 | BF57: S0361915
A58: W0682459 | B58: 10000 | C58: 10000 | D58: 45751 | E58: 502LAUGH | F58: 5:17:53 pm | G58: J00WT7100 | I58: 1 | J58: Yes | K58: 72 | L58: PM17 | M58: 1750 | P58: 45750 | R58: 4 | S58: 7000 | T58: PE | U58: 86123360001 | V58: 0 | W58: 5000 | X58: 2000 | Y58: 0 | Z58: 0 | AA58: 0 | AD58: 0 | AM58: 8612336 | AN58: B02083 | AP58: 0 | AQ58: 0 | AR58: 0 | AS58: 0 | AT58: 0 | AU58: 0 | AY58: No | AZ58: W664167 | BA58: 0 | BC58: B02083 | BF58: S0361915
A59: W0682460 | B59: 10000 | C59: 10000 | D59: 45754 | E59: 502LAUGH | F59: 0.53291667 | G59: J00WT7100 | I59: 1 | J59: Yes | K59: 72 | L59: PM17 | M59: 2750 | P59: 45750 | R59: 4 | S59: 11000 | T59: PE | U59: 5000443910001 | V59: 0 | W59: 9000 | X59: 2000 | Y59: 0 | Z59: 0 | AA59: 0 | AD59: 0 | AM59: 500044391 | AN59: B02083 | AP59: 0 | AQ59: 0 | AR59: 0 | AS59: 0 | AT59: 0 | AU59: 0 | AY59: No | AZ59: W664654 | BA59: 0 | BC59: B02083 | BF59: S0361915
A60: W0682466 | B60: 10000 | C60: 10000 | D60: 45751 | E60: 502LAUGH | F60: 5:18:34 pm | G60: J00WT7100 | I60: 1 | J60: Yes | K60: 72 | L60: PM17 | M60: 1750 | P60: 45750 | R60: 4 | S60: 7000 | T60: PE | U60: 86123360001 | V60: 0 | W60: 5000 | X60: 2000 | Y60: 0 | Z60: 0 | AA60: 0 | AD60: 0 | AM60: 8612336 | AN60: B02083 | AP60: 0 | AQ60: 0 | AR60: 0 | AS60: 0 | AT60: 0 | AU60: 0 | AY60: No | AZ60: W664168 | BA60: 0 | BC60: B02083 | BF60: S0361916
A61: W0682481 | B61: 10000 | C61: 10000 | D61: 45751 | E61: 502LAUGH | F61: 0.44172454 | G61: I311U8032/4032510U5 | I61: 1 | J61: Yes | K61: 31 | L61: PS19 | M61: 50 | P61: 45750 | R61: 1 | S61: 50 | T61: PE | U61: 218112A0001 | V61: 0 | W61: 50 | X61: 0 | Y61: 0 | Z61: 0 | AA61: 0 | AD61: 0 | AM61: 218112A | AN61: E05185 | AP61: 0 | AQ61: 0 | AR61: 0 | AS61: 0 | AT61: 0 | AU61: 0 | AY61: No | AZ61: W664169 | BA61: 0 | BC61: E05185 | BF61: S0361922
A62: W0682527 | B62: 10000 | C62: 20000 | D62: 45750 | E62: 502LAUGH | F62: 3:56:06 pm | G62: 4067S1 | I62: 1 | J62: Yes | K62: 22 | L62: PS13 | M62: 2500 | P62: 45750 | R62: 2 | S62: 5000 | T62: PE | U62: 805589 REV4000001 | V62: 0 | W62: 5000 | X62: 0 | Y62: 0 | Z62: 0 | AA62: 0 | AD62: 0 | AM62: 805589 REV400 | AN62: V22000 | AP62: 0 | AQ62: 0 | AR62: 0 | AS62: 0 | AT62: 0 | AU62: 0 | AY62: No | AZ62: W664670 | BA62: 0 | BC62: V22000 | BF62: S0361943
A63: W0682531 | B63: 10000 | C63: 10000 | D63: 45755 | E63: 502LAUGH | F63: 4:45:43 pm | G63: BYM039-02 | I63: 1 | J63: Yes | K63: 79 | L63: PM16 | M63: 188 | P63: 45750 | R63: 24 | S63: 4512 | T63: PE | U63: GR-1810001 | V63: 0 | W63: 3000 | X63: 1512 | Y63: 0 | Z63: 0 | AA63: 0 | AD63: 0 | AM63: GR-181 | AN63: G07076 | AP63: 0 | AQ63: 0 | AR63: 0 | AS63: 0 | AT63: 0 | AU63: 0 | AY63: No | AZ63: W664673 | BA63: 0 | BC63: G07076 | BF63: S0361949
A64: W0682535 | B64: 10000 | C64: 30000 | D64: 45751 | E64: 502LAUGH | F64: 0.48146991 | G64: 10656256085 | I64: 3 | J64: Yes | K64: 85 | L64: QM78 | M64: 4546 | P64: 45750 | R64: 11 | S64: 50006 | T64: PE | U64: 7FP39-80002-FT0001 | V64: 0 | W64: 50000 | X64: 6 | Y64: 0 | Z64: 0 | AA64: 0 | AD64: 0 | AM64: 7FP39-80002-FT | AN64: H08031-JIM-M | AP64: 0 | AQ64: 0 | AR64: 0 | AS64: 0 | AT64: 0 | AU64: 0 | AY64: No | AZ64: W664675 | BA64: 0 | BC64: H08031-JIM-M | BF64: S0361953
A65: W0682536 | B65: 10000 | C65: 10000 | D65: 45755 | E65: 502LAUGH | F65: 0.45412037 | G65: D006A5780/D008O15421525/D008O0591/D008O0561 | I65: 1 | J65: Yes | K65: 79N | L65: PM21 | M65: 8334 | P65: 45750 | R65: 15 | S65: 125010 | T65: PE | U65: 1VV24-80029-FT0001 | V65: 0 | W65: 114683 | X65: 10327 | Y65: 0 | Z65: 0 | AA65: 0 | AD65: 0 | AM65: 1VV24-80029-FT | AN65: H08031-JIM-M | AP65: 0 | AQ65: 0 | AR65: 0 | AS65: 0 | AT65: 0 | AU65: 0 | AY65: No | AZ65: W665436 | BA65: 0 | BC65: H08031-JIM-M | BF65: S0361954
A66: W0682539 | B66: 10000 | C66: 20000 | D66: 45771 | E66: 502LAUGH | F66: 8:34:44 am | G66: 10620258022 | I66: 2 | J66: Yes | K66: 77 | L66: PM74 | M66: 2884 | P66: 45750 | R66: 77 | S66: 222068 | T66: PE | U66: 7FP01-80003-FT0001 | V66: 0 | W66: 200000 | X66: 22068 | Y66: 0 | Z66: 0 | AA66: 0 | AD66: 0 | AM66: 7FP01-80003-FT | AN66: H08031-JIM-M | AP66: 0 | AQ66: 0 | AR66: 0 | AS66: 0 | AT66: 0 | AU66: 0 | AY66: No | AZ66: W665437 | BA66: 0 | BC66: H08031-JIM-M | BF66: S0361955
A67: W0682541 | B67: 10000 | C67: 10000 | D67: 45758 | E67: 502LAUGH | F67: 4:46:05 pm | G67: 10620258021/10620258023/10620258018 | I67: 1 | J67: Yes | K67: 79 | L67: PM16 | M67: 4108 | P67: 45750 | R67: 28 | S67: 115024 | T67: PE | U67: 3YM62-80017-FT0001 | V67: 0 | W67: 100000 | X67: 15024 | Y67: 0 | Z67: 0 | AA67: 0 | AD67: 0 | AM67: 3YM62-80017-FT | AN67: H08031-JIM-M | AP67: 0 | AQ67: 0 | AR67: 0 | AS67: 0 | AT67: 0 | AU67: 0 | AY67: No | AZ67: W665121 | BA67: 0 | BC67: H08031-JIM-M | BF67: S0361957
A68: W0682545 | B68: 10000 | C68: 20000 | D68: 45757 | E68: 502LAUGH | F68: 8:33:58 am | G68: 10656256087 | I68: 2 | J68: Yes | K68: 77 | L68: PM74 | M68: 1455 | P68: 45750 | R68: 66 | S68: 96030 | T68: PE | U68: C2P09-80007-FT0001 | V68: 0 | W68: 80000 | X68: 16030 | Y68: 0 | Z68: 0 | AA68: 0 | AD68: 0 | AM68: C2P09-80007-FT | AN68: H08031-JIM-M | AP68: 0 | AQ68: 0 | AR68: 0 | AS68: 0 | AT68: 0 | AU68: 0 | AY68: No | AZ68: W664677 | BA68: 0 | BC68: H08031-JIM-M | BF68: S0361961
A69: W0682554 | B69: 10000 | C69: 10000 | D69: 45758 | E69: 502LAUGH | F69: 8:43:29 am | G69: 10620258021/10620258023/10620258018 | I69: 1 | J69: Yes | K69: 79 | L69: PM16 | M69: 4108 | P69: 45750 | R69: 28 | S69: 115024 | T69: PE | U69: N9K10-80005-FT0001 | V69: 0 | W69: 100000 | X69: 15024 | Y69: 0 | Z69: 0 | AA69: 0 | AD69: 0 | AM69: N9K10-80005-FT | AN69: H08031-JIM-M | AP69: 0 | AQ69: 0 | AR69: 0 | AS69: 0 | AT69: 0 | AU69: 0 | AY69: No | AZ69: W664679 | BA69: 0 | BC69: H08031-JIM-M | BF69: S0361968
A70: W0682563 | B70: 10000 | C70: 10000 | D70: 45751 | E70: 502LAUGH | F70: 8:51:28 am | G70: 8613409 | I70: 1 | J70: Yes | K70: 63 | L70: PM80 | M70: 1174 | P70: 45750 | R70: 75 | S70: 88050 | T70: PE | U70: 730016300 REVA0001 | V70: 0 | W70: 88000 | X70: 50 | Y70: 0 | Z70: 0 | AA70: 0 | AD70: 0 | AM70: 730016300 REVA | AN70: S19081-TH | AP70: 0 | AQ70: 0 | AR70: 0 | AS70: 0 | AT70: 0 | AU70: 0 | AY70: No | AZ70: W664683 | BA70: 0 | BC70: S19081-TH | BF70: H0064896
A71: W0682571 | B71: 10000 | C71: 20000 | D71: 45751 | E71: 502LAUGH | F71: 8:41:02 am | G71: U2B09S001/U4A043S213 | I71: 2 | J71: Yes | K71: 100 | L71: PM87 | M71: 400 | P71: 45750 | R71: 3 | S71: 1200 | T71: PE | U71: URLB14A0001 | V71: 0 | W71: 1000 | X71: 200 | Y71: 0 | Z71: 0 | AA71: 0 | AD71: 0 | AM71: URLB14A | AN71: S19708-M | AP71: 0 | AQ71: 0 | AR71: 0 | AS71: 0 | AT71: 0 | AU71: 0 | AY71: No | AZ71: W664686 | BA71: 0 | BC71: S19708-M | BF71: S0361972
A72: W0682581 | B72: 10000 | C72: 10000 | D72: 45750 | E72: 502LAUGH | F72: 1:34:25 pm | G72: SG-5644655 01 | I72: 1 | J72: Yes | K72: 46 | L72: PS66 | M72: 373 | P72: 45750 | R72: 4 | S72: 1492 | T72: PE | U72: 113275270001 | V72: 0 | W72: 1490 | X72: 2 | Y72: 0 | Z72: 0 | AA72: 0 | AD72: 0 | AM72: 11327527 | AN72: I09180 | AP72: 0 | AQ72: 0 | AR72: 0 | AS72: 0 | AT72: 0 | AU72: 0 | AY72: No | AZ72: W664691 | BA72: 0 | BC72: I09180 | BF72: S0361979
A73: W0682582 | B73: 10000 | C73: 10000 | D73: 45750 | E73: 502LAUGH | F73: 1:34:25 pm | G73: SG-5644655 01 | I73: 1 | J73: Yes | K73: 46 | L73: PS66 | M73: 373 | P73: 45750 | R73: 4 | S73: 1492 | T73: PE | U73: 113275270001 | V73: 0 | W73: 1490 | X73: 2 | Y73: 0 | Z73: 0 | AA73: 0 | AD73: 0 | AM73: 11327527 | AN73: I09180 | AP73: 0 | AQ73: 0 | AR73: 0 | AS73: 0 | AT73: 0 | AU73: 0 | AY73: No | AZ73: W664692 | BA73: 0 | BC73: I09180 | BF73: S0361991
A74: W0682591 | B74: 10000 | C74: 30000 | D74: 45751 | E74: 502LAUGH | F74: 5:21:00 pm | G74: SG-5644655 01 | I74: 1 | J74: Yes | K74: 46 | L74: PS66 | M74: 830 | P74: 45750 | R74: 2 | S74: 1660 | T74: PE | U74: 112886950001 | V74: 0 | W74: 1660 | X74: 0 | Y74: 0 | Z74: 0 | AA74: 0 | AD74: 0 | AM74: 11288695 | AN74: I09180 | AP74: 0 | AQ74: 0 | AR74: 0 | AS74: 0 | AT74: 0 | AU74: 0 | AY74: No | AZ74: W664695 | BA74: 0 | BC74: I09180 | BF74: S0361995
A75: W0682594 | B75: 10000 | C75: 10000 | D75: 45750 | E75: 502LAUGH | F75: 5:39:51 pm | G75: SG-5644655 01 | I75: 1 | J75: Yes | K75: 46 | L75: PS66 | M75: 1660 | P75: 45750 | R75: 2 | S75: 3320 | T75: PE | U75: 112886950001 | V75: 0 | W75: 3320 | X75: 0 | Y75: 0 | Z75: 0 | AA75: 0 | AD75: 0 | AM75: 11288695 | AN75: I09180 | AP75: 0 | AQ75: 0 | AR75: 0 | AS75: 0 | AT75: 0 | AU75: 0 | AY75: No | AZ75: W664698 | BA75: 0 | BC75: I09180 | BF75: S0361999
A76: W0682594 | B76: 20000 | C76: 10000 | D76: 45750 | E76: 502LAUGH | F76: 5:39:51 pm | G76: SG-5644655 01 | I76: 1 | J76: Yes | K76: 46 | L76: PS66 | M76: 1660 | P76: 45750 | R76: 2 | S76: 3320 | T76: PE | U76: 112886950001 | V76: 0 | W76: 3320 | X76: 0 | Y76: 0 | Z76: 0 | AA76: 0 | AD76: 0 | AM76: 11288695 | AN76: I09180 | AP76: 0 | AQ76: 0 | AR76: 0 | AS76: 0 | AT76: 0 | AU76: 0 | AY76: No | AZ76: W664698 | BA76: 0 | BC76: I09180 | BF76: S0361999
A77: W0682595 | B77: 10000 | C77: 10000 | D77: 45758 | E77: 502LAUGH | F77: 8:39:38 am | G77: 10620258021/10620258023/10620258018 | I77: 1 | J77: Yes | K77: 79 | L77: PM16 | M77: 4108 | P77: 45750 | R77: 28 | S77: 115024 | T77: PE | U77: F6U62-80030-FT0001 | V77: 0 | W77: 100000 | X77: 15024 | Y77: 0 | Z77: 0 | AA77: 0 | AD77: 0 | AM77: F6U62-80030-FT | AN77: H08031-JIM-M | AP77: 0 | AQ77: 0 | AR77: 0 | AS77: 0 | AT77: 0 | AU77: 0 | AY77: No | AZ77: W664699 | BA77: 0 | BC77: H08031-JIM-M | BF77: S0361998
A78: W0682601 | B78: 10000 | C78: 20000 | D78: 45770 | E78: 502LAUGH | F78: 5:34:37 pm | G78: 1062058024 | I78: 1 | J78: Yes | K78: 79 | L78: PM16 | M78: 879 | P78: 45750 | R78: 264 | S78: 232056 | T78: PE | U78: 7FP03-80003-FT0001 | V78: 0 | W78: 200000 | X78: 32056 | Y78: 0 | Z78: 0 | AA78: 0 | AD78: 0 | AM78: 7FP03-80003-FT | AN78: H08031-JIM-M | AP78: 0 | AQ78: 0 | AR78: 0 | AS78: 0 | AT78: 0 | AU78: 0 | AY78: No | AZ78: W665440 | BA78: 0 | BC78: H08031-JIM-M | BF78: S0362004
A79: W0682601 | B79: 10000 | C79: 30000 | D79: 45770 | E79: 502LAUGH | F79: 5:34:37 pm | G79: 1062058024 | I79: 2 | J79: Yes | K79: 77 | L79: PM74 | M79: 2884 | P79: 45750 | R79: 77 | S79: 222068 | T79: PE | U79: 7FP03-80003-FT0001 | V79: 0 | W79: 200000 | X79: 22068 | Y79: 0 | Z79: 0 | AA79: 0 | AD79: 0 | AM79: 7FP03-80003-FT | AN79: H08031-JIM-M | AP79: 0 | AQ79: 0 | AR79: 0 | AS79: 0 | AT79: 0 | AU79: 0 | AY79: No | AZ79: W665440 | BA79: 0 | BC79: H08031-JIM-M | BF79: S0362004
A80: W0682645 | B80: 10000 | C80: 10000 | D80: 45754 | E80: 505KANGHS | F80: 8:43:58 am | G80: BYK017-03 | I80: 1 | J80: Yes | K80: 88 | L80: PP24 | M80: 2500 | P80: 45750 | R80: 1 | S80: 2500 | T80: PE | U80: GR-0870001 | V80: 0 | W80: 2000 | X80: 500 | Y80: 0 | Z80: 0 | AA80: 0 | AD80: 0 | AM80: GR-087 | AN80: G07076 | AP80: 0 | AQ80: 0 | AR80: 0 | AS80: 0 | AT80: 0 | AU80: 0 | AY80: No | AZ80: W664713 | BA80: 0 | BC80: G07076 | BF80: S0362012
A81: W0682649 | B81: 10000 | C81: 10000 | D81: 45750 | E81: 502LAUGH | F81: 3:01:52 pm | G81: 4236S1 | I81: 1 | J81: Yes | K81: 65 | L81: PMJ7 | M81: 334 | P81: 45750 | R81: 3 | S81: 1002 | T81: PE | U81: TSMB00434030001 | V81: 0 | W81: 1000 | X81: 2 | Y81: 0 | Z81: 0 | AA81: 0 | AD81: 0 | AM81: TSMB0043403 | AN81: T20104 | AP81: 0 | AQ81: 0 | AR81: 0 | AS81: 0 | AT81: 0 | AU81: 0 | AY81: No | AZ81: W663982 | BA81: 0 | BC81: T20104 | BF81: S0361990
A82: W0682650 | B82: 10000 | C82: 10000 | D82: 45750 | E82: 502LAUGH | F82: 1:31:40 pm | G82: 4170S1 | I82: 1 | J82: Yes | K82: 65 | L82: PMJ7 | M82: 232 | P82: 45750 | R82: 13 | S82: 3016 | T82: PE | U82: TSMB00661020001 | V82: 0 | W82: 3000 | X82: 16 | Y82: 0 | Z82: 0 | AA82: 0 | AD82: 0 | AM82: TSMB0066102 | AN82: T20104 | AP82: 0 | AQ82: 0 | AR82: 0 | AS82: 0 | AT82: 0 | AU82: 0 | AY82: No | AZ82: W664714 | BA82: 0 | BC82: T20104 | BF82: S0361990
A83: W0682652 | B83: 10000 | C83: 10000 | D83: 45750 | E83: 502LAUGH | F83: 3:57:01 pm | G83: 4236S1 | I83: 1 | J83: Yes | K83: 65 | L83: PMJ7 | M83: 375 | P83: 45750 | R83: 8 | S83: 3000 | T83: PE | U83: TSMB00709010001 | V83: 0 | W83: 3000 | X83: 0 | Y83: 0 | Z83: 0 | AA83: 0 | AD83: 0 | AM83: TSMB0070901 | AN83: T20104 | AP83: 0 | AQ83: 0 | AR83: 0 | AS83: 0 | AT83: 0 | AU83: 0 | AY83: No | AZ83: W664716 | BA83: 0 | BC83: T20104 | BF83: S0361990
A84: W0682653 | B84: 10000 | C84: 10000 | D84: 45750 | E84: 502LAUGH | F84: 1:45:48 pm | G84: 4170S1 | I84: 1 | J84: Yes | K84: 65 | L84: PMJ7 | M84: 157 | P84: 45750 | R84: 16 | S84: 2512 | T84: PE | U84: TSMB00710010001 | V84: 0 | W84: 2500 | X84: 12 | Y84: 0 | Z84: 0 | AA84: 0 | AD84: 0 | AM84: TSMB0071001 | AN84: T20104 | AP84: 0 | AQ84: 0 | AR84: 0 | AS84: 0 | AT84: 0 | AU84: 0 | AY84: No | AZ84: W664717 | BA84: 0 | BC84: T20104 | BF84: S0361990
A85: W0682655 | B85: 10000 | C85: 10000 | D85: 45750 | E85: 502LAUGH | F85: 3:01:52 pm | G85: 4236S1 | I85: 1 | J85: Yes | K85: 65 | L85: PMJ7 | M85: 1000 | P85: 45750 | R85: 3 | S85: 3000 | T85: PE | U85: TSMB00434030001 | V85: 0 | W85: 3000 | X85: 0 | Y85: 0 | Z85: 0 | AA85: 0 | AD85: 0 | AM85: TSMB0043403 | AN85: T20104 | AP85: 0 | AQ85: 0 | AR85: 0 | AS85: 0 | AT85: 0 | AU85: 0 | AY85: No | AZ85: W664719 | BA85: 0 | BC85: T20104 | BF85: PR006406
A86: W0682656 | B86: 10000 | C86: 10000 | D86: 45750 | E86: 502LAUGH | F86: 1:31:40 pm | G86: 4170S1 | I86: 1 | J86: Yes | K86: 65 | L86: PMJ7 | M86: 693 | P86: 45750 | R86: 13 | S86: 9009 | T86: PE | U86: TSMB00661020001 | V86: 0 | W86: 9000 | X86: 9 | Y86: 0 | Z86: 0 | AA86: 0 | AD86: 0 | AM86: TSMB0066102 | AN86: T20104 | AP86: 0 | AQ86: 0 | AR86: 0 | AS86: 0 | AT86: 0 | AU86: 0 | AY86: No | AZ86: W664720 | BA86: 0 | BC86: T20104 | BF86: PR006406
A87: W0682657 | B87: 10000 | C87: 10000 | D87: 45750 | E87: 502LAUGH | F87: 3:57:01 pm | G87: 4236S1 | I87: 1 | J87: Yes | K87: 65 | L87: PMJ7 | M87: 875 | P87: 45750 | R87: 8 | S87: 7000 | T87: PE | U87: TSMB00709010001 | V87: 0 | W87: 7000 | X87: 0 | Y87: 0 | Z87: 0 | AA87: 0 | AD87: 0 | AM87: TSMB0070901 | AN87: T20104 | AP87: 0 | AQ87: 0 | AR87: 0 | AS87: 0 | AT87: 0 | AU87: 0 | AY87: No | AZ87: W664721 | BA87: 0 | BC87: T20104 | BF87: PR006406
A88: W0682658 | B88: 10000 | C88: 10000 | D88: 45750 | E88: 502LAUGH | F88: 1:45:48 pm | G88: 4170S1 | I88: 1 | J88: Yes | K88: 65 | L88: PMJ7 | M88: 314 | P88: 45750 | R88: 16 | S88: 5024 | T88: PE | U88: TSMB00710010001 | V88: 0 | W88: 5000 | X88: 24 | Y88: 0 | Z88: 0 | AA88: 0 | AD88: 0 | AM88: TSMB0071001 | AN88: T20104 | AP88: 0 | AQ88: 0 | AR88: 0 | AS88: 0 | AT88: 0 | AU88: 0 | AY88: No | AZ88: W664722 | BA88: 0 | BC88: T20104 | BF88: PR006406
A89: W0682661 | B89: 10000 | C89: 30000 | D89: 45754 | E89: 502LAUGH | F89: 9:18:57 am | G89: 59470/59469 | I89: 2 | J89: Yes | K89: 96 | L89: QM38 | M89: 152250 | P89: 45750 | R89: 6 | S89: 913500 | T89: PE | U89: MT-1000173-00REV0003 | V89: 0 | W89: 949776 | X89: -36276 | Y89: 0 | Z89: 0 | AA89: 0 | AD89: 0 | AM89: MT-1000173-00REV008 | AN89: Z26002 | AP89: 0 | AQ89: 0 | AR89: 0 | AS89: 0 | AT89: 0 | AU89: 0 | AY89: No | AZ89: W664723 | BA89: 0 | BC89: Z26002 | BF89: S0362021
A90: W0682666 | B90: 10000 | C90: 10000 | D90: 45751 | E90: 502LAUGH | F90: 1:45:43 pm | G90: 10620258024 | I90: 1 | J90: Yes | K90: 79 | L90: PM16 | M90: 133 | P90: 45750 | R90: 264 | S90: 35112 | T90: PE | U90: 7FP10-80001-FT0001 | V90: 0 | W90: 20000 | X90: 15112 | Y90: 0 | Z90: 0 | AA90: 0 | AD90: 0 | AM90: 7FP10-80001-FT | AN90: H08031-JIM-M | AP90: 0 | AQ90: 0 | AR90: 0 | AS90: 0 | AT90: 0 | AU90: 0 | AY90: No | AZ90: W664724 | BA90: 0 | BC90: H08031-JIM-M | BF90: S0362023
A91: W0682666 | B91: 10000 | C91: 20000 | D91: 45751 | E91: 502LAUGH | F91: 1:45:43 pm | G91: 10620258024 | I91: 2 | J91: Yes | K91: 77 | L91: PM74 | M91: 416 | P91: 45750 | R91: 77 | S91: 32032 | T91: PE | U91: 7FP10-80001-FT0001 | V91: 0 | W91: 20000 | X91: 12032 | Y91: 0 | Z91: 0 | AA91: 0 | AD91: 0 | AM91: 7FP10-80001-FT | AN91: H08031-JIM-M | AP91: 0 | AQ91: 0 | AR91: 0 | AS91: 0 | AT91: 0 | AU91: 0 | AY91: No | AZ91: W664724 | BA91: 0 | BC91: H08031-JIM-M | BF91: S0362023
A92: W0682669 | B92: 10000 | C92: 10000 | D92: 45751 | E92: 502LAUGH | F92: 4:16:19 pm | G92: J00WT7100 | I92: 1 | J92: Yes | K92: 72 | L92: PM17 | M92: 2500 | P92: 45750 | R92: 6 | S92: 15000 | T92: PE | U92: 86090870001 | V92: 0 | W92: 10000 | X92: 5000 | Y92: 0 | Z92: 0 | AA92: 0 | AD92: 0 | AM92: 8609087 | AN92: B02083 | AP92: 0 | AQ92: 0 | AR92: 0 | AS92: 0 | AT92: 0 | AU92: 0 | AY92: No | AZ92: W664727 | BA92: 0 | BC92: B02083 | BF92: S0362024
A93: W0682678 | B93: 10000 | C93: 10000 | D93: 45754 | E93: 502LAUGH | F93: 8:58:25 am | G93: E190912129 | I93: 1 | J93: Yes | K93: 63 | L93: PM80 | M93: 5000 | P93: 45750 | R93: 60 | S93: 300000 | T93: PE | U93: 709898812-3M66900001 | V93: 0 | W93: 300000 | X93: 0 | Y93: 0 | Z93: 0 | AA93: 0 | AD93: 0 | AM93: 709898812-3M6690SP | AN93: S19314 | AP93: 0 | AQ93: 0 | AR93: 0 | AS93: 0 | AT93: 0 | AU93: 0 | AY93: No | AZ93: W664735 | BA93: 0 | BC93: S19314 | BF93: H0064905
A94: W0682684 | B94: 10000 | C94: 10000 | D94: 45751 | E94: 502LAUGH | F94: 8:51:28 am | G94: 8613409 | I94: 1 | J94: Yes | K94: 63 | L94: PM80 | M94: 1760 | P94: 45750 | R94: 75 | S94: 132000 | T94: PE | U94: 730016300 REVA0001 | V94: 0 | W94: 132000 | X94: 0 | Y94: 0 | Z94: 0 | AA94: 0 | AD94: 0 | AM94: 730016300 REVA | AN94: S19314 | AP94: 0 | AQ94: 0 | AR94: 0 | AS94: 0 | AT94: 0 | AU94: 0 | AY94: No | AZ94: W664740 | BA94: 0 | BC94: S19314 | BF94: H0064911
A95: W0682687 | B95: 10000 | C95: 10000 | D95: 45754 | E95: 502LAUGH | F95: 8:58:25 am | G95: 8613409 | I95: 1 | J95: Yes | K95: 63 | L95: PM80 | M95: 1334 | P95: 45750 | R95: 60 | S95: 80040 | T95: PE | U95: 740921700-32PC E0001 | V95: 0 | W95: 80000 | X95: 40 | Y95: 0 | Z95: 0 | AA95: 0 | AD95: 0 | AM95: 740921700-32PC EMPTY | AN95: S19314 | AP95: 0 | AQ95: 0 | AR95: 0 | AS95: 0 | AT95: 0 | AU95: 0 | AY95: No | AZ95: W664742 | BA95: 0 | BC95: S19314 | BF95: H0064914
A96: W0682690 | B96: 10000 | C96: 10000 | D96: 45755 | E96: 502LAUGH | F96: 9:56:34 am | G96: M0BVD0521 | I96: 1 | J96: Yes | K96: 79 | L96: PM16 | M96: 500 | P96: 45750 | R96: 250 | S96: 125000 | T96: PE | U96: 107-54006900001 | V96: 0 | W96: 100000 | X96: 25000 | Y96: 0 | Z96: 0 | AA96: 0 | AD96: 0 | AM96: 107-5400690 | AN96: K11180 | AP96: 0 | AQ96: 0 | AR96: 0 | AS96: 0 | AT96: 0 | AU96: 0 | AY96: No | AZ96: W664744 | BA96: 0 | BC96: K11180 | BF96: S0362026
A97: W0682717 | B97: 10000 | C97: 10000 | D97: 45750 | E97: 502LAUGH | F97: 1:35:03 pm | G97: 3830U7060 | I97: 1 | J97: Yes | K97: 61 | L97: PM68 | M97: 200 | P97: 45750 | R97: 1 | S97: 200 | T97: PE | U97: 107335250001 | V97: 0 | W97: 200 | X97: 0 | Y97: 0 | Z97: 0 | AA97: 0 | AD97: 0 | AM97: 10733525 | AN97: I09109 | AP97: 0 | AQ97: 0 | AR97: 0 | AS97: 0 | AT97: 0 | AU97: 0 | AY97: No | AZ97: W664750 | BA97: 0 | BC97: I09109 | BF97: S0362087
A98: W0682765 | B98: 10000 | C98: 20000 | D98: 45751 | E98: 502LAUGH | F98: 4:15:18 pm | G98: M0BSM3241 | I98: 1 | J98: Yes | K98: 72 | L98: PM17 | M98: 2000 | P98: 45750 | R98: 4 | S98: 8000 | T98: PE | U98: 86.J7350001 | V98: 0 | W98: 5000 | X98: 3000 | Y98: 0 | Z98: 0 | AA98: 0 | AD98: 0 | AM98: 86.J735 | AN98: T20390-PMI | AP98: 0 | AQ98: 0 | AR98: 0 | AS98: 0 | AT98: 0 | AU98: 0 | AY98: No | AZ98: W664751 | BA98: 0 | BC98: T20390-PMI | BF98: S0362148
A99: W0682813 | B99: 10000 | C99: 20000 | D99: 45750 | E99: 502LAUGH | F99: 0.42402778 | G99: 2101818U5/M0B7C2220 | I99: 2 | J99: Yes | K99: 82 | L99: PM11 | M99: 1072 | P99: 45750 | R99: 56 | S99: 60032 | T99: PE | U99: 86.B9480001 | V99: 0 | W99: 50000 | X99: 10032 | Y99: 0 | Z99: 0 | AA99: 0 | AD99: 0 | AM99: 86.B948 | AN99: C03423 | AP99: 0 | AQ99: 0 | AR99: 0 | AS99: 0 | AT99: 0 | AU99: 0 | AY99: No | AZ99: W664760 | BA99: 0 | BC99: C03423 | BF99: S0362176
A100: W0682918 | B100: 10000 | C100: 10000 | D100: 45751 | E100: 502LAUGH | F100: 0.48216435 | G100: 4092605U5A | I100: 1 | J100: Yes | K100: 22 | L100: PS13 | M100: 2000 | P100: 45750 | R100: 1 | S100: 2000 | T100: PE | U100: 250-6238-000001 | V100: 0 | W100: 2000 | X100: 0 | Y100: 0 | Z100: 0 | AA100: 0 | AD100: 0 | AM100: 250-6238-00 | AN100: J10025 | AP100: 0 | AQ100: 0 | AR100: 0 | AS100: 0 | AT100: 0 | AU100: 0 | AY100: No | AZ100: W664762 | BA100: 0 | BC100: J10025 | BF100: S0362359
A101: W0682922 | B101: 10000 | C101: 10000 | D101: 45751 | E101: 502LAUGH | F101: 8:53:18 am | G101: 5323501-04-01-08 | I101: 1 | J101: Yes | K101: 63 | L101: PM80 | M101: 200 | P101: 45750 | R101: 60 | S101: 12020 | T101: PE | U101: 1125-790-00002 R0001 | V101: 0 | W101: 12000 | X101: 20 | Y101: 0 | Z101: 0 | AA101: 0 | AD101: 0 | AM101: 1125-790-00002 REVB | AN101: M13337-SMD | AP101: 0 | AQ101: 0 | AR101: 0 | AS101: 0 | AT101: 0 | AU101: 0 | AY101: No | AZ101: W664764 | BA101: 0 | BC101: M13337-SMD | BF101: S0362363
...

Sheet 04-Apr
A1: Production Output
A2: Filter: Date Completed: 04/04/25
A4: Work Order No. | B4: Work Order Line No. | C4: WO Journal Line No. | D4: Add Date | E4: Add User | F4: Add Time | G4: Material Batch No. | H4: Die Cut | I4: Process No. | J4: Posted | K4: Machine Code | L4: Staff Code | M4: No. of Press | N4: Date Started | O4: Time Started | P4: Date Completed | Q4: Time Completed | R4: No. of Ups | S4: Printed Quantity | T4: Journal Type | U4: Item Code | V4: Quantity | W4: QC Approved Quantity | X4: Rejected Quantity | Y4: Roll | Z4: Length | AA4: Width | AB4: Length UOM | AC4: Width UOM | AD4: RM Quantity | AE4: Material Code | AF4: Variant Code | AG4: Request Delivery Date | AH4: Non QC Record | AI4: Link to Line No. | AJ4: Related | AK4: Expire Date | AL4: Label Remark | AM4: Customer Part Number | AN4: Customer Code | AO4: ddmm | AP4: Label Packing Quantity 1 | AQ4: Label Quantity 1 | AR4: Label Packing Quantity 2 | AS4: Label Quantity 2 | AT4: Label Packing Quantity 3 | AU4: Label Quantity 3 | AV4: UOM for Label Printing | AW4: QC Inspector | AX4: Summarised Period | AY4: Summarised | AZ4: Posted Work Order No. | BA4: Colour | BB4: Currency | BC4: Ref Customer | BD4: Group | BE4: PO | BF4: Source Doc. No.
A5: W0680557 | B5: 10000 | C5: 20000 | D5: 45754 | E5: 505KANGHS | F5: 5:38:32 pm | G5: M0BTQ4840 | H5: FSC30666 | I5: 1 | J5: No | K5: 94 | L5: PM09 | M5: 3334 | P5: 45751 | R5: 6 | S5: 20004 | T5: PE | U5: L001-773057-00000004 | V5: 0 | W5: 0 | X5: 0 | Y5: 0 | Z5: 0 | AA5: 0 | AD5: 0 | AH5: No | AI5: 0 | AJ5: No | AM5: L001-773057-000004CM | AN5: W23041-TH | AP5: 0 | AQ5: 0 | AR5: 0 | AS5: 0 | AT5: 0 | AU5: 0 | AY5: No | BC5: W23041-TH | BF5: H0064673
A6: W0682349 | B6: 10000 | C6: 20000 | D6: 45751 | E6: 502LAUGH | F6: 5:16:20 pm | G6: 10620258022 | H6: FDC30934 | I6: 2 | J6: No | K6: 77 | L6: PM74 | M6: 454 | P6: 45751 | R6: 15 | S6: 6810 | T6: PE | U6: CZ633-800050001 | V6: 0 | W6: 0 | X6: 0 | Y6: 0 | Z6: 0 | AA6: 0 | AD6: 0 | AH6: No | AI6: 0 | AJ6: No | AM6: CZ633-80005 | AN6: H08031-JIM | AP6: 0 | AQ6: 0 | AR6: 0 | AS6: 0 | AT6: 0 | AU6: 0 | AY6: No | BC6: H08031-JIM | BF6: S0361845
A7: W0682425 | B7: 10000 | C7: 20000 | D7: 45751 | E7: 502LAUGH | F7: 5:15:26 pm | G7: 10620258022 | H7: FDC30934 | I7: 2 | J7: No | K7: 77 | L7: PM74 | M7: 367 | P7: 45751 | R7: 15 | S7: 5505 | T7: PE | U7: CZ635-800050001 | V7: 0 | W7: 0 | X7: 0 | Y7: 0 | Z7: 0 | AA7: 0 | AD7: 0 | AH7: No | AI7: 0 | AJ7: No | AM7: CZ635-80005 | AN7: H08031-JIM | AP7: 0 | AQ7: 0 | AR7: 0 | AS7: 0 | AT7: 0 | AU7: 0 | AY7: No | BC7: H08031-JIM | BF7: S0361902
A8: W0676952 | B8: 10000 | C8: 30000 | D8: 45754 | E8: 502LAUGH | F8: 8:46:12 am | G8: 10639931106/10639931103/10639931102/10639931104 | I8: 3 | J8: Yes | K8: 91 | L8: QM54 | M8: 56000 | P8: 45751 | R8: 9 | S8: 504000 | T8: PE | U8: 5180-0102-BH2120001 | V8: 0 | W8: 500000 | X8: 4000 | Y8: 0 | Z8: 0 | AA8: 0 | AD8: 0 | AM8: 5180-0102-BH212 | AN8: H08031-JIM | AP8: 0 | AQ8: 0 | AR8: 0 | AS8: 0 | AT8: 0 | AU8: 0 | AY8: No | AZ8: W664482 | BA8: 0 | BC8: H08031-JIM | BF8: S0355320
A9: W0678734 | B9: 10000 | C9: 30000 | D9: 45751 | E9: 502LAUGH | F9: 5:13:10 pm | G9: M0BU23510990/MOBVG3280 | I9: 1 | J9: Yes | K9: 86 | L9: PS96 | M9: 8000 | P9: 45751 | R9: 6 | S9: 48000 | T9: PE | U9: 10036212001 REVA0001 | V9: 0 | W9: 47059 | X9: 941 | Y9: 0 | Z9: 0 | AA9: 0 | AD9: 0 | AM9: 10036212001 REVA | AN9: E05166-JAPAC | AP9: 0 | AQ9: 0 | AR9: 0 | AS9: 0 | AT9: 0 | AU9: 0 | AY9: No | AZ9: W664072 | BA9: 0 | BC9: E05166-JAPAC | BF9: S0357484
A10: W0680983 | B10: 10000 | C10: 10000 | D10: 45758 | E10: 502LAUGH | F10: 9:12:17 am | G10: WO2024/5284/1010831/XHX24911A1407/XHX2412190201/80117500 | I10: 1 | J10: Yes | K10: 103 | L10: PM47 | M10: 90000 | P10: 45751 | R10: 8 | S10: 720000 | T10: PE | U10: MT273730001 | V10: 0 | W10: 720000 | X10: 0 | Y10: 0 | Z10: 0 | AA10: 0 | AD10: 0 | AM10: MT27373 | AN10: Z26002 | AP10: 0 | AQ10: 0 | AR10: 0 | AS10: 0 | AT10: 0 | AU10: 0 | AY10: No | AZ10: W664507 | BA10: 0 | BC10: Z26002 | BF10: S0360896
A11: W0680983 | B11: 20000 | C11: 10000 | D11: 45758 | E11: 502LAUGH | F11: 9:12:17 am | G11: WO2024/5284/1010831/XHX24911A1407/XHX2412190201/80117500 | I11: 1 | J11: Yes | K11: 103 | L11: PM47 | M11: 10000 | P11: 45751 | R11: 8 | S11: 80000 | T11: PE | U11: MT273730001 | V11: 0 | W11: 80000 | X11: 0 | Y11: 0 | Z11: 0 | AA11: 0 | AD11: 0 | AM11: MT27373 | AN11: Z26002 | AP11: 0 | AQ11: 0 | AR11: 0 | AS11: 0 | AT11: 0 | AU11: 0 | AY11: No | AZ11: W664507 | BA11: 0 | BC11: Z26002 | BF11: S0360896
A12: W0680983 | B12: 20000 | C12: 20000 | D12: 45758 | E12: 502LAUGH | F12: 9:12:17 am | G12: WO2024/5284/1010831/XHX24911A1407/XHX2412190201/80117500 | I12: 1 | J12: Yes | K12: 103N | L12: PM55 | M12: 35000 | P12: 45751 | R12: 8 | S12: 280000 | T12: PE | U12: MT273730001 | V12: 0 | W12: 280000 | X12: 0 | Y12: 0 | Z12: 0 | AA12: 0 | AD12: 0 | AM12: MT27373 | AN12: Z26002 | AP12: 0 | AQ12: 0 | AR12: 0 | AS12: 0 | AT12: 0 | AU12: 0 | AY12: No | AZ12: W664507 | BA12: 0 | BC12: Z26002 | BF12: S0360896
A13: W0681066 | B13: 10000 | C13: 20000 | D13: 45751 | E13: 502LAUGH | F13: 1:00:22 pm | G13: U3B12S049 | I13: 1 | J13: Yes | K13: 61 | L13: PM68 | M13: 1250 | P13: 45751 | R13: 8 | S13: 10000 | T13: PE | U13: 039714 REV5000001 | V13: 0 | W13: 10000 | X13: 0 | Y13: 0 | Z13: 0 | AA13: 0 | AD13: 0 | AM13: 039714 REV500 | AN13: V22000 | AP13: 0 | AQ13: 0 | AR13: 0 | AS13: 0 | AT13: 0 | AU13: 0 | AY13: No | AZ13: W664088 | BA13: 0 | BC13: V22000 | BF13: S0360940
A14: W0681114 | B14: 10000 | C14: 20000 | D14: 45754 | E14: 502LAUGH | F14: 8:42:04 am | G14: U522458002 | I14: 2 | J14: Yes | K14: 60 | L14: PM30 | M14: 2000 | P14: 45751 | R14: 1 | S14: 2000 | T14: PE | U14: 250-0412-000001 | V14: 0 | W14: 2000 | X14: 0 | Y14: 0 | Z14: 0 | AA14: 0 | AD14: 0 | AM14: 250-0412-00 | AN14: J10025 | AP14: 0 | AQ14: 0 | AR14: 0 | AS14: 0 | AT14: 0 | AU14: 0 | AY14: No | AZ14: W664514 | BA14: 0 | BC14: J10025 | BF14: S0361007
A15: W0681222 | B15: 10000 | C15: 10000 | D15: 45756 | E15: 502LAUGH | F15: 0.44040509 | G15: 5307412-01-03-04/5307412-02-01-03/5305412-03-02-07 | I15: 1 | J15: Yes | K15: 90N | L15: QC04 | M15: 36450 | P15: 45751 | R15: 2 | S15: 72900 | T15: PE | U15: 723852900-PROTO 0001 | V15: 0 | W15: 72900 | X15: 0 | Y15: 0 | Z15: 0 | AA15: 0 | AD15: 0 | AM15: 723852900-PROTO D | AN15: S19081-TH | AP15: 0 | AQ15: 0 | AR15: 0 | AS15: 0 | AT15: 0 | AU15: 0 | AY15: No | AZ15: W664520 | BA15: 0 | BC15: S19081-TH | BF15: H0064765
A16: W0681576 | B16: 10000 | C16: 30000 | D16: 45751 | E16: 502LAUGH | F16: 1:46:58 pm | G16: 10620258046 | I16: 3 | J16: Yes | K16: 85 | L16: QM78 | M16: 10000 | P16: 45751 | R16: 11 | S16: 110000 | T16: PE | U16: T6N02-80020-FT0001 | V16: 0 | W16: 100000 | X16: 10000 | Y16: 0 | Z16: 0 | AA16: 0 | AD16: 0 | AM16: T6N02-80020-FT | AN16: H08031-JIM-M | AP16: 0 | AQ16: 0 | AR16: 0 | AS16: 0 | AT16: 0 | AU16: 0 | AY16: No | AZ16: W664109 | BA16: 0 | BC16: H08031-JIM-M | BF16: S0361213
A17: W0681697 | B17: 10000 | C17: 10000 | D17: 45754 | E17: 502LAUGH | F17: 8:33:18 am | G17: M0BTQ4840 | I17: 1 | J17: Yes | K17: 94 | L17: PM09 | M17: 167 | P17: 45751 | R17: 6 | S17: 1002 | T17: PE | U17: L001-773057-00000002 | V17: 0 | W17: 1000 | X17: 2 | Y17: 0 | Z17: 0 | AA17: 0 | AD17: 0 | AM17: L001-773057-000002CM | AN17: X24001-WD-SUZHOU | AP17: 0 | AQ17: 0 | AR17: 0 | AS17: 0 | AT17: 0 | AU17: 0 | AY17: No | AZ17: W664550 | BA17: 0 | BC17: X24001-WD-SUZHOU | BF17: S0361288
A18: W0681740 | B18: 10000 | C18: 20000 | D18: 45754 | E18: 505KANGHS | F18: 8:51:41 am | G18: SG-5650696 | I18: 1 | J18: Yes | K18: 73 | L18: PM59 | M18: 42000 | P18: 45751 | R18: 12 | S18: 504000 | T18: PE | U18: 80256230001 | V18: 0 | W18: 504000 | X18: 0 | Y18: 0 | Z18: 0 | AA18: 0 | AD18: 0 | AM18: 8025623 | AN18: B02083 | AP18: 0 | AQ18: 0 | AR18: 0 | AS18: 0 | AT18: 0 | AU18: 0 | AY18: No | AZ18: W664562 | BA18: 0 | BC18: B02083 | BF18: S0361322
A19: W0681758 | B19: 10000 | C19: 10000 | D19: 45754 | E19: 502LAUGH | F19: 8:59:07 am | G19: 234402 | I19: 1 | J19: Yes | K19: 90 | L19: PM35 | M19: 334 | P19: 45751 | R19: 180 | S19: 60120 | T19: PE | U19: 1113-550-00020 R0001 | V19: 0 | W19: 60000 | X19: 120 | Y19: 0 | Z19: 0 | AA19: 0 | AD19: 0 | AM19: 1113-550-00020 REVB | AN19: M13337-SMD | AP19: 0 | AQ19: 0 | AR19: 0 | AS19: 0 | AT19: 0 | AU19: 0 | AY19: No | AZ19: W664563 | BA19: 0 | BC19: M13337-SMD | BF19: S0361340
A20: W0681807 | B20: 10000 | C20: 20000 | D20: 45754 | E20: 502LAUGH | F20: 8:33:47 am | G20: J00VB7941 | I20: 1 | J20: Yes | K20: 46 | L20: PS66 | M20: 1000 | P20: 45751 | R20: 1 | S20: 1000 | T20: PE | U20: 250-5190-000001 | V20: 0 | W20: 1000 | X20: 0 | Y20: 0 | Z20: 0 | AA20: 0 | AD20: 0 | AM20: 250-5190-00 | AN20: J10025 | AP20: 0 | AQ20: 0 | AR20: 0 | AS20: 0 | AT20: 0 | AU20: 0 | AY20: No | AZ20: W664125 | BA20: 0 | BC20: J10025 | BF20: S0361373
A21: W0681907 | B21: 10000 | C21: 60000 | D21: 45751 | E21: 502LAUGH | F21: 5:33:58 pm | G21: 10620258042/10620258038 | I21: 3 | J21: Yes | K21: 85 | L21: QM78 | M21: 16000 | P21: 45751 | R21: 11 | S21: 176000 | T21: PE | U21: 3JB26-800010001 | V21: 0 | W21: 98462 | X21: 77538 | Y21: 0 | Z21: 0 | AA21: 0 | AD21: 0 | AM21: 3JB26-80001 | AN21: H08031-JIM-M | AP21: 0 | AQ21: 0 | AR21: 0 | AS21: 0 | AT21: 0 | AU21: 0 | AY21: No | AZ21: W664582 | BA21: 0 | BC21: H08031-JIM-M | BF21: S0361414
A22: W0681950 | B22: 10000 | C22: 10000 | D22: 45751 | E22: 502LAUGH | F22: 4:14:20 pm | G22: 4092S1/404123725 | I22: 1 | J22: Yes | K22: 61 | L22: PM68 | M22: 500 | P22: 45751 | R22: 1 | S22: 500 | T22: PE | U22: INACTIVE ASSET L0001 | V22: 0 | W22: 500 | X22: 0 | Y22: 0 | Z22: 0 | AA22: 0 | AD22: 0 | AM22: INACTIVE ASSET LABEL | AN22: S19186 | AP22: 0 | AQ22: 0 | AR22: 0 | AS22: 0 | AT22: 0 | AU22: 0 | AY22: No | AZ22: W664136 | BA22: 0 | BC22: S19186 | BF22: S0361430
A23: W0682009 | B23: 10000 | C23: 10000 | D23: 45754 | E23: 502LAUGH | F23: 8:54:52 am | G23: T0AF1219072 | I23: 1 | J23: Yes | K23: 78 | L23: PM84 | M23: 2750 | P23: 45751 | R23: 16 | S23: 44000 | T23: PE | U23: 714370201-ADS1360001 | V23: 0 | W23: 40000 | X23: 4000 | Y23: 0 | Z23: 0 | AA23: 0 | AD23: 0 | AM23: 714370201-ADS1366 | AN23: S19314 | AP23: 0 | AQ23: 0 | AR23: 0 | AS23: 0 | AT23: 0 | AU23: 0 | AY23: No | AZ23: W664138 | BA23: 0 | BC23: S19314 | BF23: H0064846
A24: W0682009 | B24: 10000 | C24: 20000 | D24: 45754 | E24: 502LAUGH | F24: 8:54:52 am | G24: T0AF1219072 | I24: 2 | J24: Yes | K24: 63 | L24: PM80 | M24: 2500 | P24: 45751 | R24: 16 | S24: 40000 | T24: PE | U24: 714370201-ADS1360001 | V24: 0 | W24: 40000 | X24: 0 | Y24: 0 | Z24: 0 | AA24: 0 | AD24: 0 | AM24: 714370201-ADS1366 | AN24: S19314 | AP24: 0 | AQ24: 0 | AR24: 0 | AS24: 0 | AT24: 0 | AU24: 0 | AY24: No | AZ24: W664138 | BA24: 0 | BC24: S19314 | BF24: H0064846
A25: W0682088 | B25: 10000 | C25: 20000 | D25: 45751 | E25: 502LAUGH | F25: 2:29:24 pm | G25: 501060725 | I25: 2 | J25: Yes | K25: 46 | L25: PS66 | M25: 2500 | P25: 45751 | R25: 2 | S25: 5000 | T25: PE | U25: OHARA LABEL0001 | V25: 0 | W25: 5000 | X25: 0 | Y25: 0 | Z25: 0 | AA25: 0 | AD25: 0 | AM25: OHARA LABEL | AN25: H08217 | AP25: 0 | AQ25: 0 | AR25: 0 | AS25: 0 | AT25: 0 | AU25: 0 | AY25: No | AZ25: W664142 | BA25: 0 | BC25: H08217 | BF25: S0361562
A26: W0682115 | B26: 10000 | C26: 20000 | D26: 45754 | E26: 505KANGHS | F26: 8:45:08 am | G26: 10656256096 | I26: 2 | J26: Yes | K26: 77 | L26: PM74 | M26: 1285 | P26: 45751 | R26: 88 | S26: 113080 | T26: PE | U26: 3YM58-80010-FT0001 | V26: 0 | W26: 100000 | X26: 13080 | Y26: 0 | Z26: 0 | AA26: 0 | AD26: 0 | AM26: 3YM58-80010-FT | AN26: H08031-JIM-M | AP26: 0 | AQ26: 0 | AR26: 0 | AS26: 0 | AT26: 0 | AU26: 0 | AY26: No | AZ26: W664603 | BA26: 0 | BC26: H08031-JIM-M | BF26: S0361569
A27: W0682167 | B27: 10000 | C27: 10000 | D27: 45751 | E27: 502LAUGH | F27: 2:54:08 pm | G27: SG-5644655 01 | I27: 1 | J27: Yes | K27: 59 | L27: PS74 | M27: 1000 | P27: 45751 | R27: 10 | S27: 10000 | T27: PE | U27: 112023700001 | V27: 0 | W27: 10000 | X27: 0 | Y27: 0 | Z27: 0 | AA27: 0 | AD27: 0 | AM27: 11202370 | AN27: I09180 | AP27: 0 | AQ27: 0 | AR27: 0 | AS27: 0 | AT27: 0 | AU27: 0 | AY27: No | AZ27: W664145 | BA27: 0 | BC27: I09180 | BF27: S0361668
A28: W0682167 | B28: 20000 | C28: 10000 | D28: 45751 | E28: 502LAUGH | F28: 2:54:08 pm | G28: SG-5644655 01 | I28: 1 | J28: Yes | K28: 59 | L28: PS74 | M28: 1000 | P28: 45751 | R28: 10 | S28: 10000 | T28: PE | U28: 112023700001 | V28: 0 | W28: 10000 | X28: 0 | Y28: 0 | Z28: 0 | AA28: 0 | AD28: 0 | AM28: 11202370 | AN28: I09180 | AP28: 0 | AQ28: 0 | AR28: 0 | AS28: 0 | AT28: 0 | AU28: 0 | AY28: No | AZ28: W664145 | BA28: 0 | BC28: I09180 | BF28: S0361668
A29: W0682167 | B29: 30000 | C29: 10000 | D29: 45751 | E29: 502LAUGH | F29: 2:54:08 pm | G29: SG-5644655 01 | I29: 1 | J29: Yes | K29: 59 | L29: PS74 | M29: 1000 | P29: 45751 | R29: 10 | S29: 10000 | T29: PE | U29: 112023700001 | V29: 0 | W29: 10000 | X29: 0 | Y29: 0 | Z29: 0 | AA29: 0 | AD29: 0 | AM29: 11202370 | AN29: I09180 | AP29: 0 | AQ29: 0 | AR29: 0 | AS29: 0 | AT29: 0 | AU29: 0 | AY29: No | AZ29: W664145 | BA29: 0 | BC29: I09180 | BF29: S0361668
A30: W0682167 | B30: 40000 | C30: 10000 | D30: 45751 | E30: 502LAUGH | F30: 2:54:08 pm | G30: SG-5644655 01 | I30: 1 | J30: Yes | K30: 59 | L30: PS74 | M30: 1000 | P30: 45751 | R30: 10 | S30: 10000 | T30: PE | U30: 112023700001 | V30: 0 | W30: 10000 | X30: 0 | Y30: 0 | Z30: 0 | AA30: 0 | AD30: 0 | AM30: 11202370 | AN30: I09180 | AP30: 0 | AQ30: 0 | AR30: 0 | AS30: 0 | AT30: 0 | AU30: 0 | AY30: No | AZ30: W664145 | BA30: 0 | BC30: I09180 | BF30: S0361668
A31: W0682167 | B31: 50000 | C31: 10000 | D31: 45751 | E31: 502LAUGH | F31: 2:54:08 pm | G31: SG-5644655 01 | I31: 1 | J31: Yes | K31: 59 | L31: PS74 | M31: 500 | P31: 45751 | R31: 10 | S31: 5000 | T31: PE | U31: 112023700001 | V31: 0 | W31: 5000 | X31: 0 | Y31: 0 | Z31: 0 | AA31: 0 | AD31: 0 | AM31: 11202370 | AN31: I09180 | AP31: 0 | AQ31: 0 | AR31: 0 | AS31: 0 | AT31: 0 | AU31: 0 | AY31: No | AZ31: W664145 | BA31: 0 | BC31: I09180 | BF31: S0361668
A32: W0682177 | B32: 10000 | C32: 10000 | D32: 45751 | E32: 502LAUGH | F32: 4:36:46 pm | G32: SG-5644655 01 | I32: 1 | J32: Yes | K32: 59 | L32: PS74 | M32: 300 | P32: 45751 | R32: 10 | S32: 3000 | T32: PE | U32: 112024500001 | V32: 0 | W32: 3000 | X32: 0 | Y32: 0 | Z32: 0 | AA32: 0 | AD32: 0 | AM32: 11202450 | AN32: I09180 | AP32: 0 | AQ32: 0 | AR32: 0 | AS32: 0 | AT32: 0 | AU32: 0 | AY32: No | AZ32: W664149 | BA32: 0 | BC32: I09180 | BF32: S0361678
A33: W0682177 | B33: 20000 | C33: 10000 | D33: 45751 | E33: 502LAUGH | F33: 4:36:46 pm | G33: SG-5644655 01 | I33: 1 | J33: Yes | K33: 59 | L33: PS74 | M33: 200 | P33: 45751 | R33: 10 | S33: 2000 | T33: PE | U33: 112024500001 | V33: 0 | W33: 2000 | X33: 0 | Y33: 0 | Z33: 0 | AA33: 0 | AD33: 0 | AM33: 11202450 | AN33: I09180 | AP33: 0 | AQ33: 0 | AR33: 0 | AS33: 0 | AT33: 0 | AU33: 0 | AY33: No | AZ33: W664149 | BA33: 0 | BC33: I09180 | BF33: S0361678
A34: W0682241 | B34: 10000 | C34: 20000 | D34: 45751 | E34: 502LAUGH | F34: 4:17:10 pm | G34: J00WT7100 | I34: 2 | J34: Yes | K34: 71 | L34: PMJ7 | M34: 2000 | P34: 45751 | R34: 6 | S34: 12000 | T34: PE | U34: 80834720001 | V34: 0 | W34: 10000 | X34: 2000 | Y34: 0 | Z34: 0 | AA34: 0 | AD34: 0 | AM34: 8083472 | AN34: B02083 | AP34: 0 | AQ34: 0 | AR34: 0 | AS34: 0 | AT34: 0 | AU34: 0 | AY34: No | AZ34: W664619 | BA34: 0 | BC34: B02083 | BF34: S0361716
A35: W0682251 | B35: 10000 | C35: 10000 | D35: 45754 | E35: 502LAUGH | F35: 8:42:34 am | G35: 91221325 | I35: 1 | J35: Yes | K35: 60 | L35: PM30 | M35: 1667 | P35: 45751 | R35: 6 | S35: 10002 | T35: PE | U35: 2V9604710001 | V35: 0 | W35: 10000 | X35: 2 | Y35: 0 | Z35: 0 | AA35: 0 | AD35: 0 | AM35: 2V960471 | AN35: T20198 | AP35: 0 | AQ35: 0 | AR35: 0 | AS35: 0 | AT35: 0 | AU35: 0 | AY35: No | AZ35: W664621 | BA35: 0 | BC35: T20198 | BF35: S0361719
A36: W0682253 | B36: 10000 | C36: 20000 | D36: 45754 | E36: 505KANGHS | F36: 8:41:32 am | G36: 211041725 | I36: 2 | J36: Yes | K36: 100 | L36: PM87 | M36: 2100 | P36: 45751 | R36: 1 | S36: 2100 | T36: PE | U36: INSPECTION STICK0002 | V36: 0 | W36: 2000 | X36: 100 | Y36: 0 | Z36: 0 | AA36: 0 | AD36: 0 | AM36: INSPECTION STICKER | AN36: C03033 | AP36: 0 | AQ36: 0 | AR36: 0 | AS36: 0 | AT36: 0 | AU36: 0 | AY36: No | AZ36: W664154 | BA36: 0 | BC36: C03033 | BF36: S0361721
A37: W0682257 | B37: 10000 | C37: 20000 | D37: 45755 | E37: 502LAUGH | F37: 8:37:52 am | G37: 4112311U5A/4110110425 | I37: 2 | J37: Yes | K37: 105 | L37: PM87 | M37: 2300 | P37: 45751 | R37: 1 | S37: 2300 | T37: PE | U37: ALL PURPOSE F57 0001 | V37: 0 | W37: 2000 | X37: 300 | Y37: 0 | Z37: 0 | AA37: 0 | AD37: 0 | AM37: ALL PURPOSE F57 LBL | AN37: R18140 | AP37: 0 | AQ37: 0 | AR37: 0 | AS37: 0 | AT37: 0 | AU37: 0 | AY37: No | AZ37: W664622 | BA37: 0 | BC37: R18140 | BF37: S0361715
A38: W0682258 | B38: 10000 | C38: 20000 | D38: 45755 | E38: 502LAUGH | F38: 8:37:52 am | G38: 4112311U5A/4110110425 | I38: 2 | J38: Yes | K38: 105 | L38: PM87 | M38: 6300 | P38: 45751 | R38: 1 | S38: 6300 | T38: PE | U38: GUNWASH-F49 LBL0001 | V38: 0 | W38: 6000 | X38: 300 | Y38: 0 | Z38: 0 | AA38: 0 | AD38: 0 | AM38: GUNWASH-F49 LBL | AN38: R18140 | AP38: 0 | AQ38: 0 | AR38: 0 | AS38: 0 | AT38: 0 | AU38: 0 | AY38: No | AZ38: W664623 | BA38: 0 | BC38: R18140 | BF38: S0361715
A39: W0682267 | B39: 10000 | C39: 10000 | D39: 45754 | E39: 505KANGHS | F39: 8:41:32 am | G39: SG-5652869 01 | I39: 1 | J39: Yes | K39: 31 | L39: PS19 | M39: 10000 | P39: 45751 | R39: 9 | S39: 90000 | T39: PE | U39: NOBU PURSER-ORAN0001 | V39: 0 | W39: 90000 | X39: 0 | Y39: 0 | Z39: 0 | AA39: 0 | AD39: 0 | AM39: NOBU PURSER-ORANGE | AN39: H08117 | AP39: 0 | AQ39: 0 | AR39: 0 | AS39: 0 | AT39: 0 | AU39: 0 | AY39: No | AZ39: W664624 | BA39: 0 | BC39: H08117 | BF39: S0361733
A40: W0682318 | B40: 10000 | C40: 20000 | D40: 45754 | E40: 502LAUGH | F40: 8:32:32 am | G40: J00WF0611 | I40: 2 | J40: Yes | K40: 60 | L40: PM30 | M40: 800 | P40: 45751 | R40: 1 | S40: 800 | T40: PE | U40: HPM-4VW11-801970001 | V40: 0 | W40: 850 | X40: -50 | Y40: 0 | Z40: 0 | AA40: 0 | AD40: 0 | AM40: HPM-4VW11-80197 | AN40: Z26005 | AP40: 0 | AQ40: 0 | AR40: 0 | AS40: 0 | AT40: 0 | AU40: 0 | AY40: No | AZ40: W664628 | BA40: 0 | BC40: Z26005 | BF40: S0361760
A41: W0682397 | B41: 10000 | C41: 30000 | D41: 45751 | E41: 502LAUGH | F41: 2:52:49 pm | G41: 10656256095 | I41: 3 | J41: Yes | K41: 85 | L41: QM78 | M41: 8000 | P41: 45751 | R41: 11 | S41: 88000 | T41: PE | U41: B3B28-80007-FT0001 | V41: 0 | W41: 80000 | X41: 8000 | Y41: 0 | Z41: 0 | AA41: 0 | AD41: 0 | AM41: B3B28-80007-FT | AN41: H08031-JIM-M | AP41: 0 | AQ41: 0 | AR41: 0 | AS41: 0 | AT41: 0 | AU41: 0 | AY41: No | AZ41: W664631 | BA41: 0 | BC41: H08031-JIM-M | BF41: S0361875
A42: W0682407 | B42: 10000 | C42: 20000 | D42: 45754 | E42: 505KANGHS | F42: 1:49:32 pm | G42: 10656256086/10656256095 | I42: 2 | J42: Yes | K42: 77 | L42: PM74 | M42: 3705 | P42: 45751 | R42: 88 | S42: 326040 | T42: PE | U42: 6ZD61-800010001 | V42: 0 | W42: 330000 | X42: -3960 | Y42: 0 | Z42: 0 | AA42: 0 | AD42: 0 | AM42: 6ZD61-80001 | AN42: H08031-JIM-M | AP42: 0 | AQ42: 0 | AR42: 0 | AS42: 0 | AT42: 0 | AU42: 0 | AY42: No | AZ42: W665181 | BA42: 0 | BC42: H08031-JIM-M | BF42: S0361886
A43: W0682423 | B43: 10000 | C43: 20000 | D43: 45751 | E43: 502LAUGH | F43: 5:14:27 pm | G43: 10620258022 | I43: 2 | J43: Yes | K43: 77 | L43: PM74 | M43: 934 | P43: 45751 | R43: 15 | S43: 14010 | T43: PE | U43: CR330-800150001 | V43: 0 | W43: 10000 | X43: 4010 | Y43: 0 | Z43: 0 | AA43: 0 | AD43: 0 | AM43: CR330-80015 | AN43: H08031-JIM | AP43: 0 | AQ43: 0 | AR43: 0 | AS43: 0 | AT43: 0 | AU43: 0 | AY43: No | AZ43: W665919 | BA43: 0 | BC43: H08031-JIM | BF43: S0361900
A44: W0682431 | B44: 10000 | C44: 10000 | D44: 45751 | E44: 502LAUGH | F44: 5:41:59 pm | G44: U532052062/503011726 | I44: 1 | J44: Yes | K44: 32 | L44: PM26 | M44: 5860 | P44: 45751 | R44: 1 | S44: 5860 | T44: PE | U44: 250-5323-000001 | V44: 0 | W44: 5360 | X44: 500 | Y44: 0 | Z44: 0 | AA44: 0 | AD44: 0 | AM44: 250-5323-00 | AN44: J10025 | AP44: 0 | AQ44: 0 | AR44: 0 | AS44: 0 | AT44: 0 | AU44: 0 | AY44: No | AZ44: W664642 | BA44: 0 | BC44: J10025 | BF44: S0361905
A45: W0682435 | B45: 10000 | C45: 10000 | D45: 45751 | E45: 502LAUGH | F45: 5:41:59 pm | G45: U532052062/503011726 | I45: 1 | J45: Yes | K45: 32 | L45: PM26 | M45: 5860 | P45: 45751 | R45: 1 | S45: 5860 | T45: PE | U45: 250-5323-000001 | V45: 0 | W45: 5360 | X45: 500 | Y45: 0 | Z45: 0 | AA45: 0 | AD45: 0 | AM45: 250-5323-00 | AN45: J10025 | AP45: 0 | AQ45: 0 | AR45: 0 | AS45: 0 | AT45: 0 | AU45: 0 | AY45: No | AZ45: W664646 | BA45: 0 | BC45: J10025 | BF45: S0361906
A46: W0682455 | B46: 10000 | C46: 20000 | D46: 45754 | E46: 502LAUGH | F46: 0.4897338 | G46: J00WT7100 | I46: 2 | J46: Yes | K46: 71 | L46: PMJ7 | M46: 1667 | P46: 45751 | R46: 6 | S46: 10002 | T46: PE | U46: 83615010001 | V46: 0 | W46: 10000 | X46: 2 | Y46: 0 | Z46: 0 | AA46: 0 | AD46: 0 | AM46: 8361501 | AN46: B02083 | AP46: 0 | AQ46: 0 | AR46: 0 | AS46: 0 | AT46: 0 | AU46: 0 | AY46: No | AZ46: W664653 | BA46: 0 | BC46: B02083 | BF46: S0361915
A47: W0682459 | B47: 10000 | C47: 20000 | D47: 45751 | E47: 502LAUGH | F47: 5:17:53 pm | G47: J00WT7100 | I47: 2 | J47: Yes | K47: 71 | L47: PMJ7 | M47: 1000 | P47: 45751 | R47: 6 | S47: 6000 | T47: PE | U47: 86123360001 | V47: 0 | W47: 5000 | X47: 1000 | Y47: 0 | Z47: 0 | AA47: 0 | AD47: 0 | AM47: 8612336 | AN47: B02083 | AP47: 0 | AQ47: 0 | AR47: 0 | AS47: 0 | AT47: 0 | AU47: 0 | AY47: No | AZ47: W664167 | BA47: 0 | BC47: B02083 | BF47: S0361915
A48: W0682466 | B48: 10000 | C48: 20000 | D48: 45751 | E48: 502LAUGH | F48: 5:18:34 pm | G48: J00WT7100 | I48: 2 | J48: Yes | K48: 71 | L48: PMJ7 | M48: 1000 | P48: 45751 | R48: 6 | S48: 6000 | T48: PE | U48: 86123360001 | V48: 0 | W48: 5000 | X48: 1000 | Y48: 0 | Z48: 0 | AA48: 0 | AD48: 0 | AM48: 8612336 | AN48: B02083 | AP48: 0 | AQ48: 0 | AR48: 0 | AS48: 0 | AT48: 0 | AU48: 0 | AY48: No | AZ48: W664168 | BA48: 0 | BC48: B02083 | BF48: S0361916
A49: W0682487 | B49: 10000 | C49: 10000 | D49: 45754 | E49: 502LAUGH | F49: 8:39:12 am | G49: 502190692 | I49: 1 | J49: Yes | K49: 22 | L49: PS13 | M49: 10000 | P49: 45751 | R49: 1 | S49: 10000 | T49: PE | U49: TDF ADDRESS-76X10001 | V49: 0 | W49: 10000 | X49: 0 | Y49: 0 | Z49: 0 | AA49: 0 | AD49: 0 | AM49: TDF ADDRESS-76X102MM | AN49: T20300 | AP49: 0 | AQ49: 0 | AR49: 0 | AS49: 0 | AT49: 0 | AU49: 0 | AY49: No | AZ49: W664171 | BA49: 0 | BC49: T20300 | BF49: S0361928
A50: W0682488 | B50: 10000 | C50: 20000 | D50: 45758 | E50: 502LAUGH | F50: 8:53:55 am | G50: SG-5653741 01 | I50: 1 | J50: Yes | K50: 72 | L50: PM17 | M50: 6500 | P50: 45751 | R50: 20 | S50: 130000 | T50: PE | U50: HSA SECURITY LAB0001 | V50: 0 | W50: 100000 | X50: 30000 | Y50: 0 | Z50: 0 | AA50: 0 | AD50: 0 | AM50: HSA SECURITY LABEL | AN50: S19337-HEALTHCARE | AP50: 0 | AQ50: 0 | AR50: 0 | AS50: 0 | AT50: 0 | AU50: 0 | AY50: No | AZ50: W664661 | BA50: 0 | BC50: S19337-HEALTHCARE | BF50: S0361927
A51: W0682509 | B51: 10000 | C51: 10000 | D51: 45754 | E51: 502LAUGH | F51: 5:27:07 pm | G51: BYJ032-07 | I51: 1 | J51: Yes | K51: 72 | L51: PM17 | M51: 3500 | P51: 45751 | R51: 4 | S51: 14000 | T51: PE | U51: HASACONI FLUX-DA0001 | V51: 0 | W51: 10000 | X51: 4000 | Y51: 0 | Z51: 0 | AA51: 0 | AD51: 0 | AM51: HASACONI FLUX-DANGER | AN51: S19254 | AP51: 0 | AQ51: 0 | AR51: 0 | AS51: 0 | AT51: 0 | AU51: 0 | AY51: No | AZ51: W664664 | BA51: 0 | BC51: S19254 | BF51: S0361924
A52: W0682511 | B52: 10000 | C52: 10000 | D52: 45754 | E52: 505KANGHS | F52: 1:55:25 pm | G52: BYJ032-07 | I52: 1 | J52: Yes | K52: 72 | L52: PM17 | M52: 6000 | P52: 45751 | R52: 6 | S52: 36000 | T52: PE | U52: 69 SCS-ROHS-Y0001 | V52: 0 | W52: 30000 | X52: 6000 | Y52: 0 | Z52: 0 | AA52: 0 | AD52: 0 | AM52: 69 SCS-ROHS-Y | AN52: S19254 | AP52: 0 | AQ52: 0 | AR52: 0 | AS52: 0 | AT52: 0 | AU52: 0 | AY52: No | AZ52: W664665 | BA52: 0 | BC52: S19254 | BF52: S0361924
A53: W0682536 | B53: 10000 | C53: 20000 | D53: 45755 | E53: 502LAUGH | F53: 0.45412037 | G53: D006A5780/D008O15421525/D008O0591/D008O0561 | I53: 1 | J53: Yes | K53: 79 | L53: PM29 | M53: 6200 | P53: 45751 | R53: 15 | S53: 93000 | T53: PE | U53: 1VV24-80029-FT0001 | V53: 0 | W53: 85317 | X53: 7683 | Y53: 0 | Z53: 0 | AA53: 0 | AD53: 0 | AM53: 1VV24-80029-FT | AN53: H08031-JIM-M | AP53: 0 | AQ53: 0 | AR53: 0 | AS53: 0 | AT53: 0 | AU53: 0 | AY53: No | AZ53: W665436 | BA53: 0 | BC53: H08031-JIM-M | BF53: S0361954
A54: W0682538 | B54: 10000 | C54: 30000 | D54: 45779 | E54: 502LAUGH | F54: 5:43:37 pm | G54: 10656256088/10656256086 | I54: 2 | J54: Yes | K54: 77 | L54: PM74 | M54: 8500 | P54: 45751 | R54: 88 | S54: 748000 | T54: PE | U54: 3YM60-80017-FT0001 | V54: 0 | W54: 700000 | X54: 48000 | Y54: 0 | Z54: 0 | AA54: 0 | AD54: 0 | AM54: 3YM60-80017-FT | AN54: H08031-JIM-M | AP54: 0 | AQ54: 0 | AR54: 0 | AS54: 0 | AT54: 0 | AU54: 0 | AY54: No | AZ54: W665921 | BA54: 0 | BC54: H08031-JIM-M | BF54: S0361950
A55: W0682552 | B55: 10000 | C55: 10000 | D55: 45751 | E55: 502LAUGH | F55: 5:31:34 pm | G55: BYJ032-07 | I55: 1 | J55: Yes | K55: 72 | L55: PM17 | M55: 750 | P55: 45751 | R55: 16 | S55: 12000 | T55: PE | U55: 46 SCS-PB-ROHS-Y0001 | V55: 0 | W55: 9000 | X55: 3000 | Y55: 0 | Z55: 0 | AA55: 0 | AD55: 0 | AM55: 46 SCS-PB-ROHS-Y | AN55: S19254 | AP55: 0 | AQ55: 0 | AR55: 0 | AS55: 0 | AT55: 0 | AU55: 0 | AY55: No | AZ55: W664678 | BA55: 0 | BC55: S19254 | BF55: S0361924
A56: W0682552 | B56: 10000 | C56: 20000 | D56: 45751 | E56: 502LAUGH | F56: 5:31:34 pm | G56: BYJ032-07 | I56: 2 | J56: Yes | K56: 82 | L56: PM11 | M56: 750 | P56: 45751 | R56: 16 | S56: 12000 | T56: PE | U56: 46 SCS-PB-ROHS-Y0001 | V56: 0 | W56: 9000 | X56: 3000 | Y56: 0 | Z56: 0 | AA56: 0 | AD56: 0 | AM56: 46 SCS-PB-ROHS-Y | AN56: S19254 | AP56: 0 | AQ56: 0 | AR56: 0 | AS56: 0 | AT56: 0 | AU56: 0 | AY56: No | AZ56: W664678 | BA56: 0 | BC56: S19254 | BF56: S0361924
A57: W0682579 | B57: 10000 | C57: 10000 | D57: 45751 | E57: 502LAUGH | F57: 5:34:54 pm | G57: SG-5644655 01 | I57: 1 | J57: Yes | K57: 59 | L57: PS74 | M57: 400 | P57: 45751 | R57: 10 | S57: 4000 | T57: PE | U57: 112023960001 | V57: 0 | W57: 4000 | X57: 0 | Y57: 0 | Z57: 0 | AA57: 0 | AD57: 0 | AM57: 11202396 | AN57: I09180 | AP57: 0 | AQ57: 0 | AR57: 0 | AS57: 0 | AT57: 0 | AU57: 0 | AY57: No | AZ57: W664689 | BA57: 0 | BC57: I09180 | BF57: S0361977
A58: W0682580 | B58: 10000 | C58: 10000 | D58: 45751 | E58: 502LAUGH | F58: 5:34:54 pm | G58: SG-5644655 01 | I58: 1 | J58: Yes | K58: 59 | L58: PS74 | M58: 500 | P58: 45751 | R58: 10 | S58: 5000 | T58: PE | U58: 112023960001 | V58: 0 | W58: 5000 | X58: 0 | Y58: 0 | Z58: 0 | AA58: 0 | AD58: 0 | AM58: 11202396 | AN58: I09180 | AP58: 0 | AQ58: 0 | AR58: 0 | AS58: 0 | AT58: 0 | AU58: 0 | AY58: No | AZ58: W664690 | BA58: 0 | BC58: I09180 | BF58: S0361978
A59: W0682580 | B59: 20000 | C59: 10000 | D59: 45751 | E59: 502LAUGH | F59: 5:34:54 pm | G59: SG-5644655 01 | I59: 1 | J59: Yes | K59: 59 | L59: PS74 | M59: 500 | P59: 45751 | R59: 10 | S59: 5000 | T59: PE | U59: 112023960001 | V59: 0 | W59: 5000 | X59: 0 | Y59: 0 | Z59: 0 | AA59: 0 | AD59: 0 | AM59: 11202396 | AN59: I09180 | AP59: 0 | AQ59: 0 | AR59: 0 | AS59: 0 | AT59: 0 | AU59: 0 | AY59: No | AZ59: W664690 | BA59: 0 | BC59: I09180 | BF59: S0361978
A60: W0682580 | B60: 30000 | C60: 10000 | D60: 45751 | E60: 502LAUGH | F60: 5:34:54 pm | G60: SG-5644655 01 | I60: 1 | J60: Yes | K60: 59 | L60: PS74 | M60: 500 | P60: 45751 | R60: 10 | S60: 5000 | T60: PE | U60: 112023960001 | V60: 0 | W60: 5000 | X60: 0 | Y60: 0 | Z60: 0 | AA60: 0 | AD60: 0 | AM60: 11202396 | AN60: I09180 | AP60: 0 | AQ60: 0 | AR60: 0 | AS60: 0 | AT60: 0 | AU60: 0 | AY60: No | AZ60: W664690 | BA60: 0 | BC60: I09180 | BF60: S0361978
A61: W0682622 | B61: 10000 | C61: 10000 | D61: 45771 | E61: 502LAUGH | F61: 4:16:54 pm | G61: 10620258020 | I61: 1 | J61: Yes | K61: 79N | L61: PM21 | M61: 805 | P61: 45751 | R61: 264 | S61: 212520 | T61: PE | U61: 7FP06-80001 REVB0001 | V61: 0 | W61: 200000 | X61: 12520 | Y61: 0 | Z61: 0 | AA61: 0 | AD61: 0 | AM61: 7FP06-80001 REVB-FT | AN61: H08031-JIM-M | AP61: 0 | AQ61: 0 | AR61: 0 | AS61: 0 | AT61: 0 | AU61: 0 | AY61: No | AZ61: W665924 | BA61: 0 | BC61: H08031-JIM-M | BF61: S0362006
A62: W0682623 | B62: 10000 | C62: 10000 | D62: 45751 | E62: 502LAUGH | F62: 4:36:46 pm | G62: SG-5644655 01 | I62: 1 | J62: Yes | K62: 59 | L62: PS74 | M62: 300 | P62: 45751 | R62: 10 | S62: 3000 | T62: PE | U62: 112024500001 | V62: 0 | W62: 3000 | X62: 0 | Y62: 0 | Z62: 0 | AA62: 0 | AD62: 0 | AM62: 11202450 | AN62: I09180 | AP62: 0 | AQ62: 0 | AR62: 0 | AS62: 0 | AT62: 0 | AU62: 0 | AY62: No | AZ62: W664705 | BA62: 0 | BC62: I09180 | BF62: S0362007
A63: W0682623 | B63: 20000 | C63: 10000 | D63: 45751 | E63: 502LAUGH | F63: 4:36:46 pm | G63: SG-5644655 01 | I63: 1 | J63: Yes | K63: 59 | L63: PS74 | M63: 300 | P63: 45751 | R63: 10 | S63: 3000 | T63: PE | U63: 112024500001 | V63: 0 | W63: 3000 | X63: 0 | Y63: 0 | Z63: 0 | AA63: 0 | AD63: 0 | AM63: 11202450 | AN63: I09180 | AP63: 0 | AQ63: 0 | AR63: 0 | AS63: 0 | AT63: 0 | AU63: 0 | AY63: No | AZ63: W664705 | BA63: 0 | BC63: I09180 | BF63: S0362007
A64: W0682641 | B64: 10000 | C64: 20000 | D64: 45755 | E64: 502LAUGH | F64: 2:18:23 pm | G64: SG-5399135-01 | I64: 2 | J64: Yes | K64: 92 | L64: PM87 | M64: 600 | P64: 45751 | R64: 1 | S64: 600 | T64: PE | U64: GR-1580001 | V64: 0 | W64: 500 | X64: 100 | Y64: 0 | Z64: 0 | AA64: 0 | AD64: 0 | AM64: GR-158 | AN64: G07076 | AP64: 0 | AQ64: 0 | AR64: 0 | AS64: 0 | AT64: 0 | AU64: 0 | AY64: No | AZ64: W664710 | BA64: 0 | BC64: G07076 | BF64: S0362015
A65: W0682651 | B65: 10000 | C65: 10000 | D65: 45751 | E65: 502LAUGH | F65: 0.48216435 | G65: 3082509U9 | I65: 1 | J65: Yes | K65: 22 | L65: PS13 | M65: 200 | P65: 45751 | R65: 5 | S65: 1000 | T65: PE | U65: TSMB00665020001 | V65: 0 | W65: 1000 | X65: 0 | Y65: 0 | Z65: 0 | AA65: 0 | AD65: 0 | AM65: TSMB0066502 | AN65: T20104 | AP65: 0 | AQ65: 0 | AR65: 0 | AS65: 0 | AT65: 0 | AU65: 0 | AY65: No | AZ65: W664715 | BA65: 0 | BC65: T20104 | BF65: S0361990
A66: W0682661 | B66: 10000 | C66: 40000 | D66: 45754 | E66: 502LAUGH | F66: 9:18:57 am | G66: 59470/59469 | I66: 2 | J66: Yes | K66: 96N | L66: QM87 | M66: 90125 | P66: 45751 | R66: 6 | S66: 540750 | T66: PE | U66: MT-1000173-00REV0003 | V66: 0 | W66: 562224 | X66: -21474 | Y66: 0 | Z66: 0 | AA66: 0 | AD66: 0 | AM66: MT-1000173-00REV008 | AN66: Z26002 | AP66: 0 | AQ66: 0 | AR66: 0 | AS66: 0 | AT66: 0 | AU66: 0 | AY66: No | AZ66: W664723 | BA66: 0 | BC66: Z26002 | BF66: S0362021
A67: W0682666 | B67: 10000 | C67: 30000 | D67: 45751 | E67: 502LAUGH | F67: 1:45:43 pm | G67: 10620258024 | I67: 3 | J67: Yes | K67: 85 | L67: QM78 | M67: 2728 | P67: 45751 | R67: 11 | S67: 30008 | T67: PE | U67: 7FP10-80001-FT0001 | V67: 0 | W67: 20000 | X67: 10008 | Y67: 0 | Z67: 0 | AA67: 0 | AD67: 0 | AM67: 7FP10-80001-FT | AN67: H08031-JIM-M | AP67: 0 | AQ67: 0 | AR67: 0 | AS67: 0 | AT67: 0 | AU67: 0 | AY67: No | AZ67: W664724 | BA67: 0 | BC67: H08031-JIM-M | BF67: S0362023
A68: W0682669 | B68: 10000 | C68: 20000 | D68: 45751 | E68: 502LAUGH | F68: 4:16:19 pm | G68: J00WT7100 | I68: 2 | J68: Yes | K68: 71 | L68: PMJ7 | M68: 2000 | P68: 45751 | R68: 6 | S68: 12000 | T68: PE | U68: 86090870001 | V68: 0 | W68: 10000 | X68: 2000 | Y68: 0 | Z68: 0 | AA68: 0 | AD68: 0 | AM68: 8609087 | AN68: B02083 | AP68: 0 | AQ68: 0 | AR68: 0 | AS68: 0 | AT68: 0 | AU68: 0 | AY68: No | AZ68: W664727 | BA68: 0 | BC68: B02083 | BF68: S0362024
A69: W0682670 | B69: 10000 | C69: 20000 | D69: 45751 | E69: 502LAUGH | F69: 0.48287037 | G69: J00WT7100 | I69: 2 | J69: Yes | K69: 71 | L69: PMJ7 | M69: 3667 | P69: 45751 | R69: 6 | S69: 22002 | T69: PE | U69: 86090880001 | V69: 0 | W69: 18000 | X69: 4002 | Y69: 0 | Z69: 0 | AA69: 0 | AD69: 0 | AM69: 8609088 | AN69: B02083 | AP69: 0 | AQ69: 0 | AR69: 0 | AS69: 0 | AT69: 0 | AU69: 0 | AY69: No | AZ69: W664728 | BA69: 0 | BC69: B02083 | BF69: S0362024
A70: W0682677 | B70: 10000 | C70: 10000 | D70: 45755 | E70: 502LAUGH | F70: 8:54:43 am | G70: 1006323 | I70: 1 | J70: Yes | K70: 63 | L70: PM80 | M70: 3200 | P70: 45751 | R70: 50 | S70: 160000 | T70: PE | U70: 709898802-EL93160001 | V70: 0 | W70: 160000 | X70: 0 | Y70: 0 | Z70: 0 | AA70: 0 | AD70: 0 | AM70: 709898802-EL93164 | AN70: S19314 | AP70: 0 | AQ70: 0 | AR70: 0 | AS70: 0 | AT70: 0 | AU70: 0 | AY70: No | AZ70: W664734 | BA70: 0 | BC70: S19314 | BF70: H0064904
A71: W0682679 | B71: 10000 | C71: 10000 | D71: 45754 | E71: 502LAUGH | F71: 8:58:25 am | G71: E190912129 | I71: 1 | J71: Yes | K71: 63 | L71: PM80 | M71: 2667 | P71: 45751 | R71: 30 | S71: 80010 | T71: PE | U71: 709898817 REVB0001 | V71: 0 | W71: 80000 | X71: 10 | Y71: 0 | Z71: 0 | AA71: 0 | AD71: 0 | AM71: 709898817 REVB | AN71: S19314 | AP71: 0 | AQ71: 0 | AR71: 0 | AS71: 0 | AT71: 0 | AU71: 0 | AY71: No | AZ71: W664736 | BA71: 0 | BC71: S19314 | BF71: H0064906
A72: W0682707 | B72: 10000 | C72: 10000 | D72: 45751 | E72: 502LAUGH | F72: 4:17:36 pm | G72: E04G128901530 | I72: 1 | J72: Yes | K72: 78 | L72: PM84 | M72: 667 | P72: 45751 | R72: 3 | S72: 2001 | T72: PE | U72: 86.K4320001 | V72: 0 | W72: 2000 | X72: 1 | Y72: 0 | Z72: 0 | AA72: 0 | AD72: 0 | AM72: 86.K432 | AN72: T20390-PMI | AP72: 0 | AQ72: 0 | AR72: 0 | AS72: 0 | AT72: 0 | AU72: 0 | AY72: No | AZ72: W664746 | BA72: 0 | BC72: T20390-PMI | BF72: S0362034
A73: W0682765 | B73: 10000 | C73: 30000 | D73: 45751 | E73: 502LAUGH | F73: 4:15:18 pm | G73: M0BSM3241 | I73: 2 | J73: Yes | K73: 82 | L73: PM11 | M73: 875 | P73: 45751 | R73: 8 | S73: 7000 | T73: PE | U73: 86.J7350001 | V73: 0 | W73: 5000 | X73: 2000 | Y73: 0 | Z73: 0 | AA73: 0 | AD73: 0 | AM73: 86.J735 | AN73: T20390-PMI | AP73: 0 | AQ73: 0 | AR73: 0 | AS73: 0 | AT73: 0 | AU73: 0 | AY73: No | AZ73: W664751 | BA73: 0 | BC73: T20390-PMI | BF73: S0362148
A74: W0682920 | B74: 10000 | C74: 10000 | D74: 45754 | E74: 502LAUGH | F74: 5:27:48 pm | G74: U4A043S213/3060209U9 | I74: 1 | J74: Yes | K74: 88 | L74: PP24 | M74: 250 | P74: 45751 | R74: 2 | S74: 500 | T74: PE | U74: 107110100001 | V74: 0 | W74: 300 | X74: 200 | Y74: 0 | Z74: 0 | AA74: 0 | AD74: 0 | AM74: 10711010 | AN74: L12070 | AP74: 0 | AQ74: 0 | AR74: 0 | AS74: 0 | AT74: 0 | AU74: 0 | AY74: No | AZ74: W664763 | BA74: 0 | BC74: L12070 | BF74: S0362361
A75: W0682936 | B75: 10000 | C75: 10000 | D75: 45770 | E75: 502LAUGH | F75: 3:51:08 pm | G75: 10620258019 | I75: 1 | J75: Yes | K75: 79N | L75: PM21 | M75: 880 | P75: 45751 | R75: 264 | S75: 232320 | T75: PE | U75: 7FP00-80003-FT0001 | V75: 0 | W75: 200000 | X75: 32320 | Y75: 0 | Z75: 0 | AA75: 0 | AD75: 0 | AM75: 7FP00-80003-FT | AN75: H08031-JIM-M | AP75: 0 | AQ75: 0 | AR75: 0 | AS75: 0 | AT75: 0 | AU75: 0 | AY75: No | AZ75: W665450 | BA75: 0 | BC75: H08031-JIM-M | BF75: S0362373
A76: W0682937 | B76: 10000 | C76: 10000 | D76: 45755 | E76: 502LAUGH | F76: 1:07:24 pm | G76: D008O15421525 | I76: 1 | J76: Yes | K76: 79N | L76: PM21 | M76: 1700 | P76: 45751 | R76: 15 | S76: 25500 | T76: PE | U76: 1VV02-80009-FT0001 | V76: 0 | W76: 20000 | X76: 5500 | Y76: 0 | Z76: 0 | AA76: 0 | AD76: 0 | AM76: 1VV02-80009-FT | AN76: H08031-JIM-M | AP76: 0 | AQ76: 0 | AR76: 0 | AS76: 0 | AT76: 0 | AU76: 0 | AY76: No | AZ76: W664771 | BA76: 0 | BC76: H08031-JIM-M | BF76: S0362374
A77: W0682950 | B77: 10000 | C77: 10000 | D77: 45755 | E77: 502LAUGH | F77: 8:36:36 am | G77: 10620258020 | I77: 1 | J77: Yes | K77: 79N | L77: PM21 | M77: 500 | P77: 45751 | R77: 660 | S77: 330000 | T77: PE | U77: M0H50-80022-FT0001 | V77: 0 | W77: 280000 | X77: 50000 | Y77: 0 | Z77: 0 | AA77: 0 | AD77: 0 | AM77: M0H50-80022-FT | AN77: H08031-JIM-M | AP77: 0 | AQ77: 0 | AR77: 0 | AS77: 0 | AT77: 0 | AU77: 0 | AY77: No | AZ77: W665195 | BA77: 0 | BC77: H08031-JIM-M | BF77: S0362388
A78: W0682972 | B78: 10000 | C78: 10000 | D78: 45763 | E78: 502LAUGH | F78: 9:12:23 am | G78: BZC064-11 | I78: 1 | J78: Yes | K78: 93N | L78: PC02 | M78: 4585 | P78: 45751 | R78: 24 | S78: 110040 | T78: PE | U78: CHAMP SQ-WHITE0001 | V78: 0 | W78: 100000 | X78: 10040 | Y78: 0 | Z78: 0 | AA78: 0 | AD78: 0 | AM78: CHAMP SQ-WHITE | AN78: E05203 | AP78: 0 | AQ78: 0 | AR78: 0 | AS78: 0 | AT78: 0 | AU78: 0 | AY78: No | AZ78: W665946 | BA78: 0 | BC78: E05203 | BF78: S0362394
A79: W0682978 | B79: 10000 | C79: 10000 | D79: 45755 | E79: 502LAUGH | F79: 5:45:42 pm | G79: 3113015U5 | I79: 1 | J79: Yes | K79: 88 | L79: PP24 | M79: 2800 | P79: 45751 | R79: 2 | S79: 5600 | T79: PE | U79: MVCTS-BKAOYWS-220001 | V79: 0 | W79: 5000 | X79: 600 | Y79: 0 | Z79: 0 | AA79: 0 | AD79: 0 | AM79: MVCTS-BKAOYWS-22MM | AN79: A01490 | AP79: 0 | AQ79: 0 | AR79: 0 | AS79: 0 | AT79: 0 | AU79: 0 | AY79: No | AZ79: W664777 | BA79: 0 | BC79: A01490 | BF79: S0362396
A80: W0682983 | B80: 10000 | C80: 10000 | D80: 45754 | E80: 502LAUGH | F80: 8:56:52 am | G80: E190912129 | I80: 1 | J80: Yes | K80: 63 | L80: PM80 | M80: 6000 | P80: 45751 | R80: 60 | S80: 360000 | T80: PE | U80: 709898812-3M66900001 | V80: 0 | W80: 360000 | X80: 0 | Y80: 0 | Z80: 0 | AA80: 0 | AD80: 0 | AM80: 709898812-3M6690SP | AN80: S19314 | AP80: 0 | AQ80: 0 | AR80: 0 | AS80: 0 | AT80: 0 | AU80: 0 | AY80: No | AZ80: W664781 | BA80: 0 | BC80: S19314 | BF80: H0064932
A81: W0682996 | B81: 10000 | C81: 10000 | D81: 45754 | E81: 502LAUGH | F81: 8:56:52 am | G81: 8613409 | I81: 1 | J81: Yes | K81: 63 | L81: PM80 | M81: 1334 | P81: 45751 | R81: 60 | S81: 80040 | T81: PE | U81: 740921700-32PC E0001 | V81: 0 | W81: 80000 | X81: 40 | Y81: 0 | Z81: 0 | AA81: 0 | AD81: 0 | AM81: 740921700-32PC EMPTY | AN81: S19314 | AP81: 0 | AQ81: 0 | AR81: 0 | AS81: 0 | AT81: 0 | AU81: 0 | AY81: No | AZ81: W664790 | BA81: 0 | BC81: S19314 | BF81: H0064945
A82: W0682999 | B82: 10000 | C82: 10000 | D82: 45755 | E82: 502LAUGH | F82: 8:54:43 am | G82: 1006323 | I82: 1 | J82: Yes | K82: 63 | L82: PM80 | M82: 1600 | P82: 45751 | R82: 50 | S82: 80000 | T82: PE | U82: 709898802-EL93160001 | V82: 0 | W82: 80000 | X82: 0 | Y82: 0 | Z82: 0 | AA82: 0 | AD82: 0 | AM82: 709898802-EL93164 | AN82: S19081-TH | AP82: 0 | AQ82: 0 | AR82: 0 | AS82: 0 | AT82: 0 | AU82: 0 | AY82: No | AZ82: W664793 | BA82: 0 | BC82: S19081-TH | BF82: H0064948
A83: W0683002 | B83: 10000 | C83: 10000 | D83: 45756 | E83: 502LAUGH | F83: 0.44246528 | G83: 17190809009 | I83: 1 | J83: Yes | K83: 68 | L83: PM63 | M83: 15000 | P83: 45751 | R83: 2 | S83: 30000 | T83: PE | U83: 719007600 REVA0001 | V83: 0 | W83: 30000 | X83: 0 | Y83: 0 | Z83: 0 | AA83: 0 | AD83: 0 | AM83: 719007600 REVA | AN83: S19081-TH | AP83: 0 | AQ83: 0 | AR83: 0 | AS83: 0 | AT83: 0 | AU83: 0 | AY83: No | AZ83: W664795 | BA83: 0 | BC83: S19081-TH | BF83: H0064951
A84: W0683091 | B84: 10000 | C84: 10000 | D84: 45755 | E84: 502LAUGH | F84: 8:43:54 am | G84: U4A043S213/3082510U9 | I84: 1 | J84: Yes | K84: 88 | L84: PP24 | M84: 800 | P84: 45751 | R84: 1 | S84: 800 | T84: PE | U84: 107156130001 | V84: 0 | W84: 500 | X84: 300 | Y84: 0 | Z84: 0 | AA84: 0 | AD84: 0 | AM84: 10715613 | AN84: I09109 | AP84: 0 | AQ84: 0 | AR84: 0 | AS84: 0 | AT84: 0 | AU84: 0 | AY84: No | AZ84: W664819 | BA84: 0 | BC84: I09109 | BF84: S0362454

Sheet 05-Apr
A1: Production Output
A2: Filter: Date Completed: 05/04/25
A4: Work Order No. | B4: Work Order Line No. | C4: WO Journal Line No. | D4: Add Date | E4: Add User | F4: Add Time | G4: Material Batch No. | H4: Die Cut | I4: Process No. | J4: Posted | K4: Machine Code | L4: Staff Code | M4: No. of Press | N4: Date Started | O4: Time Started | P4: Date Completed | Q4: Time Completed | R4: No. of Ups | S4: Printed Quantity | T4: Journal Type | U4: Item Code | V4: Quantity | W4: QC Approved Quantity | X4: Rejected Quantity | Y4: Roll | Z4: Length | AA4: Width | AB4: Length UOM | AC4: Width UOM | AD4: RM Quantity | AE4: Material Code | AF4: Variant Code | AG4: Request Delivery Date | AH4: Non QC Record | AI4: Link to Line No. | AJ4: Related | AK4: Expire Date | AL4: Label Remark | AM4: Customer Part Number | AN4: Customer Code | AO4: ddmm | AP4: Label Packing Quantity 1 | AQ4: Label Quantity 1 | AR4: Label Packing Quantity 2 | AS4: Label Quantity 2 | AT4: Label Packing Quantity 3 | AU4: Label Quantity 3 | AV4: UOM for Label Printing | AW4: QC Inspector | AX4: Summarised Period | AY4: Summarised | AZ4: Posted Work Order No. | BA4: Colour | BB4: Currency | BC4: Ref Customer | BD4: Group | BE4: PO | BF4: Source Doc. No.
A5: W0678401 | B5: 10000 | C5: 10000 | D5: 45754 | E5: 505KANGHS | F5: 8:50:35 am | G5: SG-5650696 | I5: 1 | J5: Yes | K5: 73 | L5: PM59 | M5: 30000 | P5: 45752 | R5: 12 | S5: 360000 | T5: PE | U5: 80256220001 | V5: 0 | W5: 360000 | X5: 0 | Y5: 0 | Z5: 0 | AA5: 0 | AD5: 0 | AM5: 8025622 | AN5: B02083 | AP5: 0 | AQ5: 0 | AR5: 0 | AS5: 0 | AT5: 0 | AU5: 0 | AY5: No | AZ5: W664486 | BA5: 0 | BC5: B02083 | BF5: S0357138
A6: W0678401 | B6: 10000 | C6: 20000 | D6: 45754 | E6: 505KANGHS | F6: 8:50:35 am | G6: SG-5650696 | I6: 1 | J6: Yes | K6: 73N | L6: PM18 | M6: 6000 | P6: 45752 | R6: 12 | S6: 72000 | T6: PE | U6: 80256220001 | V6: 0 | W6: 72000 | X6: 0 | Y6: 0 | Z6: 0 | AA6: 0 | AD6: 0 | AM6: 8025622 | AN6: B02083 | AP6: 0 | AQ6: 0 | AR6: 0 | AS6: 0 | AT6: 0 | AU6: 0 | AY6: No | AZ6: W664486 | BA6: 0 | BC6: B02083 | BF6: S0357138
A7: W0678733 | B7: 10000 | C7: 30000 | D7: 45754 | E7: 502LAUGH | F7: 8:49:41 am | G7: M0BU23510990/BOBVG9280 | I7: 1 | J7: Yes | K7: 86 | L7: PS96 | M7: 7500 | P7: 45752 | R7: 4 | S7: 30000 | T7: PE | U7: 10028345001 REVA0001 | V7: 0 | W7: 30000 | X7: 0 | Y7: 0 | Z7: 0 | AA7: 0 | AD7: 0 | AM7: 10028345001 REVA | AN7: E05166-JAPAC | AP7: 0 | AQ7: 0 | AR7: 0 | AS7: 0 | AT7: 0 | AU7: 0 | AY7: No | AZ7: W664488 | BA7: 0 | BC7: E05166-JAPAC | BF7: S0357484
A8: W0679624 | B8: 10000 | C8: 30000 | D8: 45755 | E8: 502LAUGH | F8: 8:53:34 am | G8: E04OB9810 | I8: 2 | J8: Yes | K8: 62 | L8: PM75 | M8: 35000 | P8: 45752 | R8: 1 | S8: 35000 | T8: PE | U8: Y00-0000928-000001 | V8: 0 | W8: 35000 | X8: 0 | Y8: 0 | Z8: 0 | AA8: 0 | AD8: 0 | AM8: 300-0000396-00 | AN8: F06170-JIANGSU | AP8: 0 | AQ8: 0 | AR8: 0 | AS8: 0 | AT8: 0 | AU8: 0 | AY8: No | AZ8: W664495 | BA8: 0 | BC8: F06170-JIANGSU | BF8: S0358339
A9: W0680983 | B9: 20000 | C9: 30000 | D9: 45758 | E9: 502LAUGH | F9: 9:12:17 am | G9: WO2024/5284/1010831/XHX24911A1407/XHX2412190201/80117500 | I9: 1 | J9: Yes | K9: 103N | L9: PM41 | M9: 45000 | P9: 45752 | R9: 8 | S9: 360000 | T9: PE | U9: MT273730001 | V9: 0 | W9: 360000 | X9: 0 | Y9: 0 | Z9: 0 | AA9: 0 | AD9: 0 | AM9: MT27373 | AN9: Z26002 | AP9: 0 | AQ9: 0 | AR9: 0 | AS9: 0 | AT9: 0 | AU9: 0 | AY9: No | AZ9: W664507 | BA9: 0 | BC9: Z26002 | BF9: S0360896
A10: W0681118 | B10: 10000 | C10: 20000 | D10: 45754 | E10: 502LAUGH | F10: 8:41:10 am | G10: U522458002 | I10: 2 | J10: Yes | K10: 60 | L10: PM30 | M10: 4500 | P10: 45752 | R10: 1 | S10: 4500 | T10: PE | U10: 250-0412-000001 | V10: 0 | W10: 3000 | X10: 1500 | Y10: 0 | Z10: 0 | AA10: 0 | AD10: 0 | AM10: 250-0412-00 | AN10: J10025 | AP10: 0 | AQ10: 0 | AR10: 0 | AS10: 0 | AT10: 0 | AU10: 0 | AY10: No | AZ10: W664515 | BA10: 0 | BC10: J10025 | BF10: S0361009
A11: W0681338 | B11: 10000 | C11: 10000 | D11: 45754 | E11: 502LAUGH | F11: 8:40:07 am | G11: J00VB7941 | I11: 1 | J11: Yes | K11: 46 | L11: PS66 | M11: 1000 | P11: 45752 | R11: 1 | S11: 1000 | T11: PE | U11: 260-5378-000001 | V11: 0 | W11: 1000 | X11: 0 | Y11: 0 | Z11: 0 | AA11: 0 | AD11: 0 | AM11: 260-5378-00 | AN11: J10025 | AP11: 0 | AQ11: 0 | AR11: 0 | AS11: 0 | AT11: 0 | AU11: 0 | AY11: No | AZ11: W664092 | BA11: 0 | BC11: J10025 | BF11: S0361089
A12: W0681341 | B12: 10000 | C12: 10000 | D12: 45754 | E12: 505KANGHS | F12: 8:49:39 am | G12: 4112304U5A | I12: 1 | J12: Yes | K12: 46 | L12: PS66 | M12: 3000 | P12: 45752 | R12: 1 | S12: 3000 | T12: PE | U12: 260-6472-000001 | V12: 0 | W12: 3000 | X12: 0 | Y12: 0 | Z12: 0 | AA12: 0 | AD12: 0 | AM12: 260-6472-00 | AN12: J10025 | AP12: 0 | AQ12: 0 | AR12: 0 | AS12: 0 | AT12: 0 | AU12: 0 | AY12: No | AZ12: W664525 | BA12: 0 | BC12: J10025 | BF12: S0361089
A13: W0681471 | B13: 10000 | C13: 20000 | D13: 45754 | E13: 502LAUGH | F13: 8:43:38 am | G13: 4101908U5A | I13: 1 | J13: Yes | K13: 12 | L13: PM26 | M13: 3000 | P13: 45752 | R13: 1 | S13: 3000 | T13: PE | U13: 250-6223-000001 | V13: 0 | W13: 3000 | X13: 0 | Y13: 0 | Z13: 0 | AA13: 0 | AD13: 0 | AM13: 250-6223-00 | AN13: J10025 | AP13: 0 | AQ13: 0 | AR13: 0 | AS13: 0 | AT13: 0 | AU13: 0 | AY13: No | AZ13: W664533 | BA13: 0 | BC13: J10025 | BF13: S0361174
A14: W0681522 | B14: 10000 | C14: 50000 | D14: 45754 | E14: 502LAUGH | F14: 8:45:10 am | G14: D006O6500 | I14: 3 | J14: Yes | K14: 91 | L14: QM54 | M14: 66667 | P14: 45752 | R14: 3 | S14: 200001 | T14: PE | U14: 1VV21-80021-FT0001 | V14: 0 | W14: 185000 | X14: 15001 | Y14: 0 | Z14: 0 | AA14: 0 | AD14: 0 | AM14: 1VV21-80021-FT | AN14: H08031-JIM-M | AP14: 0 | AQ14: 0 | AR14: 0 | AS14: 0 | AT14: 0 | AU14: 0 | AY14: No | AZ14: W664540 | BA14: 0 | BC14: H08031-JIM-M | BF14: S0361189
A15: W0681698 | B15: 10000 | C15: 10000 | D15: 45754 | E15: 502LAUGH | F15: 8:52:04 am | G15: M0BTQ4840 | I15: 1 | J15: Yes | K15: 94 | L15: PM09 | M15: 167 | P15: 45752 | R15: 6 | S15: 1002 | T15: PE | U15: L001-773057-00000003 | V15: 0 | W15: 1000 | X15: 2 | Y15: 0 | Z15: 0 | AA15: 0 | AD15: 0 | AM15: L001-773057-000003CM | AN15: X24001-WD-SUZHOU | AP15: 0 | AQ15: 0 | AR15: 0 | AS15: 0 | AT15: 0 | AU15: 0 | AY15: No | AZ15: W664551 | BA15: 0 | BC15: X24001-WD-SUZHOU | BF15: S0361288
A16: W0681703 | B16: 10000 | C16: 10000 | D16: 45754 | E16: 505KANGHS | F16: 8:46:43 am | G16: 4103001U5 | I16: 1 | J16: Yes | K16: 94 | L16: PM09 | M16: 500 | P16: 45752 | R16: 4 | S16: 2000 | T16: PE | U16: 0B49096 REVAA0001 | V16: 0 | W16: 2000 | X16: 0 | Y16: 0 | Z16: 0 | AA16: 0 | AD16: 0 | AM16: 0B49096 REVAA | AN16: X24001-WD-SUZHOU | AP16: 0 | AQ16: 0 | AR16: 0 | AS16: 0 | AT16: 0 | AU16: 0 | AY16: No | AZ16: W664553 | BA16: 0 | BC16: X24001-WD-SUZHOU | BF16: S0361288
A17: W0681704 | B17: 10000 | C17: 10000 | D17: 45754 | E17: 502LAUGH | F17: 8:37:42 am | G17: 4103001U5 | I17: 1 | J17: Yes | K17: 94 | L17: PM09 | M17: 500 | P17: 45752 | R17: 4 | S17: 2000 | T17: PE | U17: 0B49097 REVAA0001 | V17: 0 | W17: 1000 | X17: 1000 | Y17: 0 | Z17: 0 | AA17: 0 | AD17: 0 | AM17: 0B49097 REVAA | AN17: X24001-WD-SUZHOU | AP17: 0 | AQ17: 0 | AR17: 0 | AS17: 0 | AT17: 0 | AU17: 0 | AY17: No | AZ17: W664554 | BA17: 0 | BC17: X24001-WD-SUZHOU | BF17: S0361288
A18: W0681705 | B18: 10000 | C18: 10000 | D18: 45754 | E18: 502LAUGH | F18: 8:37:42 am | G18: 4103005U5A | I18: 1 | J18: Yes | K18: 94 | L18: PM09 | M18: 500 | P18: 45752 | R18: 4 | S18: 2000 | T18: PE | U18: 0B49099 REVAA0001 | V18: 0 | W18: 2000 | X18: 0 | Y18: 0 | Z18: 0 | AA18: 0 | AD18: 0 | AM18: 0B49099 REVAA | AN18: X24001-WD-SUZHOU | AP18: 0 | AQ18: 0 | AR18: 0 | AS18: 0 | AT18: 0 | AU18: 0 | AY18: No | AZ18: W664555 | BA18: 0 | BC18: X24001-WD-SUZHOU | BF18: S0361288
A19: W0681706 | B19: 10000 | C19: 10000 | D19: 45754 | E19: 502LAUGH | F19: 8:37:42 am | G19: 4103005U5A | I19: 1 | J19: Yes | K19: 94 | L19: PM09 | M19: 500 | P19: 45752 | R19: 4 | S19: 2000 | T19: PE | U19: 0B49100 REVAA0001 | V19: 0 | W19: 2000 | X19: 0 | Y19: 0 | Z19: 0 | AA19: 0 | AD19: 0 | AM19: 0B49100 REVAA | AN19: X24001-WD-SUZHOU | AP19: 0 | AQ19: 0 | AR19: 0 | AS19: 0 | AT19: 0 | AU19: 0 | AY19: No | AZ19: W664556 | BA19: 0 | BC19: X24001-WD-SUZHOU | BF19: S0361288
A20: W0681715 | B20: 10000 | C20: 10000 | D20: 45756 | E20: 502LAUGH | F20: 8:33:02 am | G20: SG-5650696 | I20: 1 | J20: Yes | K20: 73N | L20: PM18 | M20: 36000 | P20: 45752 | R20: 12 | S20: 432000 | T20: PE | U20: 80256220001 | V20: 0 | W20: 432000 | X20: 0 | Y20: 0 | Z20: 0 | AA20: 0 | AD20: 0 | AM20: 8025622 | AN20: B02083 | AP20: 0 | AQ20: 0 | AR20: 0 | AS20: 0 | AT20: 0 | AU20: 0 | AY20: No | AZ20: W664557 | BA20: 0 | BC20: B02083 | BF20: S0361297
A21: W0681767 | B21: 10000 | C21: 10000 | D21: 45755 | E21: 502LAUGH | F21: 5:10:20 pm | G21: J00TB1740 | I21: 1 | J21: Yes | K21: 102 | L21: PM61 | M21: 27000 | P21: 45752 | R21: 2 | S21: 54000 | T21: PE | U21: R001-410200001 | V21: 0 | W21: 54000 | X21: 0 | Y21: 0 | Z21: 0 | AA21: 0 | AD21: 0 | AM21: R001-41020 | AN21: R18131 | AP21: 0 | AQ21: 0 | AR21: 0 | AS21: 0 | AT21: 0 | AU21: 0 | AY21: No | AZ21: W664565 | BA21: 0 | BC21: R18131 | BF21: S0361344
A22: W0681895 | B22: 10000 | C22: 30000 | D22: 45754 | E22: 502LAUGH | F22: 8:47:11 am | G22: 10620258046 | I22: 3 | J22: Yes | K22: 85 | L22: QM78 | M22: 10000 | P22: 45752 | R22: 11 | S22: 110000 | T22: PE | U22: 3UB27-800030001 | V22: 0 | W22: 100000 | X22: 10000 | Y22: 0 | Z22: 0 | AA22: 0 | AD22: 0 | AM22: 3UB27-80003 | AN22: H08031-JIM-M | AP22: 0 | AQ22: 0 | AR22: 0 | AS22: 0 | AT22: 0 | AU22: 0 | AY22: No | AZ22: W664576 | BA22: 0 | BC22: H08031-JIM-M | BF22: S0361404
A23: W0681896 | B23: 10000 | C23: 30000 | D23: 45754 | E23: 502LAUGH | F23: 8:36:19 am | G23: 10620258046 | I23: 3 | J23: Yes | K23: 85 | L23: QM78 | M23: 10000 | P23: 45752 | R23: 11 | S23: 110000 | T23: PE | U23: 3YM83-800010001 | V23: 0 | W23: 100000 | X23: 10000 | Y23: 0 | Z23: 0 | AA23: 0 | AD23: 0 | AM23: 3YM83-80001 | AN23: H08031-JIM-M | AP23: 0 | AQ23: 0 | AR23: 0 | AS23: 0 | AT23: 0 | AU23: 0 | AY23: No | AZ23: W664577 | BA23: 0 | BC23: H08031-JIM-M | BF23: S0361405
A24: W0681897 | B24: 10000 | C24: 30000 | D24: 45754 | E24: 502LAUGH | F24: 8:35:07 am | G24: 10620258037 | I24: 3 | J24: Yes | K24: 85 | L24: QM78 | M24: 8000 | P24: 45752 | R24: 11 | S24: 88000 | T24: PE | U24: E5Z02-80008-FT0001 | V24: 0 | W24: 80000 | X24: 8000 | Y24: 0 | Z24: 0 | AA24: 0 | AD24: 0 | AM24: E5Z02-80008-FT | AN24: H08031-JIM-M | AP24: 0 | AQ24: 0 | AR24: 0 | AS24: 0 | AT24: 0 | AU24: 0 | AY24: No | AZ24: W664578 | BA24: 0 | BC24: H08031-JIM-M | BF24: S0361406
A25: W0681949 | B25: 10000 | C25: 10000 | D25: 45754 | E25: 502LAUGH | F25: 8:52:04 am | G25: 404123725/4092S1 | I25: 1 | J25: Yes | K25: 61 | L25: PM68 | M25: 1500 | P25: 45752 | R25: 1 | S25: 1500 | T25: PE | U25: CAL-PMS GREEN C0001 | V25: 0 | W25: 1500 | X25: 0 | Y25: 0 | Z25: 0 | AA25: 0 | AD25: 0 | AM25: CALIBRATION GREEN | AN25: S19186 | AP25: 0 | AQ25: 0 | AR25: 0 | AS25: 0 | AT25: 0 | AU25: 0 | AY25: No | AZ25: W664135 | BA25: 0 | BC25: S19186 | BF25: S0361430
A26: W0682015 | B26: 10000 | C26: 10000 | D26: 45755 | E26: 502LAUGH | F26: 8:56:39 am | G26: 5305412-03-02-08/5307412-02-01-01/5307412-01-05-08 | I26: 1 | J26: Yes | K26: 90N | L26: QC04 | M26: 14850 | P26: 45752 | R26: 2 | S26: 29700 | T26: PE | U26: 723852900-PROTO 0001 | V26: 0 | W26: 29700 | X26: 0 | Y26: 0 | Z26: 0 | AA26: 0 | AD26: 0 | AM26: 723852900-PROTO D | AN26: S19314 | AP26: 0 | AQ26: 0 | AR26: 0 | AS26: 0 | AT26: 0 | AU26: 0 | AY26: No | AZ26: W664590 | BA26: 0 | BC26: S19314 | BF26: H0064852
A27: W0682041 | B27: 10000 | C27: 30000 | D27: 45754 | E27: 502LAUGH | F27: 8:50:45 am | G27: 10620258046 | I27: 3 | J27: Yes | K27: 85 | L27: QM78 | M27: 10000 | P27: 45752 | R27: 11 | S27: 110000 | T27: PE | U27: T6M58-800040001 | V27: 0 | W27: 100000 | X27: 10000 | Y27: 0 | Z27: 0 | AA27: 0 | AD27: 0 | AM27: T6M58-80004 | AN27: H08031-JIM-M | AP27: 0 | AQ27: 0 | AR27: 0 | AS27: 0 | AT27: 0 | AU27: 0 | AY27: No | AZ27: W664591 | BA27: 0 | BC27: H08031-JIM-M | BF27: S0361539
A28: W0682096 | B28: 10000 | C28: 10000 | D28: 45755 | E28: 502LAUGH | F28: 8:59:03 am | G28: M0BFL2381 | I28: 1 | J28: Yes | K28: 78 | L28: PM84 | M28: 8000 | P28: 45752 | R28: 16 | S28: 128000 | T28: PE | U28: 714370201-ADS1360001 | V28: 0 | W28: 120000 | X28: 8000 | Y28: 0 | Z28: 0 | AA28: 0 | AD28: 0 | AM28: 714370201-ADS1366 | AN28: S19081-TH | AP28: 0 | AQ28: 0 | AR28: 0 | AS28: 0 | AT28: 0 | AU28: 0 | AY28: No | AZ28: W664595 | BA28: 0 | BC28: S19081-TH | BF28: H0064864
A29: W0682097 | B29: 10000 | C29: 10000 | D29: 45755 | E29: 502LAUGH | F29: 8:59:03 am | G29: M0BFL2381 | I29: 1 | J29: Yes | K29: 78 | L29: PM84 | M29: 8000 | P29: 45752 | R29: 16 | S29: 128000 | T29: PE | U29: 714370201-ADS1360001 | V29: 0 | W29: 120000 | X29: 8000 | Y29: 0 | Z29: 0 | AA29: 0 | AD29: 0 | AM29: 714370201-ADS1366 | AN29: S19081-TH | AP29: 0 | AQ29: 0 | AR29: 0 | AS29: 0 | AT29: 0 | AU29: 0 | AY29: No | AZ29: W664596 | BA29: 0 | BC29: S19081-TH | BF29: H0064865
A30: W0682098 | B30: 10000 | C30: 10000 | D30: 45755 | E30: 502LAUGH | F30: 8:59:03 am | G30: M0BFL2381 | I30: 1 | J30: Yes | K30: 78 | L30: PM84 | M30: 8000 | P30: 45752 | R30: 16 | S30: 128000 | T30: PE | U30: 714370201-ADS1360001 | V30: 0 | W30: 120000 | X30: 8000 | Y30: 0 | Z30: 0 | AA30: 0 | AD30: 0 | AM30: 714370201-ADS1366 | AN30: S19081-TH | AP30: 0 | AQ30: 0 | AR30: 0 | AS30: 0 | AT30: 0 | AU30: 0 | AY30: No | AZ30: W664597 | BA30: 0 | BC30: S19081-TH | BF30: H0064866
A31: W0682114 | B31: 10000 | C31: 30000 | D31: 45754 | E31: 502LAUGH | F31: 2:46:49 pm | G31: 10656256096 | I31: 3 | J31: Yes | K31: 85 | L31: QM78 | M31: 5455 | P31: 45752 | R31: 11 | S31: 60005 | T31: PE | U31: 3YM56-80009-FT0001 | V31: 0 | W31: 60000 | X31: 5 | Y31: 0 | Z31: 0 | AA31: 0 | AD31: 0 | AM31: 3YM56-80009-FT | AN31: H08031-JIM-M | AP31: 0 | AQ31: 0 | AR31: 0 | AS31: 0 | AT31: 0 | AU31: 0 | AY31: No | AZ31: W664602 | BA31: 0 | BC31: H08031-JIM-M | BF31: S0361568
A32: W0682115 | B32: 10000 | C32: 30000 | D32: 45754 | E32: 505KANGHS | F32: 8:45:08 am | G32: 10656256096 | I32: 3 | J32: Yes | K32: 85 | L32: QM78 | M32: 10000 | P32: 45752 | R32: 11 | S32: 110000 | T32: PE | U32: 3YM58-80010-FT0001 | V32: 0 | W32: 100000 | X32: 10000 | Y32: 0 | Z32: 0 | AA32: 0 | AD32: 0 | AM32: 3YM58-80010-FT | AN32: H08031-JIM-M | AP32: 0 | AQ32: 0 | AR32: 0 | AS32: 0 | AT32: 0 | AU32: 0 | AY32: No | AZ32: W664603 | BA32: 0 | BC32: H08031-JIM-M | BF32: S0361569
A33: W0682168 | B33: 10000 | C33: 10000 | D33: 45754 | E33: 505KANGHS | F33: 8:45:44 am | G33: SG-5644655 01 | I33: 1 | J33: Yes | K33: 59 | L33: PS74 | M33: 1000 | P33: 45752 | R33: 10 | S33: 10000 | T33: PE | U33: 112024330001 | V33: 0 | W33: 10000 | X33: 0 | Y33: 0 | Z33: 0 | AA33: 0 | AD33: 0 | AM33: 11202433 | AN33: I09180 | AP33: 0 | AQ33: 0 | AR33: 0 | AS33: 0 | AT33: 0 | AU33: 0 | AY33: No | AZ33: W664608 | BA33: 0 | BC33: I09180 | BF33: S0361669
A34: W0682168 | B34: 20000 | C34: 10000 | D34: 45754 | E34: 505KANGHS | F34: 8:45:44 am | G34: SG-5644655 01 | I34: 1 | J34: Yes | K34: 59 | L34: PS74 | M34: 1000 | P34: 45752 | R34: 10 | S34: 10000 | T34: PE | U34: 112024330001 | V34: 0 | W34: 10000 | X34: 0 | Y34: 0 | Z34: 0 | AA34: 0 | AD34: 0 | AM34: 11202433 | AN34: I09180 | AP34: 0 | AQ34: 0 | AR34: 0 | AS34: 0 | AT34: 0 | AU34: 0 | AY34: No | AZ34: W664608 | BA34: 0 | BC34: I09180 | BF34: S0361669
A35: W0682178 | B35: 20000 | C35: 10000 | D35: 45754 | E35: 505KANGHS | F35: 8:49:39 am | G35: SG-5644655 01 | I35: 1 | J35: Yes | K35: 59 | L35: PS74 | M35: 800 | P35: 45752 | R35: 10 | S35: 8000 | T35: PE | U35: 112063620001 | V35: 0 | W35: 4000 | X35: 4000 | Y35: 0 | Z35: 0 | AA35: 0 | AD35: 0 | AM35: 11206362 | AN35: I09180 | AP35: 0 | AQ35: 0 | AR35: 0 | AS35: 0 | AT35: 0 | AU35: 0 | AY35: No | AZ35: W664611 | BA35: 0 | BC35: I09180 | BF35: S0361679
A36: W0682178 | B36: 30000 | C36: 10000 | D36: 45754 | E36: 505KANGHS | F36: 8:49:39 am | G36: SG-5644655 01 | I36: 1 | J36: Yes | K36: 59 | L36: PS74 | M36: 200 | P36: 45752 | R36: 10 | S36: 2000 | T36: PE | U36: 112063620001 | V36: 0 | W36: 2000 | X36: 0 | Y36: 0 | Z36: 0 | AA36: 0 | AD36: 0 | AM36: 11206362 | AN36: I09180 | AP36: 0 | AQ36: 0 | AR36: 0 | AS36: 0 | AT36: 0 | AU36: 0 | AY36: No | AZ36: W664611 | BA36: 0 | BC36: I09180 | BF36: S0361679
A37: W0682180 | B37: 10000 | C37: 10000 | D37: 45754 | E37: 502LAUGH | F37: 8:40:07 am | G37: SG-5644655 01 | I37: 1 | J37: Yes | K37: 59 | L37: PS74 | M37: 400 | P37: 45752 | R37: 10 | S37: 4000 | T37: PE | U37: 112024250001 | V37: 0 | W37: 4000 | X37: 0 | Y37: 0 | Z37: 0 | AA37: 0 | AD37: 0 | AM37: 11202425 | AN37: I09180 | AP37: 0 | AQ37: 0 | AR37: 0 | AS37: 0 | AT37: 0 | AU37: 0 | AY37: No | AZ37: W664612 | BA37: 0 | BC37: I09180 | BF37: S0361681
A38: W0682180 | B38: 20000 | C38: 10000 | D38: 45754 | E38: 502LAUGH | F38: 8:40:07 am | G38: SG-5644655 01 | I38: 1 | J38: Yes | K38: 59 | L38: PS74 | M38: 400 | P38: 45752 | R38: 10 | S38: 4000 | T38: PE | U38: 112024250001 | V38: 0 | W38: 4000 | X38: 0 | Y38: 0 | Z38: 0 | AA38: 0 | AD38: 0 | AM38: 11202425 | AN38: I09180 | AP38: 0 | AQ38: 0 | AR38: 0 | AS38: 0 | AT38: 0 | AU38: 0 | AY38: No | AZ38: W664612 | BA38: 0 | BC38: I09180 | BF38: S0361681
A39: W0682205 | B39: 10000 | C39: 10000 | D39: 45754 | E39: 505KANGHS | F39: 8:48:20 am | G39: S-5644655 01 | I39: 1 | J39: Yes | K39: 59 | L39: PS74 | M39: 400 | P39: 45752 | R39: 10 | S39: 4000 | T39: PE | U39: 112063620001 | V39: 0 | W39: 4000 | X39: 0 | Y39: 0 | Z39: 0 | AA39: 0 | AD39: 0 | AM39: 11206362 | AN39: I09180 | AP39: 0 | AQ39: 0 | AR39: 0 | AS39: 0 | AT39: 0 | AU39: 0 | AY39: No | AZ39: W664613 | BA39: 0 | BC39: I09180 | BF39: S0361699
A40: W0682227 | B40: 10000 | C40: 10000 | D40: 45755 | E40: 502LAUGH | F40: 8:43:10 am | G40: 2087S1 | I40: 1 | J40: Yes | K40: 60 | L40: PM30 | M40: 3000 | P40: 45752 | R40: 1 | S40: 3000 | T40: PE | U40: SECURITY-30X80-70002 | V40: 0 | W40: 3000 | X40: 0 | Y40: 0 | Z40: 0 | AA40: 0 | AD40: 0 | AM40: SECURITY-30X80-7872 | AN40: S19557 | AP40: 0 | AQ40: 0 | AR40: 0 | AS40: 0 | AT40: 0 | AU40: 0 | AY40: No | AZ40: W664617 | BA40: 0 | BC40: S19557 | BF40: S0361709
A41: W0682320 | B41: 10000 | C41: 10000 | D41: 45755 | E41: 502LAUGH | F41: 8:39:38 am | G41: I53065H056 | I41: 1 | J41: Yes | K41: 72 | L41: PMJ4 | M41: 9500 | P41: 45752 | R41: 6 | S41: 57000 | T41: PE | U41: 068657 REV4000001 | V41: 0 | W41: 50000 | X41: 7000 | Y41: 0 | Z41: 0 | AA41: 0 | AD41: 0 | AM41: 068657 REV400 | AN41: V22000-DE | AP41: 0 | AQ41: 0 | AR41: 0 | AS41: 0 | AT41: 0 | AU41: 0 | AY41: No | AZ41: W664629 | BA41: 0 | BC41: V22000-DE | BF41: S0361787
A42: W0682399 | B42: 10000 | C42: 10000 | D42: 45769 | E42: 502LAUGH | F42: 9:58:16 am | G42: 10620258014/10620258013/10620258019 | I42: 1 | J42: Yes | K42: 79 | L42: PM17 | M42: 3594 | P42: 45752 | R42: 32 | S42: 115008 | T42: PE | U42: CZ103-80022-FT0001 | V42: 0 | W42: 100000 | X42: 15008 | Y42: 0 | Z42: 0 | AA42: 0 | AD42: 0 | AM42: CZ103-80022-FT | AN42: H08031-JIM-M | AP42: 0 | AQ42: 0 | AR42: 0 | AS42: 0 | AT42: 0 | AU42: 0 | AY42: No | AZ42: W665433 | BA42: 0 | BC42: H08031-JIM-M | BF42: S0361877
A43: W0682408 | B43: 10000 | C43: 10000 | D43: 45754 | E43: 505KANGHS | F43: 8:48:20 am | G43: 502190692 | I43: 1 | J43: Yes | K43: 22 | L43: PS13 | M43: 10000 | P43: 45752 | R43: 1 | S43: 10000 | T43: PE | U43: WAT0062770001 | V43: 0 | W43: 10000 | X43: 0 | Y43: 0 | Z43: 0 | AA43: 0 | AD43: 0 | AM43: WAT006277 | AN43: G07042 | AP43: 0 | AQ43: 0 | AR43: 0 | AS43: 0 | AT43: 0 | AU43: 0 | AY43: No | AZ43: W664637 | BA43: 0 | BC43: G07042 | BF43: S0361887
A44: W0682422 | B44: 10000 | C44: 10000 | D44: 45769 | E44: 502LAUGH | F44: 9:59:23 am | G44: 10620258014/10620258013/10620258019 | I44: 1 | J44: Yes | K44: 79 | L44: PM17 | M44: 3594 | P44: 45752 | R44: 64 | S44: 230016 | T44: PE | U44: C2P04-80053-FT0001 | V44: 0 | W44: 200000 | X44: 30016 | Y44: 0 | Z44: 0 | AA44: 0 | AD44: 0 | AM44: C2P04-80053-FT | AN44: H08031-JIM-M | AP44: 0 | AQ44: 0 | AR44: 0 | AS44: 0 | AT44: 0 | AU44: 0 | AY44: No | AZ44: W665279 | BA44: 0 | BC44: H08031-JIM-M | BF44: S0361899
A45: W0682482 | B45: 10000 | C45: 10000 | D45: 45755 | E45: 502LAUGH | F45: 9:57:39 am | G45: I53065H056 | I45: 1 | J45: Yes | K45: 72 | L45: PMJ4 | M45: 4000 | P45: 45752 | R45: 6 | S45: 24000 | T45: PE | U45: FLAMMABLE LIQUID0015 | V45: 0 | W45: 20000 | X45: 4000 | Y45: 0 | Z45: 0 | AA45: 0 | AD45: 0 | AM45: FLAMMABLE LIQUID 3 | AN45: S19254 | AP45: 0 | AQ45: 0 | AR45: 0 | AS45: 0 | AT45: 0 | AU45: 0 | AY45: No | AZ45: W664659 | BA45: 0 | BC45: S19254 | BF45: S0361923
A46: W0682515 | B46: 10000 | C46: 10000 | D46: 45755 | E46: 502LAUGH | F46: 1:10:12 pm | G46: 4112210U5/H00004158/4005U7005/U3071S041 | I46: 1 | J46: Yes | K46: 60 | L46: PM30 | M46: 2000 | P46: 45752 | R46: 1 | S46: 2000 | T46: PE | U46: STICK4016700330001 | V46: 0 | W46: 2000 | X46: 0 | Y46: 0 | Z46: 0 | AA46: 0 | AD46: 0 | AM46: STICK401670033 | AN46: T20096 | AP46: 0 | AQ46: 0 | AR46: 0 | AS46: 0 | AT46: 0 | AU46: 0 | AY46: No | AZ46: W664667 | BA46: 0 | BC46: T20096 | BF46: S0361936
A47: W0682515 | B47: 10000 | C47: 20000 | D47: 45755 | E47: 502LAUGH | F47: 1:10:12 pm | G47: 4112210U5/H00004158/4005U7005/U3071S041 | I47: 2 | J47: Yes | K47: 61 | L47: PM68 | M47: 1000 | P47: 45752 | R47: 2 | S47: 2000 | T47: PE | U47: STICK4016700330001 | V47: 0 | W47: 2000 | X47: 0 | Y47: 0 | Z47: 0 | AA47: 0 | AD47: 0 | AM47: STICK401670033 | AN47: T20096 | AP47: 0 | AQ47: 0 | AR47: 0 | AS47: 0 | AT47: 0 | AU47: 0 | AY47: No | AZ47: W664667 | BA47: 0 | BC47: T20096 | BF47: S0361936
A48: W0682524 | B48: 10000 | C48: 10000 | D48: 45755 | E48: 502LAUGH | F48: 9:58:58 am | G48: SG-5649983 01 | I48: 1 | J48: Yes | K48: 72 | L48: PMJ4 | M48: 2250 | P48: 45752 | R48: 4 | S48: 9000 | T48: PE | U48: QC PASSED LABEL0004 | V48: 0 | W48: 5000 | X48: 4000 | Y48: 0 | Z48: 0 | AA48: 0 | AD48: 0 | AM48: QC PASSED LABEL | AN48: A01471 | AP48: 0 | AQ48: 0 | AR48: 0 | AS48: 0 | AT48: 0 | AU48: 0 | AY48: No | AZ48: W664669 | BA48: 0 | BC48: A01471 | BF48: S0361941
A49: W0682529 | B49: 10000 | C49: 20000 | D49: 45754 | E49: 505KANGHS | F49: 1:54:41 pm | G49: BYK017-03 | I49: 2 | J49: Yes | K49: 100 | L49: PM87 | M49: 2400 | P49: 45752 | R49: 1 | S49: 2400 | T49: PE | U49: ARROW UP-70X100M0001 | V49: 0 | W49: 1800 | X49: 600 | Y49: 0 | Z49: 0 | AA49: 0 | AD49: 0 | AM49: ARROW UP-70X100MM | AN49: A01409 | AP49: 0 | AQ49: 0 | AR49: 0 | AS49: 0 | AT49: 0 | AU49: 0 | AY49: No | AZ49: W664672 | BA49: 0 | BC49: A01409 | BF49: S0361945
A50: W0682536 | B50: 10000 | C50: 30000 | D50: 45772 | E50: 502LAUGH | F50: 5:53:32 pm | G50: D008O0591/D008O0561 | I50: 2 | J50: Yes | K50: 77 | L50: PM74 | M50: 35550 | P50: 45752 | R50: 6 | S50: 213300 | T50: PE | U50: 1VV24-80029-FT0001 | V50: 0 | W50: 200000 | X50: 13300 | Y50: 0 | Z50: 0 | AA50: 0 | AD50: 0 | AM50: 1VV24-80029-FT | AN50: H08031-JIM-M | AP50: 0 | AQ50: 0 | AR50: 0 | AS50: 0 | AT50: 0 | AU50: 0 | AY50: No | AZ50: W665436 | BA50: 0 | BC50: H08031-JIM-M | BF50: S0361954
A51: W0682547 | B51: 10000 | C51: 10000 | D51: 45763 | E51: 502LAUGH | F51: 0.46974537 | G51: 10620258014/10620258013/10620258019 | I51: 1 | J51: Yes | K51: 79 | L51: PM17 | M51: 3594 | P51: 45752 | R51: 64 | S51: 230016 | T51: PE | U51: 3YM73-80008-FT0001 | V51: 0 | W51: 200000 | X51: 30016 | Y51: 0 | Z51: 0 | AA51: 0 | AD51: 0 | AM51: 3YM73-80008-FT | AN51: H08031-JIM-M | AP51: 0 | AQ51: 0 | AR51: 0 | AS51: 0 | AT51: 0 | AU51: 0 | AY51: No | AZ51: W665122 | BA51: 0 | BC51: H08031-JIM-M | BF51: S0361963
A52: W0682553 | B52: 10000 | C52: 10000 | D52: 45763 | E52: 502LAUGH | F52: 8:32:11 am | G52: 10620258014/10620258013/10620258019 | I52: 1 | J52: Yes | K52: 79 | L52: PM17 | M52: 3594 | P52: 45752 | R52: 32 | S52: 115008 | T52: PE | U52: 3YM81-80005-FT0001 | V52: 0 | W52: 100000 | X52: 15008 | Y52: 0 | Z52: 0 | AA52: 0 | AD52: 0 | AM52: 3YM81-80005-FT | AN52: H08031-JIM-M | AP52: 0 | AQ52: 0 | AR52: 0 | AS52: 0 | AT52: 0 | AU52: 0 | AY52: No | AZ52: W665123 | BA52: 0 | BC52: H08031-JIM-M | BF52: S0361967
A53: W0682602 | B53: 10000 | C53: 10000 | D53: 45754 | E53: 505KANGHS | F53: 8:48:20 am | G53: S-5644655 01 | I53: 1 | J53: Yes | K53: 59 | L53: PS74 | M53: 600 | P53: 45752 | R53: 10 | S53: 6000 | T53: PE | U53: 200302680001 | V53: 0 | W53: 6000 | X53: 0 | Y53: 0 | Z53: 0 | AA53: 0 | AD53: 0 | AM53: 20030268 | AN53: I09180 | AP53: 0 | AQ53: 0 | AR53: 0 | AS53: 0 | AT53: 0 | AU53: 0 | AY53: No | AZ53: W664704 | BA53: 0 | BC53: I09180 | BF53: S0362005
A54: W0682602 | B54: 20000 | C54: 10000 | D54: 45754 | E54: 505KANGHS | F54: 8:48:20 am | G54: S-5644655 01 | I54: 1 | J54: Yes | K54: 59 | L54: PS74 | M54: 600 | P54: 45752 | R54: 10 | S54: 6000 | T54: PE | U54: 200302680001 | V54: 0 | W54: 6000 | X54: 0 | Y54: 0 | Z54: 0 | AA54: 0 | AD54: 0 | AM54: 20030268 | AN54: I09180 | AP54: 0 | AQ54: 0 | AR54: 0 | AS54: 0 | AT54: 0 | AU54: 0 | AY54: No | AZ54: W664704 | BA54: 0 | BC54: I09180 | BF54: S0362005
A55: W0682622 | B55: 10000 | C55: 20000 | D55: 45771 | E55: 502LAUGH | F55: 4:16:55 pm | G55: 10620258020 | I55: 2 | J55: Yes | K55: 77 | L55: PM74 | M55: 2598 | P55: 45752 | R55: 77 | S55: 200046 | T55: PE | U55: 7FP06-80001 REVB0001 | V55: 0 | W55: 200000 | X55: 46 | Y55: 0 | Z55: 0 | AA55: 0 | AD55: 0 | AM55: 7FP06-80001 REVB-FT | AN55: H08031-JIM-M | AP55: 0 | AQ55: 0 | AR55: 0 | AS55: 0 | AT55: 0 | AU55: 0 | AY55: No | AZ55: W665924 | BA55: 0 | BC55: H08031-JIM-M | BF55: S0362006
A56: W0682633 | B56: 10000 | C56: 10000 | D56: 45769 | E56: 502LAUGH | F56: 0.41800926 | G56: 10620258014/10620258013/10620258019 | I56: 1 | J56: Yes | K56: 79 | L56: PM17 | M56: 3594 | P56: 45752 | R56: 64 | S56: 230016 | T56: PE | U56: F6U66-80033-FT0001 | V56: 0 | W56: 200000 | X56: 30016 | Y56: 0 | Z56: 0 | AA56: 0 | AD56: 0 | AM56: F6U66-80033-FT | AN56: H08031-JIM-M | AP56: 0 | AQ56: 0 | AR56: 0 | AS56: 0 | AT56: 0 | AU56: 0 | AY56: No | AZ56: W665441 | BA56: 0 | BC56: H08031-JIM-M | BF56: S0362009
A57: W0682634 | B57: 10000 | C57: 10000 | D57: 45754 | E57: 502LAUGH | F57: 8:39:12 am | G57: SG-5644655 01 | I57: 1 | J57: Yes | K57: 59 | L57: PS74 | M57: 100 | P57: 45752 | R57: 10 | S57: 1000 | T57: PE | U57: 112024090001 | V57: 0 | W57: 1000 | X57: 0 | Y57: 0 | Z57: 0 | AA57: 0 | AD57: 0 | AM57: 11202409 | AN57: I09180 | AP57: 0 | AQ57: 0 | AR57: 0 | AS57: 0 | AT57: 0 | AU57: 0 | AY57: No | AZ57: W664706 | BA57: 0 | BC57: I09180 | BF57: S0362008
A58: W0682635 | B58: 10000 | C58: 10000 | D58: 45754 | E58: 502LAUGH | F58: 8:39:12 am | G58: SG-5644655 01 | I58: 1 | J58: Yes | K58: 59 | L58: PS74 | M58: 100 | P58: 45752 | R58: 10 | S58: 1000 | T58: PE | U58: 112024090001 | V58: 0 | W58: 1000 | X58: 0 | Y58: 0 | Z58: 0 | AA58: 0 | AD58: 0 | AM58: 11202409 | AN58: I09180 | AP58: 0 | AQ58: 0 | AR58: 0 | AS58: 0 | AT58: 0 | AU58: 0 | AY58: No | AZ58: W664707 | BA58: 0 | BC58: I09180 | BF58: S0362010
A59: W0682636 | B59: 10000 | C59: 10000 | D59: 45754 | E59: 505KANGHS | F59: 8:42:23 am | G59: SG-5644655 01 | I59: 1 | J59: Yes | K59: 59 | L59: PS74 | M59: 400 | P59: 45752 | R59: 10 | S59: 4000 | T59: PE | U59: 112023530001 | V59: 0 | W59: 4000 | X59: 0 | Y59: 0 | Z59: 0 | AA59: 0 | AD59: 0 | AM59: 11202353 | AN59: I09180 | AP59: 0 | AQ59: 0 | AR59: 0 | AS59: 0 | AT59: 0 | AU59: 0 | AY59: No | AZ59: W664708 | BA59: 0 | BC59: I09180 | BF59: S0362011
A60: W0682636 | B60: 20000 | C60: 10000 | D60: 45754 | E60: 505KANGHS | F60: 8:42:23 am | G60: SG-5644655 01 | I60: 1 | J60: Yes | K60: 59 | L60: PS74 | M60: 200 | P60: 45752 | R60: 10 | S60: 2000 | T60: PE | U60: 112023530001 | V60: 0 | W60: 2000 | X60: 0 | Y60: 0 | Z60: 0 | AA60: 0 | AD60: 0 | AM60: 11202353 | AN60: I09180 | AP60: 0 | AQ60: 0 | AR60: 0 | AS60: 0 | AT60: 0 | AU60: 0 | AY60: No | AZ60: W664708 | BA60: 0 | BC60: I09180 | BF60: S0362011
A61: W0682636 | B61: 30000 | C61: 10000 | D61: 45754 | E61: 505KANGHS | F61: 8:42:23 am | G61: SG-5644655 01 | I61: 1 | J61: Yes | K61: 59 | L61: PS74 | M61: 200 | P61: 45752 | R61: 10 | S61: 2000 | T61: PE | U61: 112023530001 | V61: 0 | W61: 2000 | X61: 0 | Y61: 0 | Z61: 0 | AA61: 0 | AD61: 0 | AM61: 11202353 | AN61: I09180 | AP61: 0 | AQ61: 0 | AR61: 0 | AS61: 0 | AT61: 0 | AU61: 0 | AY61: No | AZ61: W664708 | BA61: 0 | BC61: I09180 | BF61: S0362011
A62: W0682637 | B62: 10000 | C62: 10000 | D62: 45769 | E62: 502LAUGH | F62: 0.53510417 | G62: 10620258014/10620258013/10620258019/10620258017 | I62: 1 | J62: Yes | K62: 79 | L62: PM17 | M62: 3594 | P62: 45752 | R62: 32 | S62: 115008 | T62: PE | U62: N9K02-80017-FT0001 | V62: 0 | W62: 100000 | X62: 15008 | Y62: 0 | Z62: 0 | AA62: 0 | AD62: 0 | AM62: N9K02-80017-FT | AN62: H08031-JIM-M | AP62: 0 | AQ62: 0 | AR62: 0 | AS62: 0 | AT62: 0 | AU62: 0 | AY62: No | AZ62: W665185 | BA62: 0 | BC62: H08031-JIM-M | BF62: S0362013
A63: W0682638 | B63: 10000 | C63: 10000 | D63: 45769 | E63: 502LAUGH | F63: 0.41710648 | G63: 10620258014/10620258013/10620258019 | I63: 1 | J63: Yes | K63: 79 | L63: PM17 | M63: 3594 | P63: 45752 | R63: 32 | S63: 115008 | T63: PE | U63: N9K06-80021-FT0001 | V63: 0 | W63: 100000 | X63: 15008 | Y63: 0 | Z63: 0 | AA63: 0 | AD63: 0 | AM63: N9K06-80021-FT | AN63: H08031-JIM-M | AP63: 0 | AQ63: 0 | AR63: 0 | AS63: 0 | AT63: 0 | AU63: 0 | AY63: No | AZ63: W665281 | BA63: 0 | BC63: H08031-JIM-M | BF63: S0362014
A64: W0682645 | B64: 10000 | C64: 20000 | D64: 45754 | E64: 505KANGHS | F64: 8:43:58 am | G64: BYK017-03 | I64: 2 | J64: Yes | K64: 92 | L64: PM87 | M64: 2400 | P64: 45752 | R64: 1 | S64: 2400 | T64: PE | U64: GR-0870001 | V64: 0 | W64: 2000 | X64: 400 | Y64: 0 | Z64: 0 | AA64: 0 | AD64: 0 | AM64: GR-087 | AN64: G07076 | AP64: 0 | AQ64: 0 | AR64: 0 | AS64: 0 | AT64: 0 | AU64: 0 | AY64: No | AZ64: W664713 | BA64: 0 | BC64: G07076 | BF64: S0362012
A65: W0682681 | B65: 10000 | C65: 10000 | D65: 45755 | E65: 502LAUGH | F65: 8:59:03 am | G65: M0BFL2381 | I65: 1 | J65: Yes | K65: 78 | L65: PM84 | M65: 2750 | P65: 45752 | R65: 16 | S65: 44000 | T65: PE | U65: 714370201-ADS1360001 | V65: 0 | W65: 40000 | X65: 4000 | Y65: 0 | Z65: 0 | AA65: 0 | AD65: 0 | AM65: 714370201-ADS1366 | AN65: S19314 | AP65: 0 | AQ65: 0 | AR65: 0 | AS65: 0 | AT65: 0 | AU65: 0 | AY65: No | AZ65: W664738 | BA65: 0 | BC65: S19314 | BF65: H0064908
A66: W0682691 | B66: 10000 | C66: 10000 | D66: 45755 | E66: 502LAUGH | F66: 3:36:31 pm | G66: U4B0458049 | I66: 1 | J66: Yes | K66: 72 | L66: PMJ4 | M66: 4250 | P66: 45752 | R66: 8 | S66: 34000 | T66: PE | U66: 109-54003240001 | V66: 0 | W66: 30000 | X66: 4000 | Y66: 0 | Z66: 0 | AA66: 0 | AD66: 0 | AM66: 109-5400324 | AN66: K11180 | AP66: 0 | AQ66: 0 | AR66: 0 | AS66: 0 | AT66: 0 | AU66: 0 | AY66: No | AZ66: W664745 | BA66: 0 | BC66: K11180 | BF66: S0362026
A67: W0682804 | B67: 10000 | C67: 20000 | D67: 45755 | E67: 502LAUGH | F67: 2:17:24 pm | G67: BXC030-01 | I67: 2 | J67: Yes | K67: 92 | L67: PM87 | M67: 1500 | P67: 45752 | R67: 1 | S67: 1500 | T67: PE | U67: BMS-60X20MM0001 | V67: 0 | W67: 1000 | X67: 500 | Y67: 0 | Z67: 0 | AA67: 0 | AD67: 0 | AM67: BMS-60X20MM | AN67: S19671 | AP67: 0 | AQ67: 0 | AR67: 0 | AS67: 0 | AT67: 0 | AU67: 0 | AY67: No | AZ67: W664757 | BA67: 0 | BC67: S19671 | BF67: S0362169
